Workbook

Sheet 财务报表填写要求
A1: 财务报表填写要求
A2: 报表 | C2: 明细 | D2: 所属位置 | E2: 填写要求 | F2: 发表时间
A3: 每日登记 | B3: XX店财务报表 | C3: 收入汇总表 | D3: 收入汇总表!A1 | E3: 有公式自动计算，不允许手动更改 | F3: 每天下班前前台发送到财务邮箱
C4: 收据流水表 | D4: 收入流水表!A1 | E4: 1、根据真实情况填写，每一列都需要写清楚，与SASS后台系统保持一致（收据合约号必须按顺序填写，不允许跳号使用。） 2、填写日期格式与汇总保持表一致 3、收入类别从下拉框中勾选，不允许随意增加 4、对应实际情况，填写对应会籍和私教姓名（以最终成交为准）。
C5: 水吧销售明细表 | D5: 水吧销售明细表!A1 | E5: 早晚班只需要统计当天的销售数量（以瓶为单位，只写数字）， 收入和利润有公式可自动统计。
C6: 游泳装备销售明细表 | D6: 游泳装备销售明细表!A1 | E6: 早晚班只需要统计当天的销售数量（以件为单位，只写数字）， 收入和利润有公式可自动统计。
A7: 每周登记 | B7: 发票信息登记表 | C7: 发票信息登记表 | D7: 发票信息登记表!A1 | E7: 请核对需开票的会员真实性， 若当月会员未能领取的及时将发票退回财务部门。 | F7: 每周四晚下班前发送到财务邮箱
A8: 每月登记 | B8: 礼品盘点表 | C8: 礼品盘点表 | D8: 礼品盘点表!A1 | E8: 以公司实际采购、赠送来填写礼品当月的情况。 | F8: 次月1号下午发送到财务邮箱
B9: 固定资产盘点 | C9: 固定资产盘点表 | D9: 固定资产盘点表!A1 | E9: 以公司实际购入、报损来填写器械当月的情况。

Sheet 收入汇总表
A1: 2026年山道健身营业收入统计总表
B2: 主营业务 | I2: 其它业务 | N2: 当日收入 | O2: 付款方式 | S2: 当日现金情况 | V2: 备注
A3: 日期 | B3: 会籍收入 | C3: 私教收入 | D3: 教练班收入 | E3: 中国舞 | F3: 餐吧收入 | G3: 其他收入 | H3: 小计 | I3: 水吧收入 | J3: 游泳装备 | K3: 美团收入 | L3: 抖音收入 | M3: 小计 | N3: 合计 | O3: 微信 | P3: 支付宝 | Q3: POS | R3: 现金 | S3: 存入 | T3: 备用金 | U3: 经办人
A4: 46204 | B4: =SUMIFS(收入流水表!J:J,收入流水表!C:C,$B$3,收入流水表!A:A,A4) -> 3973 | C4: =SUMIFS(收入流水表!J:J,收入流水表!C:C,$C$3,收入流水表!A:A,A4) -> 0 | D4: =SUMIFS(收入流水表!J:J,收入流水表!C:C,$D$3,收入流水表!A:A,A4) -> 13640 | E4: =SUMIFS(收入流水表!J:J,收入流水表!C:C,$E$3,收入流水表!A:A,A4) -> 0 | F4: =SUMIFS(收入流水表!J:J,收入流水表!C:C,$F$3,收入流水表!A:A,A4) -> 0 | G4: =SUMIFS(收入流水表!J:J,收入流水表!C:C,$G$3,收入流水表!A:A,A4) -> 140 | H4: =SUM(B4:G4) -> 17753 | I4: =SUMIFS(收入流水表!J:J,收入流水表!C:C,$I$3,收入流水表!A:A,A4) -> 58 | J4: =SUMIFS(收入流水表!J:J,收入流水表!C:C,$J$3,收入流水表!A:A,A4) -> 0 | K4: =SUMIFS(收入流水表!J:J,收入流水表!C:C,$K$3,收入流水表!A:A,A4) -> 39.6 | L4: =SUMIFS(收入流水表!J:J,收入流水表!C:C,$L$3,收入流水表!A:A,A4) -> 0 | M4: =SUM(I4:L4) -> 97.6 | N4: =H4+M4 -> 17850.6 | O4: =SUMIFS(收入流水表!J:J,收入流水表!I:I,$O$3,收入流水表!A:A,A4) -> 9413 | P4: =SUMIFS(收入流水表!J:J,收入流水表!I:I,$P$3,收入流水表!A:A,A4) -> 8200 | Q4: =SUMIFS(收入流水表!J:J,收入流水表!I:I,$Q$3,收入流水表!A:A,A4) -> 0 | R4: =SUMIFS(收入流水表!J:J,收入流水表!I:I,$R$3,收入流水表!A:A,A4) -> 0
A5: 46205 | B5: =SUMIFS(收入流水表!J:J,收入流水表!C:C,$B$3,收入流水表!A:A,A5) -> 7411 | C5: =SUMIFS(收入流水表!J:J,收入流水表!C:C,$C$3,收入流水表!A:A,A5) -> 2356 | D5: =SUMIFS(收入流水表!J:J,收入流水表!C:C,$D$3,收入流水表!A:A,A5) -> 2500 | E5: =SUMIFS(收入流水表!J:J,收入流水表!C:C,$E$3,收入流水表!A:A,A5) -> 0 | F5: =SUMIFS(收入流水表!J:J,收入流水表!C:C,$F$3,收入流水表!A:A,A5) -> 0 | G5: =SUMIFS(收入流水表!J:J,收入流水表!C:C,$G$3,收入流水表!A:A,A5) -> 295 | H5: =SUM(B5:G5) -> 12562 | I5: =SUMIFS(收入流水表!J:J,收入流水表!C:C,$I$3,收入流水表!A:A,A5) -> 18 | J5: =SUMIFS(收入流水表!J:J,收入流水表!C:C,$J$3,收入流水表!A:A,A5) -> 0 | K5: =SUMIFS(收入流水表!J:J,收入流水表!C:C,$K$3,收入流水表!A:A,A5) -> 409.7 | L5: =SUMIFS(收入流水表!J:J,收入流水表!C:C,$L$3,收入流水表!A:A,A5) -> 0 | M5: =SUM(I5:L5) -> 427.7 | N5: =H5+M5 -> 12989.7 | O5: =SUMIFS(收入流水表!J:J,收入流水表!I:I,$O$3,收入流水表!A:A,A5) -> 11976 | P5: =SUMIFS(收入流水表!J:J,收入流水表!I:I,$P$3,收入流水表!A:A,A5) -> 0 | Q5: =SUMIFS(收入流水表!J:J,收入流水表!I:I,$Q$3,收入流水表!A:A,A5) -> 0 | R5: =SUMIFS(收入流水表!J:J,收入流水表!I:I,$R$3,收入流水表!A:A,A5) -> 0
A6: 46206 | B6: =SUMIFS(收入流水表!J:J,收入流水表!C:C,$B$3,收入流水表!A:A,A6) -> 3485 | C6: =SUMIFS(收入流水表!J:J,收入流水表!C:C,$C$3,收入流水表!A:A,A6) -> 460 | D6: =SUMIFS(收入流水表!J:J,收入流水表!C:C,$D$3,收入流水表!A:A,A6) -> 2400 | E6: =SUMIFS(收入流水表!J:J,收入流水表!C:C,$E$3,收入流水表!A:A,A6) -> 0 | F6: =SUMIFS(收入流水表!J:J,收入流水表!C:C,$F$3,收入流水表!A:A,A6) -> 0 | G6: =SUMIFS(收入流水表!J:J,收入流水表!C:C,$G$3,收入流水表!A:A,A6) -> 80 | H6: =SUM(B6:G6) -> 6425 | I6: =SUMIFS(收入流水表!J:J,收入流水表!C:C,$I$3,收入流水表!A:A,A6) -> 23 | J6: =SUMIFS(收入流水表!J:J,收入流水表!C:C,$J$3,收入流水表!A:A,A6) -> 0 | K6: =SUMIFS(收入流水表!J:J,收入流水表!C:C,$K$3,收入流水表!A:A,A6) -> 29.7 | L6: =SUMIFS(收入流水表!J:J,收入流水表!C:C,$L$3,收入流水表!A:A,A6) -> 0 | M6: =SUM(I6:L6) -> 52.7 | N6: =H6+M6 -> 6477.7 | O6: =SUMIFS(收入流水表!J:J,收入流水表!I:I,$O$3,收入流水表!A:A,A6) -> 5060 | P6: =SUMIFS(收入流水表!J:J,收入流水表!I:I,$P$3,收入流水表!A:A,A6) -> 0 | Q6: =SUMIFS(收入流水表!J:J,收入流水表!I:I,$Q$3,收入流水表!A:A,A6) -> 0 | R6: =SUMIFS(收入流水表!J:J,收入流水表!I:I,$R$3,收入流水表!A:A,A6) -> 1000
A7: 46207 | B7: =SUMIFS(收入流水表!J:J,收入流水表!C:C,$B$3,收入流水表!A:A,A7) -> 3900 | C7: =SUMIFS(收入流水表!J:J,收入流水表!C:C,$C$3,收入流水表!A:A,A7) -> 0 | D7: =SUMIFS(收入流水表!J:J,收入流水表!C:C,$D$3,收入流水表!A:A,A7) -> 8899 | E7: =SUMIFS(收入流水表!J:J,收入流水表!C:C,$E$3,收入流水表!A:A,A7) -> 0 | F7: =SUMIFS(收入流水表!J:J,收入流水表!C:C,$F$3,收入流水表!A:A,A7) -> 0 | G7: =SUMIFS(收入流水表!J:J,收入流水表!C:C,$G$3,收入流水表!A:A,A7) -> 20 | H7: =SUM(B7:G7) -> 12819 | I7: =SUMIFS(收入流水表!J:J,收入流水表!C:C,$I$3,收入流水表!A:A,A7) -> 27 | J7: =SUMIFS(收入流水表!J:J,收入流水表!C:C,$J$3,收入流水表!A:A,A7) -> 0 | K7: =SUMIFS(收入流水表!J:J,收入流水表!C:C,$K$3,收入流水表!A:A,A7) -> 29.7 | L7: =SUMIFS(收入流水表!J:J,收入流水表!C:C,$L$3,收入流水表!A:A,A7) -> 0 | M7: =SUM(I7:L7) -> 56.7 | N7: =H7+M7 -> 12875.7 | O7: =SUMIFS(收入流水表!J:J,收入流水表!I:I,$O$3,收入流水表!A:A,A7) -> 12799 | P7: =SUMIFS(收入流水表!J:J,收入流水表!I:I,$P$3,收入流水表!A:A,A7) -> 0 | Q7: =SUMIFS(收入流水表!J:J,收入流水表!I:I,$Q$3,收入流水表!A:A,A7) -> 0 | R7: =SUMIFS(收入流水表!J:J,收入流水表!I:I,$R$3,收入流水表!A:A,A7) -> 0
A8: 46208 | B8: =SUMIFS(收入流水表!J:J,收入流水表!C:C,$B$3,收入流水表!A:A,A8) -> 8723 | C8: =SUMIFS(收入流水表!J:J,收入流水表!C:C,$C$3,收入流水表!A:A,A8) -> 2800 | D8: =SUMIFS(收入流水表!J:J,收入流水表!C:C,$D$3,收入流水表!A:A,A8) -> 8299 | E8: =SUMIFS(收入流水表!J:J,收入流水表!C:C,$E$3,收入流水表!A:A,A8) -> 0 | F8: =SUMIFS(收入流水表!J:J,收入流水表!C:C,$F$3,收入流水表!A:A,A8) -> 0 | G8: =SUMIFS(收入流水表!J:J,收入流水表!C:C,$G$3,收入流水表!A:A,A8) -> 110 | H8: =SUM(B8:G8) -> 19932 | I8: =SUMIFS(收入流水表!J:J,收入流水表!C:C,$I$3,收入流水表!A:A,A8) -> 33 | J8: =SUMIFS(收入流水表!J:J,收入流水表!C:C,$J$3,收入流水表!A:A,A8) -> 0 | K8: =SUMIFS(收入流水表!J:J,收入流水表!C:C,$K$3,收入流水表!A:A,A8) -> 0 | L8: =SUMIFS(收入流水表!J:J,收入流水表!C:C,$L$3,收入流水表!A:A,A8) -> 0 | M8: =SUM(I8:L8) -> 33 | N8: =H8+M8 -> 19965 | O8: =SUMIFS(收入流水表!J:J,收入流水表!I:I,$O$3,收入流水表!A:A,A8) -> 14923 | P8: =SUMIFS(收入流水表!J:J,收入流水表!I:I,$P$3,收入流水表!A:A,A8) -> 4400 | Q8: =SUMIFS(收入流水表!J:J,收入流水表!I:I,$Q$3,收入流水表!A:A,A8) -> 0 | R8: =SUMIFS(收入流水表!J:J,收入流水表!I:I,$R$3,收入流水表!A:A,A8) -> 0
A9: 46209 | B9: =SUMIFS(收入流水表!J:J,收入流水表!C:C,$B$3,收入流水表!A:A,A9) -> 7899.9 | C9: =SUMIFS(收入流水表!J:J,收入流水表!C:C,$C$3,收入流水表!A:A,A9) -> 1720 | D9: =SUMIFS(收入流水表!J:J,收入流水表!C:C,$D$3,收入流水表!A:A,A9) -> 6999 | E9: =SUMIFS(收入流水表!J:J,收入流水表!C:C,$E$3,收入流水表!A:A,A9) -> 0 | F9: =SUMIFS(收入流水表!J:J,收入流水表!C:C,$F$3,收入流水表!A:A,A9) -> 0 | G9: =SUMIFS(收入流水表!J:J,收入流水表!C:C,$G$3,收入流水表!A:A,A9) -> 85 | H9: =SUM(B9:G9) -> 16703.9 | I9: =SUMIFS(收入流水表!J:J,收入流水表!C:C,$I$3,收入流水表!A:A,A9) -> 31 | J9: =SUMIFS(收入流水表!J:J,收入流水表!C:C,$J$3,收入流水表!A:A,A9) -> 0 | K9: =SUMIFS(收入流水表!J:J,收入流水表!C:C,$K$3,收入流水表!A:A,A9) -> 0 | L9: =SUMIFS(收入流水表!J:J,收入流水表!C:C,$L$3,收入流水表!A:A,A9) -> 0 | M9: =SUM(I9:L9) -> 31 | N9: =H9+M9 -> 16734.9 | O9: =SUMIFS(收入流水表!J:J,收入流水表!I:I,$O$3,收入流水表!A:A,A9) -> 15949 | P9: =SUMIFS(收入流水表!J:J,收入流水表!I:I,$P$3,收入流水表!A:A,A9) -> 520 | Q9: =SUMIFS(收入流水表!J:J,收入流水表!I:I,$Q$3,收入流水表!A:A,A9) -> 0 | R9: =SUMIFS(收入流水表!J:J,收入流水表!I:I,$R$3,收入流水表!A:A,A9) -> 0
A10: 46210 | B10: =SUMIFS(收入流水表!J:J,收入流水表!C:C,$B$3,收入流水表!A:A,A10) -> 8599 | C10: =SUMIFS(收入流水表!J:J,收入流水表!C:C,$C$3,收入流水表!A:A,A10) -> 600 | D10: =SUMIFS(收入流水表!J:J,收入流水表!C:C,$D$3,收入流水表!A:A,A10) -> 299 | E10: =SUMIFS(收入流水表!J:J,收入流水表!C:C,$E$3,收入流水表!A:A,A10) -> 0 | F10: =SUMIFS(收入流水表!J:J,收入流水表!C:C,$F$3,收入流水表!A:A,A10) -> 0 | G10: =SUMIFS(收入流水表!J:J,收入流水表!C:C,$G$3,收入流水表!A:A,A10) -> 75 | H10: =SUM(B10:G10) -> 9573 | I10: =SUMIFS(收入流水表!J:J,收入流水表!C:C,$I$3,收入流水表!A:A,A10) -> 22 | J10: 0 | K10: =SUMIFS(收入流水表!J:J,收入流水表!C:C,$K$3,收入流水表!A:A,A10) -> 0 | L10: =SUMIFS(收入流水表!J:J,收入流水表!C:C,$L$3,收入流水表!A:A,A10) -> 0 | M10: =SUM(I10:L10) -> 22 | N10: =H10+M10 -> 9595 | O10: =SUMIFS(收入流水表!J:J,收入流水表!I:I,$O$3,收入流水表!A:A,A10) -> 8998 | P10: =SUMIFS(收入流水表!J:J,收入流水表!I:I,$P$3,收入流水表!A:A,A10) -> 500 | Q10: =SUMIFS(收入流水表!J:J,收入流水表!I:I,$Q$3,收入流水表!A:A,A10) -> 0 | R10: =SUMIFS(收入流水表!J:J,收入流水表!I:I,$R$3,收入流水表!A:A,A10) -> 0
A11: 46211 | B11: =SUMIFS(收入流水表!J:J,收入流水表!C:C,$B$3,收入流水表!A:A,A11) -> 7199 | C11: =SUMIFS(收入流水表!J:J,收入流水表!C:C,$C$3,收入流水表!A:A,A11) -> 0 | D11: =SUMIFS(收入流水表!J:J,收入流水表!C:C,$D$3,收入流水表!A:A,A11) -> 6811 | E11: =SUMIFS(收入流水表!J:J,收入流水表!C:C,$E$3,收入流水表!A:A,A11) -> 0 | F11: =SUMIFS(收入流水表!J:J,收入流水表!C:C,$F$3,收入流水表!A:A,A11) -> 0 | G11: =SUMIFS(收入流水表!J:J,收入流水表!C:C,$G$3,收入流水表!A:A,A11) -> 0 | H11: =SUM(B11:G11) -> 14010 | I11: =SUMIFS(收入流水表!J:J,收入流水表!C:C,$I$3,收入流水表!A:A,A11) -> 46 | J11: =SUMIFS(收入流水表!J:J,收入流水表!C:C,$J$3,收入流水表!A:A,A11) -> 0 | K11: =SUMIFS(收入流水表!J:J,收入流水表!C:C,$K$3,收入流水表!A:A,A11) -> 29.7 | L11: =SUMIFS(收入流水表!J:J,收入流水表!C:C,$L$3,收入流水表!A:A,A11) -> 0 | M11: =SUM(I11:L11) -> 75.7 | N11: =H11+M11 -> 14085.7 | O11: =SUMIFS(收入流水表!J:J,收入流水表!I:I,$O$3,收入流水表!A:A,A11) -> 8910 | P11: =SUMIFS(收入流水表!J:J,收入流水表!I:I,$P$3,收入流水表!A:A,A11) -> 2100 | Q11: =SUMIFS(收入流水表!J:J,收入流水表!I:I,$Q$3,收入流水表!A:A,A11) -> 3000 | R11: =SUMIFS(收入流水表!J:J,收入流水表!I:I,$R$3,收入流水表!A:A,A11) -> 0
A12: 46212 | B12: =SUMIFS(收入流水表!J:J,收入流水表!C:C,$B$3,收入流水表!A:A,A12) -> 5059 | C12: =SUMIFS(收入流水表!J:J,收入流水表!C:C,$C$3,收入流水表!A:A,A12) -> 3600 | D12: =SUMIFS(收入流水表!J:J,收入流水表!C:C,$D$3,收入流水表!A:A,A12) -> 9090 | E12: =SUMIFS(收入流水表!J:J,收入流水表!C:C,$E$3,收入流水表!A:A,A12) -> 0 | F12: =SUMIFS(收入流水表!J:J,收入流水表!C:C,$F$3,收入流水表!A:A,A12) -> 0 | G12: =SUMIFS(收入流水表!J:J,收入流水表!C:C,$G$3,收入流水表!A:A,A12) -> 40 | H12: =SUM(B12:G12) -> 17789 | I12: =SUMIFS(收入流水表!J:J,收入流水表!C:C,$I$3,收入流水表!A:A,A12) -> 25 | J12: =SUMIFS(收入流水表!J:J,收入流水表!C:C,$J$3,收入流水表!A:A,A12) -> 0 | K12: =SUMIFS(收入流水表!J:J,收入流水表!C:C,$K$3,收入流水表!A:A,A12) -> 29.7 | L12: =SUMIFS(收入流水表!J:J,收入流水表!C:C,$L$3,收入流水表!A:A,A12) -> 0 | M12: =SUM(I12:L12) -> 54.7 | N12: =H12+M12 -> 17843.7 | O12: =SUMIFS(收入流水表!J:J,收入流水表!I:I,$O$3,收入流水表!A:A,A12) -> 17269 | P12: =SUMIFS(收入流水表!J:J,收入流水表!I:I,$P$3,收入流水表!A:A,A12) -> 480 | Q12: =SUMIFS(收入流水表!J:J,收入流水表!I:I,$Q$3,收入流水表!A:A,A12) -> 0 | R12: =SUMIFS(收入流水表!J:J,收入流水表!I:I,$R$3,收入流水表!A:A,A12) -> 0
A13: 46213 | B13: 15855 | C13: =SUMIFS(收入流水表!J:J,收入流水表!C:C,$C$3,收入流水表!A:A,A13) -> 1509 | D13: =SUMIFS(收入流水表!J:J,收入流水表!C:C,$D$3,收入流水表!A:A,A13) -> 15380 | E13: =SUMIFS(收入流水表!J:J,收入流水表!C:C,$E$3,收入流水表!A:A,A13) -> 0 | F13: =SUMIFS(收入流水表!J:J,收入流水表!C:C,$F$3,收入流水表!A:A,A13) -> 0 | G13: =SUMIFS(收入流水表!J:J,收入流水表!C:C,$G$3,收入流水表!A:A,A13) -> 60 | H13: =SUM(B13:G13) -> 32804 | I13: =SUMIFS(收入流水表!J:J,收入流水表!C:C,$I$3,收入流水表!A:A,A13) -> 52 | J13: 80 | K13: =SUMIFS(收入流水表!J:J,收入流水表!C:C,$K$3,收入流水表!A:A,A13) -> 9.9 | L13: =SUMIFS(收入流水表!J:J,收入流水表!C:C,$L$3,收入流水表!A:A,A13) -> 0 | M13: =SUM(I13:L13) -> 141.9 | N13: =H13+M13 -> 32945.9 | O13: =SUMIFS(收入流水表!J:J,收入流水表!I:I,$O$3,收入流水表!A:A,A13) -> 14879 | P13: =SUMIFS(收入流水表!J:J,收入流水表!I:I,$P$3,收入流水表!A:A,A13) -> 3980 | Q13: =SUMIFS(收入流水表!J:J,收入流水表!I:I,$Q$3,收入流水表!A:A,A13) -> 0 | R13: =SUMIFS(收入流水表!J:J,收入流水表!I:I,$R$3,收入流水表!A:A,A13) -> 0
A14: 46214 | B14: =SUMIFS(收入流水表!J:J,收入流水表!C:C,$B$3,收入流水表!A:A,A14) -> 9931.1 | C14: =SUMIFS(收入流水表!J:J,收入流水表!C:C,$C$3,收入流水表!A:A,A14) -> 7818 | D14: =SUMIFS(收入流水表!J:J,收入流水表!C:C,$D$3,收入流水表!A:A,A14) -> 8147 | E14: =SUMIFS(收入流水表!J:J,收入流水表!C:C,$E$3,收入流水表!A:A,A14) -> 0 | F14: =SUMIFS(收入流水表!J:J,收入流水表!C:C,$F$3,收入流水表!A:A,A14) -> 0 | G14: =SUMIFS(收入流水表!J:J,收入流水表!C:C,$G$3,收入流水表!A:A,A14) -> 150 | H14: =SUM(B14:G14) -> 26046.1 | I14: =SUMIFS(收入流水表!J:J,收入流水表!C:C,$I$3,收入流水表!A:A,A14) -> 6 | J14: 125 | K14: =SUMIFS(收入流水表!J:J,收入流水表!C:C,$K$3,收入流水表!A:A,A14) -> 83.5 | L14: =SUMIFS(收入流水表!J:J,收入流水表!C:C,$L$3,收入流水表!A:A,A14) -> 0 | M14: =SUM(I14:L14) -> 214.5 | N14: =H14+M14 -> 26260.6 | O14: =SUMIFS(收入流水表!J:J,收入流水表!I:I,$O$3,收入流水表!A:A,A14) -> 14950 | P14: =SUMIFS(收入流水表!J:J,收入流水表!I:I,$P$3,收入流水表!A:A,A14) -> 0 | Q14: =SUMIFS(收入流水表!J:J,收入流水表!I:I,$Q$3,收入流水表!A:A,A14) -> 0 | R14: =SUMIFS(收入流水表!J:J,收入流水表!I:I,$R$3,收入流水表!A:A,A14) -> 10
A15: 46215 | B15: =SUMIFS(收入流水表!J:J,收入流水表!C:C,$B$3,收入流水表!A:A,A15) -> 5577 | C15: =SUMIFS(收入流水表!J:J,收入流水表!C:C,$C$3,收入流水表!A:A,A15) -> 6999 | D15: =SUMIFS(收入流水表!J:J,收入流水表!C:C,$D$3,收入流水表!A:A,A15) -> 3899 | E15: =SUMIFS(收入流水表!J:J,收入流水表!C:C,$E$3,收入流水表!A:A,A15) -> 0 | F15: =SUMIFS(收入流水表!J:J,收入流水表!C:C,$F$3,收入流水表!A:A,A15) -> 0 | G15: =SUMIFS(收入流水表!J:J,收入流水表!C:C,$G$3,收入流水表!A:A,A15) -> 100 | H15: =SUM(B15:G15) -> 16575 | I15: =SUMIFS(收入流水表!J:J,收入流水表!C:C,$I$3,收入流水表!A:A,A15) -> 11 | J15: 85 | K15: =SUMIFS(收入流水表!J:J,收入流水表!C:C,$K$3,收入流水表!A:A,A15) -> 9.9 | L15: =SUMIFS(收入流水表!J:J,收入流水表!C:C,$L$3,收入流水表!A:A,A15) -> 0 | M15: =SUM(I15:L15) -> 105.9 | N15: =H15+M15 -> 16680.9 | O15: =SUMIFS(收入流水表!J:J,收入流水表!I:I,$O$3,收入流水表!A:A,A15) -> 8436 | P15: =SUMIFS(收入流水表!J:J,收入流水表!I:I,$P$3,收入流水表!A:A,A15) -> 0 | Q15: =SUMIFS(收入流水表!J:J,收入流水表!I:I,$Q$3,收入流水表!A:A,A15) -> 0 | R15: =SUMIFS(收入流水表!J:J,收入流水表!I:I,$R$3,收入流水表!A:A,A15) -> 10
A16: 46216 | B16: =SUMIFS(收入流水表!J:J,收入流水表!C:C,$B$3,收入流水表!A:A,A16) -> 0 | C16: =SUMIFS(收入流水表!J:J,收入流水表!C:C,$C$3,收入流水表!A:A,A16) -> 0 | D16: =SUMIFS(收入流水表!J:J,收入流水表!C:C,$D$3,收入流水表!A:A,A16) -> 0 | E16: =SUMIFS(收入流水表!J:J,收入流水表!C:C,$E$3,收入流水表!A:A,A16) -> 0 | F16: =SUMIFS(收入流水表!J:J,收入流水表!C:C,$F$3,收入流水表!A:A,A16) -> 0 | G16: =SUMIFS(收入流水表!J:J,收入流水表!C:C,$G$3,收入流水表!A:A,A16) -> 0 | H16: =SUM(B16:G16) -> 0 | I16: =SUMIFS(收入流水表!J:J,收入流水表!C:C,$I$3,收入流水表!A:A,A16) -> 0 | J16: =SUMIFS(收入流水表!J:J,收入流水表!C:C,$J$3,收入流水表!A:A,A16) -> 0 | K16: =SUMIFS(收入流水表!J:J,收入流水表!C:C,$K$3,收入流水表!A:A,A16) -> 0 | L16: =SUMIFS(收入流水表!J:J,收入流水表!C:C,$L$3,收入流水表!A:A,A16) -> 0 | M16: =SUM(I16:L16) -> 0 | N16: =H16+M16 -> 0 | O16: =SUMIFS(收入流水表!J:J,收入流水表!I:I,$O$3,收入流水表!A:A,A16) -> 0 | P16: =SUMIFS(收入流水表!J:J,收入流水表!I:I,$P$3,收入流水表!A:A,A16) -> 0 | Q16: =SUMIFS(收入流水表!J:J,收入流水表!I:I,$Q$3,收入流水表!A:A,A16) -> 0 | R16: =SUMIFS(收入流水表!J:J,收入流水表!I:I,$R$3,收入流水表!A:A,A16) -> 0
A17: 46217 | B17: =SUMIFS(收入流水表!J:J,收入流水表!C:C,$B$3,收入流水表!A:A,A17) -> 0 | C17: =SUMIFS(收入流水表!J:J,收入流水表!C:C,$C$3,收入流水表!A:A,A17) -> 0 | D17: =SUMIFS(收入流水表!J:J,收入流水表!C:C,$D$3,收入流水表!A:A,A17) -> 0 | E17: =SUMIFS(收入流水表!J:J,收入流水表!C:C,$E$3,收入流水表!A:A,A17) -> 0 | F17: =SUMIFS(收入流水表!J:J,收入流水表!C:C,$F$3,收入流水表!A:A,A17) -> 0 | G17: =SUMIFS(收入流水表!J:J,收入流水表!C:C,$G$3,收入流水表!A:A,A17) -> 0 | H17: =SUM(B17:G17) -> 0 | I17: =SUMIFS(收入流水表!J:J,收入流水表!C:C,$I$3,收入流水表!A:A,A17) -> 0 | J17: =SUMIFS(收入流水表!J:J,收入流水表!C:C,$J$3,收入流水表!A:A,A17) -> 0 | K17: =SUMIFS(收入流水表!J:J,收入流水表!C:C,$K$3,收入流水表!A:A,A17) -> 0 | L17: =SUMIFS(收入流水表!J:J,收入流水表!C:C,$L$3,收入流水表!A:A,A17) -> 0 | M17: =SUM(I17:L17) -> 0 | N17: =H17+M17 -> 0 | O17: =SUMIFS(收入流水表!J:J,收入流水表!I:I,$O$3,收入流水表!A:A,A17) -> 0 | P17: =SUMIFS(收入流水表!J:J,收入流水表!I:I,$P$3,收入流水表!A:A,A17) -> 0 | Q17: =SUMIFS(收入流水表!J:J,收入流水表!I:I,$Q$3,收入流水表!A:A,A17) -> 0 | R17: =SUMIFS(收入流水表!J:J,收入流水表!I:I,$R$3,收入流水表!A:A,A17) -> 0
A18: 46218 | B18: =SUMIFS(收入流水表!J:J,收入流水表!C:C,$B$3,收入流水表!A:A,A18) -> 0 | C18: =SUMIFS(收入流水表!J:J,收入流水表!C:C,$C$3,收入流水表!A:A,A18) -> 0 | D18: =SUMIFS(收入流水表!J:J,收入流水表!C:C,$D$3,收入流水表!A:A,A18) -> 0 | E18: =SUMIFS(收入流水表!J:J,收入流水表!C:C,$E$3,收入流水表!A:A,A18) -> 0 | F18: =SUMIFS(收入流水表!J:J,收入流水表!C:C,$F$3,收入流水表!A:A,A18) -> 0 | G18: =SUMIFS(收入流水表!J:J,收入流水表!C:C,$G$3,收入流水表!A:A,A18) -> 0 | H18: =SUM(B18:G18) -> 0 | I18: =SUMIFS(收入流水表!J:J,收入流水表!C:C,$I$3,收入流水表!A:A,A18) -> 0 | J18: =SUMIFS(收入流水表!J:J,收入流水表!C:C,$J$3,收入流水表!A:A,A18) -> 0 | K18: =SUMIFS(收入流水表!J:J,收入流水表!C:C,$K$3,收入流水表!A:A,A18) -> 0 | L18: =SUMIFS(收入流水表!J:J,收入流水表!C:C,$L$3,收入流水表!A:A,A18) -> 0 | M18: =SUM(I18:L18) -> 0 | N18: =H18+M18 -> 0 | O18: =SUMIFS(收入流水表!J:J,收入流水表!I:I,$O$3,收入流水表!A:A,A18) -> 0 | P18: =SUMIFS(收入流水表!J:J,收入流水表!I:I,$P$3,收入流水表!A:A,A18) -> 0 | Q18: =SUMIFS(收入流水表!J:J,收入流水表!I:I,$Q$3,收入流水表!A:A,A18) -> 0 | R18: =SUMIFS(收入流水表!J:J,收入流水表!I:I,$R$3,收入流水表!A:A,A18) -> 0
A19: 46219 | B19: =SUMIFS(收入流水表!J:J,收入流水表!C:C,$B$3,收入流水表!A:A,A19) -> 0 | C19: =SUMIFS(收入流水表!J:J,收入流水表!C:C,$C$3,收入流水表!A:A,A19) -> 0 | D19: =SUMIFS(收入流水表!J:J,收入流水表!C:C,$D$3,收入流水表!A:A,A19) -> 0 | E19: =SUMIFS(收入流水表!J:J,收入流水表!C:C,$E$3,收入流水表!A:A,A19) -> 0 | F19: =SUMIFS(收入流水表!J:J,收入流水表!C:C,$F$3,收入流水表!A:A,A19) -> 0 | G19: =SUMIFS(收入流水表!J:J,收入流水表!C:C,$G$3,收入流水表!A:A,A19) -> 0 | H19: =SUM(B19:G19) -> 0 | I19: =SUMIFS(收入流水表!J:J,收入流水表!C:C,$I$3,收入流水表!A:A,A19) -> 0 | J19: =SUMIFS(收入流水表!J:J,收入流水表!C:C,$J$3,收入流水表!A:A,A19) -> 0 | K19: =SUMIFS(收入流水表!J:J,收入流水表!C:C,$K$3,收入流水表!A:A,A19) -> 0 | L19: =SUMIFS(收入流水表!J:J,收入流水表!C:C,$L$3,收入流水表!A:A,A19) -> 0 | M19: =SUM(I19:L19) -> 0 | N19: =H19+M19 -> 0 | O19: =SUMIFS(收入流水表!J:J,收入流水表!I:I,$O$3,收入流水表!A:A,A19) -> 0 | P19: =SUMIFS(收入流水表!J:J,收入流水表!I:I,$P$3,收入流水表!A:A,A19) -> 0 | Q19: =SUMIFS(收入流水表!J:J,收入流水表!I:I,$Q$3,收入流水表!A:A,A19) -> 0 | R19: =SUMIFS(收入流水表!J:J,收入流水表!I:I,$R$3,收入流水表!A:A,A19) -> 0
A20: 46220 | B20: =SUMIFS(收入流水表!J:J,收入流水表!C:C,$B$3,收入流水表!A:A,A20) -> 0 | C20: =SUMIFS(收入流水表!J:J,收入流水表!C:C,$C$3,收入流水表!A:A,A20) -> 0 | D20: =SUMIFS(收入流水表!J:J,收入流水表!C:C,$D$3,收入流水表!A:A,A20) -> 0 | E20: =SUMIFS(收入流水表!J:J,收入流水表!C:C,$E$3,收入流水表!A:A,A20) -> 0 | F20: =SUMIFS(收入流水表!J:J,收入流水表!C:C,$F$3,收入流水表!A:A,A20) -> 0 | G20: =SUMIFS(收入流水表!J:J,收入流水表!C:C,$G$3,收入流水表!A:A,A20) -> 0 | H20: =SUM(B20:G20) -> 0 | I20: =SUMIFS(收入流水表!J:J,收入流水表!C:C,$I$3,收入流水表!A:A,A20) -> 0 | J20: =SUMIFS(收入流水表!J:J,收入流水表!C:C,$J$3,收入流水表!A:A,A20) -> 0 | K20: =SUMIFS(收入流水表!J:J,收入流水表!C:C,$K$3,收入流水表!A:A,A20) -> 0 | L20: =SUMIFS(收入流水表!J:J,收入流水表!C:C,$L$3,收入流水表!A:A,A20) -> 0 | M20: =SUM(I20:L20) -> 0 | N20: =H20+M20 -> 0 | O20: =SUMIFS(收入流水表!J:J,收入流水表!I:I,$O$3,收入流水表!A:A,A20) -> 0 | P20: =SUMIFS(收入流水表!J:J,收入流水表!I:I,$P$3,收入流水表!A:A,A20) -> 0 | Q20: =SUMIFS(收入流水表!J:J,收入流水表!I:I,$Q$3,收入流水表!A:A,A20) -> 0 | R20: =SUMIFS(收入流水表!J:J,收入流水表!I:I,$R$3,收入流水表!A:A,A20) -> 0
A21: 46221 | B21: =SUMIFS(收入流水表!J:J,收入流水表!C:C,$B$3,收入流水表!A:A,A21) -> 0 | C21: =SUMIFS(收入流水表!J:J,收入流水表!C:C,$C$3,收入流水表!A:A,A21) -> 0 | D21: =SUMIFS(收入流水表!J:J,收入流水表!C:C,$D$3,收入流水表!A:A,A21) -> 0 | E21: =SUMIFS(收入流水表!J:J,收入流水表!C:C,$E$3,收入流水表!A:A,A21) -> 0 | F21: =SUMIFS(收入流水表!J:J,收入流水表!C:C,$F$3,收入流水表!A:A,A21) -> 0 | G21: =SUMIFS(收入流水表!J:J,收入流水表!C:C,$G$3,收入流水表!A:A,A21) -> 0 | H21: =SUM(B21:G21) -> 0 | I21: =SUMIFS(收入流水表!J:J,收入流水表!C:C,$I$3,收入流水表!A:A,A21) -> 0 | J21: =SUMIFS(收入流水表!J:J,收入流水表!C:C,$J$3,收入流水表!A:A,A21) -> 0 | K21: =SUMIFS(收入流水表!J:J,收入流水表!C:C,$K$3,收入流水表!A:A,A21) -> 0 | L21: =SUMIFS(收入流水表!J:J,收入流水表!C:C,$L$3,收入流水表!A:A,A21) -> 0 | M21: =SUM(I21:L21) -> 0 | N21: =H21+M21 -> 0 | O21: =SUMIFS(收入流水表!J:J,收入流水表!I:I,$O$3,收入流水表!A:A,A21) -> 0 | P21: =SUMIFS(收入流水表!J:J,收入流水表!I:I,$P$3,收入流水表!A:A,A21) -> 0 | Q21: =SUMIFS(收入流水表!J:J,收入流水表!I:I,$Q$3,收入流水表!A:A,A21) -> 0 | R21: =SUMIFS(收入流水表!J:J,收入流水表!I:I,$R$3,收入流水表!A:A,A21) -> 0
A22: 46222 | B22: =SUMIFS(收入流水表!J:J,收入流水表!C:C,$B$3,收入流水表!A:A,A22) -> 0 | C22: =SUMIFS(收入流水表!J:J,收入流水表!C:C,$C$3,收入流水表!A:A,A22) -> 0 | D22: =SUMIFS(收入流水表!J:J,收入流水表!C:C,$D$3,收入流水表!A:A,A22) -> 0 | E22: =SUMIFS(收入流水表!J:J,收入流水表!C:C,$E$3,收入流水表!A:A,A22) -> 0 | F22: =SUMIFS(收入流水表!J:J,收入流水表!C:C,$F$3,收入流水表!A:A,A22) -> 0 | G22: =SUMIFS(收入流水表!J:J,收入流水表!C:C,$G$3,收入流水表!A:A,A22) -> 0 | H22: =SUM(B22:G22) -> 0 | I22: =SUMIFS(收入流水表!J:J,收入流水表!C:C,$I$3,收入流水表!A:A,A22) -> 0 | J22: =SUMIFS(收入流水表!J:J,收入流水表!C:C,$J$3,收入流水表!A:A,A22) -> 0 | K22: =SUMIFS(收入流水表!J:J,收入流水表!C:C,$K$3,收入流水表!A:A,A22) -> 0 | L22: =SUMIFS(收入流水表!J:J,收入流水表!C:C,$L$3,收入流水表!A:A,A22) -> 0 | M22: =SUM(I22:L22) -> 0 | N22: =H22+M22 -> 0 | O22: =SUMIFS(收入流水表!J:J,收入流水表!I:I,$O$3,收入流水表!A:A,A22) -> 0 | P22: =SUMIFS(收入流水表!J:J,收入流水表!I:I,$P$3,收入流水表!A:A,A22) -> 0 | Q22: =SUMIFS(收入流水表!J:J,收入流水表!I:I,$Q$3,收入流水表!A:A,A22) -> 0 | R22: =SUMIFS(收入流水表!J:J,收入流水表!I:I,$R$3,收入流水表!A:A,A22) -> 0
A23: 46223 | B23: =SUMIFS(收入流水表!J:J,收入流水表!C:C,$B$3,收入流水表!A:A,A23) -> 0 | C23: =SUMIFS(收入流水表!J:J,收入流水表!C:C,$C$3,收入流水表!A:A,A23) -> 0 | D23: =SUMIFS(收入流水表!J:J,收入流水表!C:C,$D$3,收入流水表!A:A,A23) -> 0 | E23: =SUMIFS(收入流水表!J:J,收入流水表!C:C,$E$3,收入流水表!A:A,A23) -> 0 | F23: =SUMIFS(收入流水表!J:J,收入流水表!C:C,$F$3,收入流水表!A:A,A23) -> 0 | G23: =SUMIFS(收入流水表!J:J,收入流水表!C:C,$G$3,收入流水表!A:A,A23) -> 0 | H23: =SUM(B23:G23) -> 0 | I23: =SUMIFS(收入流水表!J:J,收入流水表!C:C,$I$3,收入流水表!A:A,A23) -> 0 | J23: =SUMIFS(收入流水表!J:J,收入流水表!C:C,$J$3,收入流水表!A:A,A23) -> 0 | K23: =SUMIFS(收入流水表!J:J,收入流水表!C:C,$K$3,收入流水表!A:A,A23) -> 0 | L23: =SUMIFS(收入流水表!J:J,收入流水表!C:C,$L$3,收入流水表!A:A,A23) -> 0 | M23: =SUM(I23:L23) -> 0 | N23: =H23+M23 -> 0 | O23: =SUMIFS(收入流水表!J:J,收入流水表!I:I,$O$3,收入流水表!A:A,A23) -> 0 | P23: =SUMIFS(收入流水表!J:J,收入流水表!I:I,$P$3,收入流水表!A:A,A23) -> 0 | Q23: =SUMIFS(收入流水表!J:J,收入流水表!I:I,$Q$3,收入流水表!A:A,A23) -> 0 | R23: =SUMIFS(收入流水表!J:J,收入流水表!I:I,$R$3,收入流水表!A:A,A23) -> 0
A24: 46224 | B24: =SUMIFS(收入流水表!J:J,收入流水表!C:C,$B$3,收入流水表!A:A,A24) -> 0 | C24: =SUMIFS(收入流水表!J:J,收入流水表!C:C,$C$3,收入流水表!A:A,A24) -> 0 | D24: =SUMIFS(收入流水表!J:J,收入流水表!C:C,$D$3,收入流水表!A:A,A24) -> 0 | E24: =SUMIFS(收入流水表!J:J,收入流水表!C:C,$E$3,收入流水表!A:A,A24) -> 0 | F24: =SUMIFS(收入流水表!J:J,收入流水表!C:C,$F$3,收入流水表!A:A,A24) -> 0 | G24: =SUMIFS(收入流水表!J:J,收入流水表!C:C,$G$3,收入流水表!A:A,A24) -> 0 | H24: =SUM(B24:G24) -> 0 | I24: =SUMIFS(收入流水表!J:J,收入流水表!C:C,$I$3,收入流水表!A:A,A24) -> 0 | J24: =SUMIFS(收入流水表!J:J,收入流水表!C:C,$J$3,收入流水表!A:A,A24) -> 0 | K24: =SUMIFS(收入流水表!J:J,收入流水表!C:C,$K$3,收入流水表!A:A,A24) -> 0 | L24: =SUMIFS(收入流水表!J:J,收入流水表!C:C,$L$3,收入流水表!A:A,A24) -> 0 | M24: =SUM(I24:L24) -> 0 | N24: =H24+M24 -> 0 | O24: =SUMIFS(收入流水表!J:J,收入流水表!I:I,$O$3,收入流水表!A:A,A24) -> 0 | P24: =SUMIFS(收入流水表!J:J,收入流水表!I:I,$P$3,收入流水表!A:A,A24) -> 0 | Q24: =SUMIFS(收入流水表!J:J,收入流水表!I:I,$Q$3,收入流水表!A:A,A24) -> 0 | R24: =SUMIFS(收入流水表!J:J,收入流水表!I:I,$R$3,收入流水表!A:A,A24) -> 0
A25: 46225 | B25: =SUMIFS(收入流水表!J:J,收入流水表!C:C,$B$3,收入流水表!A:A,A25) -> 0 | C25: =SUMIFS(收入流水表!J:J,收入流水表!C:C,$C$3,收入流水表!A:A,A25) -> 0 | D25: =SUMIFS(收入流水表!J:J,收入流水表!C:C,$D$3,收入流水表!A:A,A25) -> 0 | E25: =SUMIFS(收入流水表!J:J,收入流水表!C:C,$E$3,收入流水表!A:A,A25) -> 0 | F25: =SUMIFS(收入流水表!J:J,收入流水表!C:C,$F$3,收入流水表!A:A,A25) -> 0 | G25: =SUMIFS(收入流水表!J:J,收入流水表!C:C,$G$3,收入流水表!A:A,A25) -> 0 | H25: =SUM(B25:G25) -> 0 | I25: =SUMIFS(收入流水表!J:J,收入流水表!C:C,$I$3,收入流水表!A:A,A25) -> 0 | J25: =SUMIFS(收入流水表!J:J,收入流水表!C:C,$J$3,收入流水表!A:A,A25) -> 0 | K25: =SUMIFS(收入流水表!J:J,收入流水表!C:C,$K$3,收入流水表!A:A,A25) -> 0 | L25: =SUMIFS(收入流水表!J:J,收入流水表!C:C,$L$3,收入流水表!A:A,A25) -> 0 | M25: =SUM(I25:L25) -> 0 | N25: =H25+M25 -> 0 | O25: =SUMIFS(收入流水表!J:J,收入流水表!I:I,$O$3,收入流水表!A:A,A25) -> 0 | P25: =SUMIFS(收入流水表!J:J,收入流水表!I:I,$P$3,收入流水表!A:A,A25) -> 0 | Q25: =SUMIFS(收入流水表!J:J,收入流水表!I:I,$Q$3,收入流水表!A:A,A25) -> 0 | R25: =SUMIFS(收入流水表!J:J,收入流水表!I:I,$R$3,收入流水表!A:A,A25) -> 0
A26: 46226 | B26: =SUMIFS(收入流水表!J:J,收入流水表!C:C,$B$3,收入流水表!A:A,A26) -> 0 | C26: =SUMIFS(收入流水表!J:J,收入流水表!C:C,$C$3,收入流水表!A:A,A26) -> 0 | D26: =SUMIFS(收入流水表!J:J,收入流水表!C:C,$D$3,收入流水表!A:A,A26) -> 0 | E26: =SUMIFS(收入流水表!J:J,收入流水表!C:C,$E$3,收入流水表!A:A,A26) -> 0 | F26: =SUMIFS(收入流水表!J:J,收入流水表!C:C,$F$3,收入流水表!A:A,A26) -> 0 | G26: =SUMIFS(收入流水表!J:J,收入流水表!C:C,$G$3,收入流水表!A:A,A26) -> 0 | H26: =SUM(B26:G26) -> 0 | I26: =SUMIFS(收入流水表!J:J,收入流水表!C:C,$I$3,收入流水表!A:A,A26) -> 0 | J26: =SUMIFS(收入流水表!J:J,收入流水表!C:C,$J$3,收入流水表!A:A,A26) -> 0 | K26: =SUMIFS(收入流水表!J:J,收入流水表!C:C,$K$3,收入流水表!A:A,A26) -> 0 | L26: =SUMIFS(收入流水表!J:J,收入流水表!C:C,$L$3,收入流水表!A:A,A26) -> 0 | M26: =SUM(I26:L26) -> 0 | N26: =H26+M26 -> 0 | O26: =SUMIFS(收入流水表!J:J,收入流水表!I:I,$O$3,收入流水表!A:A,A26) -> 0 | P26: =SUMIFS(收入流水表!J:J,收入流水表!I:I,$P$3,收入流水表!A:A,A26) -> 0 | Q26: =SUMIFS(收入流水表!J:J,收入流水表!I:I,$Q$3,收入流水表!A:A,A26) -> 0 | R26: =SUMIFS(收入流水表!J:J,收入流水表!I:I,$R$3,收入流水表!A:A,A26) -> 0
A27: 46227 | B27: =SUMIFS(收入流水表!J:J,收入流水表!C:C,$B$3,收入流水表!A:A,A27) -> 0 | C27: =SUMIFS(收入流水表!J:J,收入流水表!C:C,$C$3,收入流水表!A:A,A27) -> 0 | D27: =SUMIFS(收入流水表!J:J,收入流水表!C:C,$D$3,收入流水表!A:A,A27) -> 0 | E27: =SUMIFS(收入流水表!J:J,收入流水表!C:C,$E$3,收入流水表!A:A,A27) -> 0 | F27: =SUMIFS(收入流水表!J:J,收入流水表!C:C,$F$3,收入流水表!A:A,A27) -> 0 | G27: =SUMIFS(收入流水表!J:J,收入流水表!C:C,$G$3,收入流水表!A:A,A27) -> 0 | H27: =SUM(B27:G27) -> 0 | I27: =SUMIFS(收入流水表!J:J,收入流水表!C:C,$I$3,收入流水表!A:A,A27) -> 0 | J27: =SUMIFS(收入流水表!J:J,收入流水表!C:C,$J$3,收入流水表!A:A,A27) -> 0 | K27: =SUMIFS(收入流水表!J:J,收入流水表!C:C,$K$3,收入流水表!A:A,A27) -> 0 | L27: =SUMIFS(收入流水表!J:J,收入流水表!C:C,$L$3,收入流水表!A:A,A27) -> 0 | M27: =SUM(I27:L27) -> 0 | N27: =H27+M27 -> 0 | O27: =SUMIFS(收入流水表!J:J,收入流水表!I:I,$O$3,收入流水表!A:A,A27) -> 0 | P27: =SUMIFS(收入流水表!J:J,收入流水表!I:I,$P$3,收入流水表!A:A,A27) -> 0 | Q27: =SUMIFS(收入流水表!J:J,收入流水表!I:I,$Q$3,收入流水表!A:A,A27) -> 0 | R27: =SUMIFS(收入流水表!J:J,收入流水表!I:I,$R$3,收入流水表!A:A,A27) -> 0
... A34: 46234 | B34: =SUMIFS(收入流水表!J:J,收入流水表!C:C,$B$3,收入流水表!A:A,A34) -> 0 | C34: =SUMIFS(收入流水表!J:J,收入流水表!C:C,$C$3,收入流水表!A:A,A34) -> 0 | D34: =SUMIFS(收入流水表!J:J,收入流水表!C:C,$D$3,收入流水表!A:A,A34) -> 0 | E34: =SUMIFS(收入流水表!J:J,收入流水表!C:C,$E$3,收入流水表!A:A,A34) -> 0 | F34: =SUMIFS(收入流水表!J:J,收入流水表!C:C,$F$3,收入流水表!A:A,A34) -> 0 | G34: =SUMIFS(收入流水表!J:J,收入流水表!C:C,$G$3,收入流水表!A:A,A34) -> 0 | H34: =SUM(B34:G34) -> 0 | I34: =SUMIFS(收入流水表!J:J,收入流水表!C:C,$I$3,收入流水表!A:A,A34) -> 0 | J34: =SUMIFS(收入流水表!J:J,收入流水表!C:C,$J$3,收入流水表!A:A,A34) -> 0 | K34: =SUMIFS(收入流水表!J:J,收入流水表!C:C,$K$3,收入流水表!A:A,A34) -> 0 | L34: =SUMIFS(收入流水表!J:J,收入流水表!C:C,$L$3,收入流水表!A:A,A34) -> 0 | M34: =SUM(I34:L34) -> 0 | N34: =H34+M34 -> 0 | O34: =SUMIFS(收入流水表!J:J,收入流水表!I:I,$O$3,收入流水表!A:A,A34) -> 0 | P34: =SUMIFS(收入流水表!J:J,收入流水表!I:I,$P$3,收入流水表!A:A,A34) -> 0 | Q34: =SUMIFS(收入流水表!J:J,收入流水表!I:I,$Q$3,收入流水表!A:A,A34) -> 0 | R34: =SUMIFS(收入流水表!J:J,收入流水表!I:I,$R$3,收入流水表!A:A,A34) -> 0
A35: 7月合计 | B35: =SUM(B4:B34) -> 87612 | C35: =SUM(C4:C34) -> 27862 | D35: =SUM(D4:D34) -> 86363 | E35: =SUM(E4:E34) -> 0 | F35: =SUM(F4:F34) -> 0 | G35: =SUM(G4:G34) -> 1155 | H35: =SUM(H4:H34) -> 202992 | I35: =SUM(I4:I34) -> 352 | ... R35: =SUM(R4:R34) -> 1020

Sheet 收入流水表
A1: 日期 | B1: 收据编号 | C1: 收入类别 | D1: 姓名 | E1: 联系方式 | F1: 卡种/课种 | G1: 课时节数 | H1: 付款类别 | I1: 付款方式 | J1: 金额 | K1: 经办人 | L1: 业绩奖励人 | M1: 奖励机制 | N1: 是否添加微信 | O1: 备注 | P1: 合约编号 | Q1: 会员是否签字 | R1: 是否续卡/续课 | S1: 是否核单 | T1: 类型 | U1: 使用门店
A2: 46204 | C2: 水吧收入 | J2: 58 | K2: 赵盼
A3: 46204 | C3: 其他收入 | J3: 140 | K3: 赵盼 | O3: 两个泳帽是现金
A4: 46204 | C4: 美团收入 | J4: 39.6 | K4: 赵盼
A5: 46204 | C5: 抖音收入 | J5: 0 | K5: 赵盼
A6: 46204 | C6: 餐吧收入 | J6: 0 | K6: 赵盼
A7: 46204 | B7: 1106236 | C7: 教练班收入 | D7: 刘芷琳 | E7: 15827527505 | F7: 游泳培训1V1 | G7: 10 | H7: 全款 | I7: 支付宝 | J7: 1500 | K7: 万诗琴 | O7: 一对一10节课 包教会 送暑假畅游 | P7: 9309282 | Q7: 是 | R7: 否 | S7: 是 | T7: 预约
A8: 46204 | B8: 2923592 | C8: 会籍收入 | D8: 凡熙震 | E8: 15927129741 | F8: 游泳培训1V2 | G8: 10 | H8: 定金 | I8: 微信 | J8: 200 | K8: 万诗琴 | O8: 一对二,10节课,定金，送三个月游泳时间
A9: 46204 | C9: 教练班收入 | H9: 定金 | I9: 微信 | J9: 160 | K9: 程浩楠
A10: 46204 | B10: 2923773 | C10: 教练班收入 | D10: 叶良艳 | E10: 18702725483 | F10: 次卡 | H10: 全款 | I10: 微信 | J10: 1000 | K10: 刘镇 | O10: 游泳50次次卡 | P10: 9122631 | Q10: 是 | R10: 否 | S10: 是 | T10: 预约
A11: 46204 | C11: 会籍收入 | H11: 单价 | I11: 微信 | J11: 80 | K11: 程浩楠
A12: 46204 | B12: 1106238 | C12: 教练班收入 | D12: 钱功业 | E12: 18971073520 | F12: 游泳培训1V2 | G12: 10 | H12: 全款 | I12: 支付宝 | J12: 1000 | K12: 万诗琴 | O12: 一对二 10节课 送暑假畅游 | P12: 9309283 | Q12: 是 | R12: 否 | S12: 是 | T12: 预约
A13: 46204 | B13: 1106237 | C13: 教练班收入 | D13: 张世杰 | E13: 15997449859 | F13: 游泳培训1V1 | G13: 20 | H13: 全款 | I13: 支付宝 | J13: 2500 | K13: 万诗琴 | O13: 一对一 20节课 送四个月 | P13: 9309284 | Q13: 是 | R13: 否 | S13: 是 | T13: 预约
A14: 46204 | B14: 2923772 | C14: 教练班收入 | D14: 柯梦晴 | E14: 15872372823 | F14: 游泳培训1V1 | G14: 10 | H14: 全款 | I14: 支付宝 | J14: 1500 | K14: 贺琨 /李兴阳 | O14: 一对一10节课 送三个月 | P14: 9310361 | Q14: 是 | R14: 否 | S14: 是 | T14: 预约
A15: 46204 | B15: 1106240 | C15: 教练班收入 | D15: 徐乐添 | E15: 18607108499 | F15: 游泳培训1V2 | H15: 全款 | I15: 微信 | J15: 1000 | K15: 陈江丽 | O15: 一对二 包教会 送3个月畅游 | P15: 9309285 | Q15: 是 | R15: 否 | S15: 是 | T15: 预约
A16: 46204 | B16: 2823796 | C16: 教练班收入 | D16: 王楚夫 王楚兮 | E16: 15391520412 | F16: 双学年卡 | H16: 全款 | I16: 微信 | J16: 2980 | K16: 刘镇 | O16: 亲子双年卡送年卡 | P16: 9122502 | Q16: 是 | R16: 否 | S16: 是 | T16: 预约
A17: 46204 | B17: 2823797 | C17: 教练班收入 | D17: 董雨宸 | E17: 15872222241 | H17: 全款 | I17: 支付宝 | J17: 1000 | K17: 陈江丽
A18: 46204 | B18: 2823798 | C18: 会籍收入 | D18: 李洋 | E18: 1327731866 | F18: 年卡 | H18: 全款 | I18: 微信 | J18: 494 | K18: 万诗琴 | O18: 年卡 | P18: 9121539 | Q18: 是 | R18: 否 | S18: 是 | T18: 预约
A19: 46204 | B19: 2923819 | C19: 会籍收入 | D19: 吴秋宇 毛俊怡 | E19: 18908669790 17671719105 | F19: 游泳培训1V2 | H19: 全款 | I19: 微信 | J19: 2000 | K19: 贺琨 | O19: 游泳一对二10节课 送3个月 | P19: 9310362 | Q19: 是 | R19: 否 | S19: 是 | T19: 预约
A20: 46204 | B20: 2923775 | C20: 会籍收入 | D20: 陈盛霖 | E20: 15564579145 | F20: 季卡 | H20: 全款 | I20: 微信 | J20: 499 | K20: 刘镇 | O20: 季卡送一个月 | P20: 9122633 | Q20: 是 | R20: 否 | S20: 是 | T20: 预约
A21: 46204 | B21: 2923776 | C21: 教练班收入 | D21: 宋欣潼 | E21: 15679193208 | F21: 游泳培训1V2 | G21: 10 | H21: 全款 | I21: 微信 | J21: 1000 | K21: 贺琨 | O21: 游泳一对二10节课 送3个月 | P21: 9310363 | Q21: 是 | R21: 否 | S21: 是 | T21: 预约
A22: 46204 | B22: 2923820 | C22: 会籍收入 | D22: 王楠 | E22: 18271460820 | F22: 半年卡 | H22: 全款 | I22: 支付宝 | J22: 700 | K22: 万诗琴 | O22: 半年卡送四个月 | P22: 9122632 | Q22: 是 | R22: 否 | S22: 是 | T22: 预约
A23: 46205 | C23: 水吧收入 | J23: 18 | K23: 赵盼
A24: 46205 | C24: 其他收入 | J24: 295 | K24: 赵盼 | O24: 转卡费200
A25: 46205 | C25: 美团收入 | J25: 409.7 | K25: 赵盼
A26: 46205 | C26: 抖音收入 | J26: 0 | K26: 赵盼
A27: 46205 | C27: 餐吧收入 | J27: 0 | K27: 赵盼
A28: 46205 | B28: 2923780 | C28: 会籍收入 | D28: 李小翠 | E28: 18162660123 | F28: 次卡 | H28: 全款 | I28: 微信 | J28: 2000 | K28: 刘镇 | O28: 游泳次卡100次送30次 | P28: 9122634 | Q28: 是 | R28: 否 | S28: 是 | T28: 预约
A29: 46205 | B29: 2460921 | C29: 会籍收入 | D29: 刘娜 | E29: 13307141995 | F29: 月卡 | H29: 全款 | I29: 微信 | J29: 280 | K29: 万诗琴 | O29: 月卡 | P29: 9122503 | Q29: 是 | R29: 否 | S29: 是 | T29: 预约
A30: 46205 | B30: 2923778 | C30: 教练班收入 | D30: 涂小红 | E30: 17762672291 | F30: 游泳培训1V1 | H30: 全款 | I30: 微信 | J30: 1500 | K30: 邱志杰 | O30: 一对一10节课 送四个月 | P30: 9310364 | Q30: 是 | R30: 否 | S30: 是 | T30: 预约
A31: 46205 | B31: 2923779 | C31: 会籍收入 | D31: 李晓霞 | E31: 15752783542 | F31: 学年卡 | H31: 升级 | I31: 微信 | J31: 400 | K31: 贺琨 | O31: 升级学年卡
A32: 46205 | B32: 2923781 | C32: 会籍收入 | D32: 夏建设 | E32: 15342258295 | F32: 双年卡 | H32: 全款 | I32: 微信 | J32: 1500 | K32: 刘镇 | O32: 双年卡 送半年 | P32: 9122504 | Q32: 是 | R32: 否 | S32: 是 | T32: 预约
A33: 46205 | B33: 2923782 | C33: 教练班收入 | D33: 王子超 | E33: 13659885255 | F33: 游泳培训1V2 | H33: 全款 | I33: 微信 | J33: 1000 | K33: 万诗琴 | O33: 一对二,10节课,包教会 | P33: 9309287 | Q33: 是 | R33: 否 | S33: 是 | T33: 预约
A34: 46205 | B34: 2923783 | C34: 会籍收入 | D34: 朱仁杰 | E34: 18327058998 | F34: 双学年卡 | H34: 全款 | I34: 微信 | J34: 1000 | K34: 万诗琴 | O34: 游泳双学年卡 送两个月 | P34: 9122505 | Q34: 是 | R34: 否 | S34: 是 | T34: 预约
A35: 46205 | B35: 2923784 | C35: 会籍收入 | D35: 寇蓉 | E35: 18694043431 | F35: 游泳培训1V2 | G35: 10 | H35: 全款 | I35: 微信 | J35: 1900 | K35: 万诗琴 | O35: 一对二10节课包教会送3个月游泳 | P35: 9309288 | Q35: 是 | R35: 否 | S35: 是 | T35: 预约
A36: 46205 | C36: 会籍收入 | H36: 全款 | I36: 微信 | J36: 40 | K36: 贺琨 | O36: 单次
A37: 46205 | B37: 2823801 | C37: 私教收入 | D37: 范琳 | E37: 15733133618 | F37: 常规课 | G37: 14 | H37: 全款 | I37: 微信 | J37: 2356 | K37: 刘笑天 | O37: 常规课 | P37: 9205528 | Q37: 是 | R37: 否 | S37: 是 | T37: 预约
A38: 46205 | B38: 2923593 | C38: 会籍收入 | D38: 王虫虫 | E38: 13517275476 | F38: 月卡 | H38: 美团 | J38: 291 | K38: 贺琨 | O38: 美团购买 | P38: 9123249 | Q38: 是 | R38: 否 | S38: 是 | T38: 预约
A39: 46206 | C39: 水吧收入 | J39: 23 | K39: 赵盼
A40: 46206 | C40: 其他收入 | J40: 80 | K40: 赵盼
A41: 46206 | C41: 美团收入 | J41: 29.7 | K41: 赵盼
A42: 46206 | C42: 抖音收入 | J42: 0 | K42: 赵盼
A43: 46206 | C43: 餐吧收入 | J43: 0 | K43: 赵盼
A44: 46206 | B44: 2923785 | C44: 教练班收入 | D44: 刘艳容 | E44: 15071369079 | F44: 年卡 | H44: 全款 | I44: 微信 | J44: 1000 | K44: 封庆 | O44: 游泳年卡 | P44: 9123250 | Q44: 是 | R44: 否 | S44: 是 | T44: 预约
A45: 46206 | B45: 2823802 | C45: 私教收入 | D45: 许立弓 | E45: 18310021447 | F45: 定金 | H45: 定金 | I45: 微信 | J45: 200 | K45: 袁辉/曾庆爽 | O45: 定金200
A46: 46206 | B46: 2955202 | C46: 会籍收入 | D46: 他煌 | E46: 13707225103 | F46: 次卡 | H46: 全款 | I46: 微信 | J46: 1800 | K46: 万诗琴 | O46: 游泳100次 送二十次 | P46: 9122506 | Q46: 是 | R46: 否 | S46: 是 | T46: 预约
A47: 46206 | B47: 2955203 | C47: 会籍收入 | D47: 黄浩 | E47: 13667253588 | F47: 次卡 | H47: 全款 | I47: 现金 | J47: 1000 | K47: 万诗琴 | O47: 游泳50次次卡 | P47: 9122507 | Q47: 是 | R47: 否 | S47: 是 | T47: 预约
A48: 46206 | B48: 2460923 | C48: 会籍收入 | D48: 周一鸣 | E48: 18271121988 | F48: 游泳培训1V1 | H48: 升级 | I48: 微信 | J48: 400 | K48: 万诗琴 | O48: 升级一对一
A49: 46206 | B49: 2955205 | C49: 教练班收入 | D49: 郭明羽 | E49: 18627723203 | F49: 月卡 | H49: 全款 | I49: 微信 | J49: 1400 | K49: 高家林 | O49: 老会员送两个月游泳卡 | P49: 9122509 | Q49: 是 | R49: 否 | S49: 是 | T49: 预约
A50: 46206 | B50: 2823800 | C50: 会籍收入 | D50: 陆羽泽 | E50: 18086628925 | F50: 月卡 | J50: 285 | K50: 万诗琴 | O50: 月卡（美团购买） | P50: 9122508 | Q50: 是 | R50: 否 | S50: 是 | T50: 预约
A51: 46206 | C51: 私教收入 | H51: 全款 | I51: 微信 | J51: 260 | K51: 曾庆爽
A52: 46207 | C52: 水吧收入 | J52: 27 | K52: 赵盼
A53: 46207 | C53: 其他收入 | J53: 20 | K53: 赵盼
A54: 46207 | C54: 美团收入 | J54: 29.7 | K54: 赵盼
A55: 46207 | C55: 抖音收入 | J55: 0 | K55: 赵盼
A56: 46207 | C56: 餐吧收入 | J56: 0 | K56: 赵盼
A57: 46207 | B57: 2955206 | C57: 会籍收入 | D57: 丁亮 | E57: 15025766950 | F57: 年卡 | H57: 全款 | I57: 微信 | J57: 100 | K57: 万诗琴 | O57: 升级健身年卡
A58: 46207 | B58: 2955207 | C58: 会籍收入 | D58: 杨铂霖 | E58: 13554140983 | F58: 游泳培训1V2 | H58: 全款 | I58: 微信 | J58: 1000 | K58: 万诗琴 | O58: 一对二,10节课,送3个月的时间 | P58: 9308995 | Q58: 是 | R58: 否 | S58: 是 | T58: 预约
A59: 46207 | B59: 2955209 | C59: 教练班收入 | D59: 奚宇涵 肖于希 | E59: 13886189673 | F59: 游泳培训1V1 | H59: 全款 | I59: 微信 | J59: 4599 | K59: 万诗琴 | O59: 长训50节课,一对一,课程没有有效期 | P59: 9309289 | Q59: 是 | R59: 否 | S59: 是 | T59: 预约
A60: 46207 | B60: 2955210 | C60: 会籍收入 | D60: 奚锐 | E60: 13476190668 | F60: 年卡 | H60: 全款 | I60: 微信 | J60: 500 | K60: 万诗琴 | O60: 升级游泳年卡 | P60: 9122510 | Q60: 是 | R60: 是 | S60: 是 | T60: 预约
A61: 46207 | B61: 2955211 | C61: 教练班收入 | D61: 胡牧也 黄嘉棋 | E61: 13163372073 18601205051 | F61: 游泳培训1V2 | H61: 全款 | I61: 微信 | J61: 1800 | K61: 封庆 | O61: 一对二10节课 送暑假畅游 | P61: 9308996 | Q61: 是 | R61: 否 | S61: 是 | T61: 预约
A62: 46207 | B62: 2823803 | C62: 会籍收入 | D62: 贺飞飞 | E62: 19571079665 | F62: 双学年卡 | H62: 全款 | I62: 微信 | J62: 501 | K62: 贺琨 | O62: 升级两学年
A63: 46207 | B63: 2460924 | C63: 会籍收入 | D63: 郑雨荷 | E63: 15172511269 | F63: 游泳培训1V1 | H63: 全款 | I63: 微信 | J63: 1500 | K63: 万诗琴 | O63: 一对一10节课 送三个月畅游 | P63: 9308997 | Q63: 是 | R63: 否 | S63: 是 | T63: 预约
A64: 46207 | B64: 24609258 | C64: 会籍收入 | D64: 刘诗晴 | E64: 18971430567 | F64: 月卡 | H64: 全款 | I64: 微信 | J64: 299 | K64: 贺琨 | O64: 月卡 | P64: 9122511 | Q64: 是 | R64: 否 | S64: 是 | T64: 预约
A65: 46207 | B65: 2955213 | C65: 教练班收入 | D65: 周蔓青 | E65: 15527473896 | F65: 游泳培训1V1 | H65: 全款 | I65: 微信 | J65: 1500 | K65: 贺琨 /李兴阳 | O65: 一对一10节课 送两个月 | P65: 9918607 | Q65: 是 | R65: 否 | S65: 是 | T65: 预约
A66: 46207 | B66: 2823805 | C66: 教练班收入 | D66: 雷皓成 | E66: 13343468139 | F66: 游泳培训1V2 | H66: 全款 | I66: 微信 | J66: 1000 | K66: 刘镇 | O66: 游泳一对二10节课 送3个月 | P66: 9310365 | Q66: 是 | R66: 否 | S66: 是 | T66: 预约
A67: 46208 | C67: 水吧收入 | J67: 33 | K67: 潘芷悦
A68: 46208 | C68: 其他收入 | J68: 110 | K68: 潘芷悦
A69: 46208 | C69: 美团收入 | J69: 0 | K69: 潘芷悦
A70: 46208 | C70: 抖音收入 | J70: 0 | K70: 潘芷悦
A71: 46208 | C71: 餐吧收入 | J71: 0 | K71: 潘芷悦
A72: 46208 | B72: 2823804 | C72: 会籍收入 | D72: 王恺 | E72: 19186945492 | F72: 半年卡 | H72: 全款 | I72: 微信 | J72: 700 | K72: 万诗琴 | O72: 半年卡送四个月 | P72: 9122635 | Q72: 是 | R72: 否 | S72: 是 | T72: 预约
A73: 46208 | B73: 2823808 | C73: 会籍收入 | D73: 王开航 | E73: 18886421407 | F73: 年卡 | H73: 升级 | I73: 微信 | J73: 200 | K73: 万诗琴 | O73: 升级健身游泳年卡
A74: 46208 | B74: 2460926 | C74: 教练班收入 | D74: 段缓 | E74: 13797094687 | F74: 年卡 | H74: 全款 | I74: 微信 | J74: 1099 | K74: 高家林 | O74: 三人同行送六个月共19个月健身卡 | P74: 9122512 | Q74: 是 | R74: 否 | S74: 是 | T74: 预约
A75: 46208 | B75: 2823806 | C75: 会籍收入 | D75: 邓存宇 | E75: 18327145709 | F75: 季卡 | H75: 全款 | I75: 微信 | J75: 499 | K75: 陈江丽 | O75: 季卡送一个月 | P75: 9122636 | Q75: 是 | R75: 否 | S75: 是 | T75: 预约
A76: 46208 | B76: 2823812 | C76: 私教收入 | D76: 张环 | E76: 15727256293 | F76: 特色课 | H76: 全款 | I76: 支付宝 | J76: 2800 | K76: 邱昊/曾庆爽 | O76: 康复课10节 | P76: 9205529 | Q76: 是 | R76: 否 | S76: 否 | T76: 预约
A77: 46208 | B77: 2823807 | C77: 会籍收入 | D77: 丁俊轩 | E77: 17320524069 | F77: 月卡 | H77: 全款 | I77: 支付宝 | J77: 400 | K77: 万诗琴 | O77: 双月卡送一个月 | P77: 9122637 | Q77: 是 | R77: 否 | S77: 是 | T77: 预约
A78: 46208 | B78: 2823809 | C78: 会籍收入 | D78: 蒙檬 | E78: 13347571417 | F78: 月卡 | H78: 升级 | I78: 微信 | J78: 100 | K78: 贺琨 | O78: 升级
A79: 46208 | B79: 2923789 | C79: 教练班收入 | D79: 季敬亭 | E79: 15271802910 | F79: 游泳培训1V1 | H79: 全款 | I79: 微信 | J79: 1500 | K79: 万诗琴 | O79: 一对一 10节课 送暑假畅游 | P79: 9309297 | Q79: 是 | R79: 否 | S79: 是 | T79: 预约
A80: 46208 | B80: 2823810 | C80: 会籍收入 | D80: 张艳婷 | E80: 13871515692 | F80: 年卡 | H80: 全款 | I80: 支付宝 | J80: 1200 | K80: 万诗琴 | O80: 年卡 送四个月 | P80: 9122638 | Q80: 是 | R80: 否 | S80: 是 | T80: 预约
A81: 46208 | B81: 2955216 | C81: 会籍收入 | D81: 薛明慎 | E81: 17794324477 | F81: 季卡 | H81: 美团 | J81: 499 | K81: 贺琨 | O81: 游泳季卡（美团购买） | P81: 9122513 | Q81: 是 | R81: 否 | S81: 是 | T81: 预约
A82: 46208 | B82: 2460927 | C82: 教练班收入 | D82: 徐宗睿 | E82: 15914167306 | F82: 游泳培训1V1 | H82: 全款 | I82: 微信 | J82: 1500 | K82: 贺琨 | O82: 一对一,10节课,送两个月游泳 | P82: 9309292 | Q82: 是 | R82: 否 | S82: 是 | T82: 预约
A83: 46208 | B83: 2923786 | C83: 教练班收入 | D83: 供婷 刘易扬 刘翌成 | E83: 17771882869 | F83: 游泳培训1V3 | H83: 全款 | I83: 微信 | J83: 2700 | K83: 万诗琴 | O83: 一对三 送两个月时间 包教会 10节课 | P83: 9309293 | Q83: 是 | R83: 否 | S83: 是 | T83: 预约
A84: 46208 | B84: 2823811 | C84: 会籍收入 | D84: 阿衣 | E84: 13778656137 | F84: 月卡 | H84: 全款 | I84: 微信 | J84: 199 | K84: 蕫殿强 | O84: 月卡 | P84: 9122639 | Q84: 是 | R84: 否 | S84: 是 | T84: 预约
A85: 46208 | B85: 2923787 | C85: 教练班收入 | D85: 陈静 王倩倩 | E85: 17671092505 15617799780 | F85: 游泳培训1V2 | H85: 全款 | I85: 微信 | J85: 1000 | K85: 刘文昌 | O85: 一对二 5节课 送一个月健身游泳卡 | P85: 9309294 | Q85: 是 | R85: 否 | S85: 是 | T85: 预约
A86: 46208 | B86: 2460929 | C86: 会籍收入 | D86: 喻丹佳 | E86: 13429893889 | F86: 年卡 | H86: 全款 | I86: 微信 | J86: 2026 | K86: 高家林 | O86: 健身游泳套餐卡 2026 | P86: 9309295 | Q86: 是 | R86: 否 | S86: 是 | T86: 预约
A87: 46208 | B87: 2923788 | C87: 会籍收入 | D87: 谢沈 尹沈越 | E87: 15102732868 | F87: 游泳培训1V2 | H87: 全款 | I87: 微信 | J87: 1900 | K87: 万诗琴 | O87: 补金1900.一对二,10节课 送2个月游泳 包教会 | P87: 9309296 | Q87: 是 | R87: 否 | S87: 是 | T87: 预约
A88: 46208 | B88: 2923794 | C88: 教练班收入 | D88: 彭闯 | E88: 1862812267 | F88: 游泳培训1V2 | H88: 补金 | I88: 微信 | J88: 500 | K88: 程浩楠
A89: 46208 | B89: 2823817 | C89: 会籍收入 | D89: 梁美燕 张元沥 | E89: 13396054132 | F89: 游泳培训1V1 | H89: 全款 | I89: 微信 | J89: 1000 | K89: 刘镇 | O89: 升级游泳一对一
A90: 46209 | C90: 水吧收入 | J90: 31 | K90: 熊睿玲
A91: 46209 | C91: 其他收入 | J91: 85 | K91: 熊睿玲
A92: 46209 | C92: 美团收入 | J92: 0 | K92: 熊睿玲
A93: 46209 | C93: 抖音收入 | J93: 0 | K93: 熊睿玲
A94: 46209 | C94: 餐吧收入 | J94: 0 | K94: 熊睿玲
A95: 46209 | B95: 2823816 | C95: 教练班收入 | D95: 张浔 | E95: 18164110667 | F95: 游泳培训1V2 | G95: 10 | H95: 全款 | I95: 微信 | J95: 1000 | K95: 刘镇 | O95: 一对二 10节课 送暑假畅游 | P95: 9310367 | Q95: 是 | R95: 否 | S95: 是 | T95: 预约
A96: 46209 | B96: 2823815 | C96: 教练班收入 | D96: 黄炎熙 | E96: 15207129562 | F96: 游泳培训1V2 | G96: 10 | H96: 全款 | I96: 微信 | J96: 1000 | K96: 刘镇 | O96: 一对二 10节课 送暑假畅游 | P96: 9310366 | Q96: 是 | R96: 否 | S96: 是 | T96: 预约
A97: 46209 | B97: 2460930 | C97: 教练班收入 | D97: 洪辰伊 | E97: 13554478580 | F97: 次卡 | H97: 全款 | I97: 微信 | J97: 1000 | K97: 万诗琴 | O97: 游泳次卡40次 | P97: 9122514 | Q97: 是 | R97: 否 | S97: 是 | T97: 预约
A98: 46209 | B98: 2923790 | C98: 会籍收入 | D98: 李文聪 | E98: 15071057204 | F98: 月卡 | H98: 全款 | I98: 微信 | J98: 400 | K98: 万诗琴 | O98: 双月卡 | P98: 9122515 | Q98: 是 | R98: 否 | S98: 是 | T98: 预约
A99: 46209 | C99: 教练班收入 | H99: 全款 | I99: 微信 | J99: 1000 | K99: 程浩楠
A100: 46209 | B100: 2923795 | C100: 教练班收入 | D100: 饶书涵 | E100: 158272882 | F100: 长训班 | G100: 25 | H100: 全款 | I100: 微信 | J100: 2999 | K100: 程浩楠 | O100: 25节长训 | P100: 9309299 | Q100: 是 | R100: 否 | S100: 是 | T100: 预约
...

Sheet 游泳装备销售明细表
A1: 游泳装备销售明细表
A2: 日期 | B2: 泳镜 | D2: 泳帽 | F2: 泳衣 | H2: 泳裤 | J2: 三件套（衣） | L2: 三件套（裤） | P2: 纸巾 | R2: 收入 | S2: 成本 | T2: 利润 | U2: 备注
B3: 进价 | C3: 售价 | D3: 进价 | E3: 售价 | F3: 进价 | G3: 售价 | H3: 进价 | I3: 售价 | J3: 进价 | K3: 售价 | L3: 进价 | M3: 售价 | N3: 进价 | O3: 售价 | P3: 进价 | Q3: 售价
B4: 5 | C4: 20 | E4: 10 | G4: 138 | I4: 25 | K4: 168 | M4: 70 | Q4: 1
A5: 月进货 | R5: =$C$4*B5+$E$4*D5+$G$4*F5+$I$4*H5+$K$4*J5+$M$4*L5+$O$4*N5+$Q$4*P5 -> 0 | S5: =$B$4*B5+$D$4*D5+$F$4*F5+$H$4*H5+$J$4*J5+$L$4*L5+$N$4*N5+$P$4*P5 -> 0 | T5: =R5-S5 -> 0
A6: 应有库存量 | R6: =$C$4*B6+$E$4*D6+$G$4*F6+$I$4*H6+$K$4*J6+$M$4*L6+$O$4*N6+$Q$4*P6 -> 0 | S6: =$B$4*B6+$D$4*D6+$F$4*F6+$H$4*H6+$J$4*J6+$L$4*L6+$N$4*N6+$P$4*P6 -> 0 | T6: =R6-S6 -> 0
A7: 实际库存量 | R7: =$C$4*B7+$E$4*D7+$G$4*F7+$I$4*H7+$K$4*J7+$M$4*L7+$O$4*N7+$Q$4*P7 -> 0 | S7: =$B$4*B7+$D$4*D7+$F$4*F7+$H$4*H7+$J$4*J7+$L$4*L7+$N$4*N7+$P$4*P7 -> 0 | T7: =R7-S7 -> 0
A8: 46204 | B8: 2 | D8: 10 | F8: 0 | H8: 0 | J8: 0 | L8: 0 | N8: 0 | P8: 0 | R8: =$C$4*B8+$E$4*D8+$G$4*F8+$I$4*H8+$K$4*J8+$M$4*L8+$O$4*N8+$Q$4*P8 -> 140 | S8: =$B$4*B8+$D$4*D8+$F$4*F8+$H$4*H8+$J$4*J8+$L$4*L8+$N$4*N8+$P$4*P8 -> 10 | T8: =R8-S8 -> 130
A9: 46205 | B9: 2 | D9: 3 | F9: 0 | H9: 1 | J9: 0 | L9: 0 | N9: 0 | P9: 0 | R9: =$C$4*B9+$E$4*D9+$G$4*F9+$I$4*H9+$K$4*J9+$M$4*L9+$O$4*N9+$Q$4*P9 -> 95 | S9: =$B$4*B9+$D$4*D9+$F$4*F9+$H$4*H9+$J$4*J9+$L$4*L9+$N$4*N9+$P$4*P9 -> 10 | T9: =R9-S9 -> 85
A10: 46206 | B10: 3 | D10: 2 | F10: 0 | H10: 0 | J10: 0 | L10: 0 | N10: 0 | P10: 0 | R10: =$C$4*B10+$E$4*D10+$G$4*F10+$I$4*H10+$K$4*J10+$M$4*L10+$O$4*N10+$Q$4*P10 -> 80 | S10: =$B$4*B10+$D$4*D10+$F$4*F10+$H$4*H10+$J$4*J10+$L$4*L10+$N$4*N10+$P$4*P10 -> 15 | T10: =R10-S10 -> 65
A11: 46207 | B11: 1 | D11: 0 | F11: 0 | H11: 0 | J11: 0 | L11: 0 | N11: 0 | P11: 0 | R11: =$C$4*B11+$E$4*D11+$G$4*F11+$I$4*H11+$K$4*J11+$M$4*L11+$O$4*N11+$Q$4*P11 -> 20 | S11: =$B$4*B11+$D$4*D11+$F$4*F11+$H$4*H11+$J$4*J11+$L$4*L11+$N$4*N11+$P$4*P11 -> 5 | T11: =R11-S11 -> 15
A12: 46208 | B12: 0 | D12: 6 | F12: 0 | H12: 2 | J12: 0 | L12: 0 | N12: 0 | P12: 0 | R12: =$C$4*B12+$E$4*D12+$G$4*F12+$I$4*H12+$K$4*J12+$M$4*L12+$O$4*N12+$Q$4*P12 -> 110 | S12: =$B$4*B12+$D$4*D12+$F$4*F12+$H$4*H12+$J$4*J12+$L$4*L12+$N$4*N12+$P$4*P12 -> 0 | T12: =R12-S12 -> 110
A13: 46209 | B13: 2 | D13: 2 | F13: 0 | H13: 1 | J13: 0 | L13: 0 | N13: 0 | P13: 0 | R13: =$C$4*B13+$E$4*D13+$G$4*F13+$I$4*H13+$K$4*J13+$M$4*L13+$O$4*N13+$Q$4*P13 -> 85 | S13: =$B$4*B13+$D$4*D13+$F$4*F13+$H$4*H13+$J$4*J13+$L$4*L13+$N$4*N13+$P$4*P13 -> 10 | T13: =R13-S13 -> 75
A14: 46210 | B14: 0 | D14: 5 | F14: 0 | H14: 1 | J14: 0 | L14: 0 | N14: 0 | P14: 0 | R14: =$C$4*B14+$E$4*D14+$G$4*F14+$I$4*H14+$K$4*J14+$M$4*L14+$O$4*N14+$Q$4*P14 -> 75 | S14: =$B$4*B14+$D$4*D14+$F$4*F14+$H$4*H14+$J$4*J14+$L$4*L14+$N$4*N14+$P$4*P14 -> 0 | T14: =R14-S14 -> 75
A15: 46211 | B15: 0 | D15: 0 | F15: 0 | H15: 0 | J15: 0 | L15: 0 | N15: 0 | P15: 0 | R15: =$C$4*B15+$E$4*D15+$G$4*F15+$I$4*H15+$K$4*J15+$M$4*L15+$O$4*N15+$Q$4*P15 -> 0 | S15: =$B$4*B15+$D$4*D15+$F$4*F15+$H$4*H15+$J$4*J15+$L$4*L15+$N$4*N15+$P$4*P15 -> 0 | T15: =R15-S15 -> 0
A16: 46212 | B16: 1 | D16: 2 | F16: 0 | H16: 0 | J16: 0 | L16: 0 | N16: 0 | P16: 0 | R16: =$C$4*B16+$E$4*D16+$G$4*F16+$I$4*H16+$K$4*J16+$M$4*L16+$O$4*N16+$Q$4*P16 -> 40 | S16: =$B$4*B16+$D$4*D16+$F$4*F16+$H$4*H16+$J$4*J16+$L$4*L16+$N$4*N16+$P$4*P16 -> 5 | T16: =R16-S16 -> 35
A17: 46213 | B17: 2 | D17: 4 | F17: 0 | H17: 0 | J17: 0 | L17: 0 | N17: 0 | P17: 0 | R17: =$C$4*B17+$E$4*D17+$G$4*F17+$I$4*H17+$K$4*J17+$M$4*L17+$O$4*N17+$Q$4*P17 -> 80 | S17: =$B$4*B17+$D$4*D17+$F$4*F17+$H$4*H17+$J$4*J17+$L$4*L17+$N$4*N17+$P$4*P17 -> 10 | T17: =R17-S17 -> 70
A18: 46214 | B18: 3 | D18: 3 | F18: 0 | H18: 2 | J18: 0 | L18: 0 | N18: 0 | P18: 1 | R18: =$C$4*B18+$E$4*D18+$G$4*F18+$I$4*H18+$K$4*J18+$M$4*L18+$O$4*N18+$Q$4*P18 -> 141 | S18: =$B$4*B18+$D$4*D18+$F$4*F18+$H$4*H18+$J$4*J18+$L$4*L18+$N$4*N18+$P$4*P18 -> 15 | T18: =R18-S18 -> 126
A19: 46215 | B19: 1 | D19: 5 | F19: 0 | H19: 1 | J19: 0 | L19: 0 | N19: 0 | P19: 0 | R19: =$C$4*B19+$E$4*D19+$G$4*F19+$I$4*H19+$K$4*J19+$M$4*L19+$O$4*N19+$Q$4*P19 -> 95 | S19: =$B$4*B19+$D$4*D19+$F$4*F19+$H$4*H19+$J$4*J19+$L$4*L19+$N$4*N19+$P$4*P19 -> 5 | T19: =R19-S19 -> 90
A20: 46216 | R20: =$C$4*B20+$E$4*D20+$G$4*F20+$I$4*H20+$K$4*J20+$M$4*L20+$O$4*N20+$Q$4*P20 -> 0 | S20: =$B$4*B20+$D$4*D20+$F$4*F20+$H$4*H20+$J$4*J20+$L$4*L20+$N$4*N20+$P$4*P20 -> 0 | T20: =R20-S20 -> 0
A21: 46217 | R21: =$C$4*B21+$E$4*D21+$G$4*F21+$I$4*H21+$K$4*J21+$M$4*L21+$O$4*N21+$Q$4*P21 -> 0 | S21: =$B$4*B21+$D$4*D21+$F$4*F21+$H$4*H21+$J$4*J21+$L$4*L21+$N$4*N21+$P$4*P21 -> 0 | T21: =R21-S21 -> 0
A22: 46218 | R22: =$C$4*B22+$E$4*D22+$G$4*F22+$I$4*H22+$K$4*J22+$M$4*L22+$O$4*N22+$Q$4*P22 -> 0 | S22: =$B$4*B22+$D$4*D22+$F$4*F22+$H$4*H22+$J$4*J22+$L$4*L22+$N$4*N22+$P$4*P22 -> 0 | T22: =R22-S22 -> 0
A23: 46219 | R23: =$C$4*B23+$E$4*D23+$G$4*F23+$I$4*H23+$K$4*J23+$M$4*L23+$O$4*N23+$Q$4*P23 -> 0 | S23: =$B$4*B23+$D$4*D23+$F$4*F23+$H$4*H23+$J$4*J23+$L$4*L23+$N$4*N23+$P$4*P23 -> 0 | T23: =R23-S23 -> 0
A24: 46220 | R24: =$C$4*B24+$E$4*D24+$G$4*F24+$I$4*H24+$K$4*J24+$M$4*L24+$O$4*N24+$Q$4*P24 -> 0 | S24: =$B$4*B24+$D$4*D24+$F$4*F24+$H$4*H24+$J$4*J24+$L$4*L24+$N$4*N24+$P$4*P24 -> 0 | T24: =R24-S24 -> 0
A25: 46221 | R25: =$C$4*B25+$E$4*D25+$G$4*F25+$I$4*H25+$K$4*J25+$M$4*L25+$O$4*N25+$Q$4*P25 -> 0 | S25: =$B$4*B25+$D$4*D25+$F$4*F25+$H$4*H25+$J$4*J25+$L$4*L25+$N$4*N25+$P$4*P25 -> 0 | T25: =R25-S25 -> 0
A26: 46222 | R26: =$C$4*B26+$E$4*D26+$G$4*F26+$I$4*H26+$K$4*J26+$M$4*L26+$O$4*N26+$Q$4*P26 -> 0 | S26: =$B$4*B26+$D$4*D26+$F$4*F26+$H$4*H26+$J$4*J26+$L$4*L26+$N$4*N26+$P$4*P26 -> 0 | T26: =R26-S26 -> 0
A27: 46223 | R27: =$C$4*B27+$E$4*D27+$G$4*F27+$I$4*H27+$K$4*J27+$M$4*L27+$O$4*N27+$Q$4*P27 -> 0 | S27: =$B$4*B27+$D$4*D27+$F$4*F27+$H$4*H27+$J$4*J27+$L$4*L27+$N$4*N27+$P$4*P27 -> 0 | T27: =R27-S27 -> 0
A28: 46224 | R28: =$C$4*B28+$E$4*D28+$G$4*F28+$I$4*H28+$K$4*J28+$M$4*L28+$O$4*N28+$Q$4*P28 -> 0 | S28: =$B$4*B28+$D$4*D28+$F$4*F28+$H$4*H28+$J$4*J28+$L$4*L28+$N$4*N28+$P$4*P28 -> 0 | T28: =R28-S28 -> 0
A29: 46225 | R29: =$C$4*B29+$E$4*D29+$G$4*F29+$I$4*H29+$K$4*J29+$M$4*L29+$O$4*N29+$Q$4*P29 -> 0 | S29: =$B$4*B29+$D$4*D29+$F$4*F29+$H$4*H29+$J$4*J29+$L$4*L29+$N$4*N29+$P$4*P29 -> 0 | T29: =R29-S29 -> 0
A30: 46226 | R30: =$C$4*B30+$E$4*D30+$G$4*F30+$I$4*H30+$K$4*J30+$M$4*L30+$O$4*N30+$Q$4*P30 -> 0 | S30: =$B$4*B30+$D$4*D30+$F$4*F30+$H$4*H30+$J$4*J30+$L$4*L30+$N$4*N30+$P$4*P30 -> 0 | T30: =R30-S30 -> 0
A31: 46227 | R31: =$C$4*B31+$E$4*D31+$G$4*F31+$I$4*H31+$K$4*J31+$M$4*L31+$O$4*N31+$Q$4*P31 -> 0 | S31: =$B$4*B31+$D$4*D31+$F$4*F31+$H$4*H31+$J$4*J31+$L$4*L31+$N$4*N31+$P$4*P31 -> 0 | T31: =R31-S31 -> 0
... A38: 46234 | R38: =$C$4*B38+$E$4*D38+$G$4*F38+$I$4*H38+$K$4*J38+$M$4*L38+$O$4*N38+$Q$4*P38 -> 0 | S38: =$B$4*B38+$D$4*D38+$F$4*F38+$H$4*H38+$J$4*J38+$L$4*L38+$N$4*N38+$P$4*P38 -> 0 | T38: =R38-S38 -> 0
A39: 7月合计 | B39: =SUM(B9:C38) -> 15 | D39: =SUM(D9:E38) -> 32 | F39: =SUM(F9:G38) -> 0 | H39: =SUM(H9:I38) -> 8 | J39: =SUM(J9:K38) -> 0 | L39: =SUM(L9:M38) -> 0 | N39: =SUM(N9:O38) -> 0 | P39: =SUM(P9:Q38) -> 1 | R39: =SUM(R9:R38) -> 821 | S39: =SUM(S9:S38) -> 75 | T39: =SUM(T9:T38) -> 746

Sheet 水吧销售明细表
A1: 水吧销售明细表
A2: 日期 | B2: 农夫山泉 | D2: 脉动 | F2: 电解质 | H2: 元气森林 | J2: 手帕纸 | L2: 冰茶 | N2: 大电解质 | P2: 二厂苏打水 | R2: 外星人维c水 | T2: 外星人wave | V2: 收入 | W2: 成本 | X2: 利润 | Y2: 备注
B3: 进价 | C3: 售价 | D3: 进价 | E3: 售价 | F3: 进价 | G3: 售价 | H3: 进价 | I3: 售价 | J3: 进价 | K3: 售价 | L3: 进价 | M3: 售价 | N3: 进价 | O3: 售价 | P3: 进价 | Q3: 售价 | R3: 进价 | S3: 售价 | T3: 进价 | U3: 售价
B4: 1.05 | C4: 2 | D4: 3.67 | E4: 5 | F4: 4.34 | G4: 7 | H4: 3.54 | I4: 5 | K4: 1 | L4: 2.8 | M4: 5 | N4: 5.34 | O4: 8 | P4: 1.7 | Q4: 3 | R4: 0 | S4: 5 | T4: 0 | U4: 4
A5: 46204 | B5: 3 | D5: 6 | F5: 3 | H5: 0 | J5: 1 | L5: 0 | N5: 0 | P5: 0 | R5: 0 | T5: 0 | V5: =$C$4*B5+$E$4*D5+$G$4*F5+$I$4*H5+$K$4*J5+$M$4*L5+$O$4*N5+$Q$4*P5+$S$4*R5+$U$4*T5 -> 58 | W5: =$C$4*C5+$E$4*E5+$G$4*G5+$I$4*I5+$K$4*K5+$M$4*M5+$O$4*O5+$Q$4*Q5+$S$4*S5+$U$4*U5 -> 0 | X5: =$C$4*D5+$E$4*F5+$G$4*H5+$I$4*J5+$K$4*L5+$M$4*N5+$O$4*P5+$Q$4*R5+$S$4*T5+$U$4*V5 -> 264
A6: 46205 | B6: 4 | D6: 1 | F6: 0 | H6: 0 | J6: 0 | L6: 1 | N6: 0 | P6: 0 | R6: 0 | T6: 0 | V6: =$C$4*B6+$E$4*D6+$G$4*F6+$I$4*H6+$K$4*J6+$M$4*L6+$O$4*N6+$Q$4*P6+$S$4*R6+$U$4*T6 -> 18 | W6: =$C$4*C6+$E$4*E6+$G$4*G6+$I$4*I6+$K$4*K6+$M$4*M6+$O$4*O6+$Q$4*Q6+$S$4*S6+$U$4*U6 -> 0 | X6: =$C$4*D6+$E$4*F6+$G$4*H6+$I$4*J6+$K$4*L6+$M$4*N6+$O$4*P6+$Q$4*R6+$S$4*T6+$U$4*V6 -> 75
A7: 46206 | B7: 3 | D7: 3 | F7: 0 | H7: 0 | J7: 2 | L7: 0 | N7: 0 | P7: 0 | R7: 0 | T7: 0 | V7: =$C$4*B7+$E$4*D7+$G$4*F7+$I$4*H7+$K$4*J7+$M$4*L7+$O$4*N7+$Q$4*P7+$S$4*R7+$U$4*T7 -> 23 | W7: =$C$4*C7+$E$4*E7+$G$4*G7+$I$4*I7+$K$4*K7+$M$4*M7+$O$4*O7+$Q$4*Q7+$S$4*S7+$U$4*U7 -> 0 | X7: =$C$4*D7+$E$4*F7+$G$4*H7+$I$4*J7+$K$4*L7+$M$4*N7+$O$4*P7+$Q$4*R7+$S$4*T7+$U$4*V7 -> 108
A8: 46207 | B8: 2 | D8: 3 | F8: 1 | H8: 0 | J8: 1 | L8: 0 | N8: 0 | P8: 0 | R8: 0 | T8: 0 | V8: =$C$4*B8+$E$4*D8+$G$4*F8+$I$4*H8+$K$4*J8+$M$4*L8+$O$4*N8+$Q$4*P8+$S$4*R8+$U$4*T8 -> 27 | W8: =$C$4*C8+$E$4*E8+$G$4*G8+$I$4*I8+$K$4*K8+$M$4*M8+$O$4*O8+$Q$4*Q8+$S$4*S8+$U$4*U8 -> 0 | X8: =$C$4*D8+$E$4*F8+$G$4*H8+$I$4*J8+$K$4*L8+$M$4*N8+$O$4*P8+$Q$4*R8+$S$4*T8+$U$4*V8 -> 124
A9: 46208 | B9: 6 | D9: 1 | F9: 0 | H9: 0 | J9: 1 | L9: 1 | N9: 0 | P9: 0 | R9: 2 | T9: 0 | V9: =$C$4*B9+$E$4*D9+$G$4*F9+$I$4*H9+$K$4*J9+$M$4*L9+$O$4*N9+$Q$4*P9+$S$4*R9+$U$4*T9 -> 33 | W9: =$C$4*C9+$E$4*E9+$G$4*G9+$I$4*I9+$K$4*K9+$M$4*M9+$O$4*O9+$Q$4*Q9+$S$4*S9+$U$4*U9 -> 0 | X9: =$C$4*D9+$E$4*F9+$G$4*H9+$I$4*J9+$K$4*L9+$M$4*N9+$O$4*P9+$Q$4*R9+$S$4*T9+$U$4*V9 -> 146
A10: 46209 | B10: 6 | D10: 1 | F10: 2 | H10: 0 | J10: 0 | L10: 0 | N10: 0 | P10: 0 | R10: 0 | T10: 0 | V10: =$C$4*B10+$E$4*D10+$G$4*F10+$I$4*H10+$K$4*J10+$M$4*L10+$O$4*N10+$Q$4*P10+$S$4*R10+$U$4*T10 -> 31 | W10: =$C$4*C10+$E$4*E10+$G$4*G10+$I$4*I10+$K$4*K10+$M$4*M10+$O$4*O10+$Q$4*Q10+$S$4*S10+$U$4*U10 -> 0 | X10: =$C$4*D10+$E$4*F10+$G$4*H10+$I$4*J10+$K$4*L10+$M$4*N10+$O$4*P10+$Q$4*R10+$S$4*T10+$U$4*V10 -> 136
A11: 46210 | B11: 7 | D11: 2 | F11: 0 | H11: 0 | J11: 0 | L11: 0 | N11: 0 | P11: 0 | R11: 0 | T11: 0 | V11: =$C$4*B11+$E$4*D11+$G$4*F11+$I$4*H11+$K$4*J11+$M$4*L11+$O$4*N11+$Q$4*P11+$S$4*R11+$U$4*T11 -> 24 | W11: =$C$4*C11+$E$4*E11+$G$4*G11+$I$4*I11+$K$4*K11+$M$4*M11+$O$4*O11+$Q$4*Q11+$S$4*S11+$U$4*U11 -> 0 | X11: =$C$4*D11+$E$4*F11+$G$4*H11+$I$4*J11+$K$4*L11+$M$4*N11+$O$4*P11+$Q$4*R11+$S$4*T11+$U$4*V11 -> 100
A12: 46211 | B12: 4 | D12: 4 | F12: 0 | H12: 0 | J12: 3 | L12: 1 | N12: 0 | P12: 0 | R12: 2 | T12: 0 | V12: =$C$4*B12+$E$4*D12+$G$4*F12+$I$4*H12+$K$4*J12+$M$4*L12+$O$4*N12+$Q$4*P12+$S$4*R12+$U$4*T12 -> 46 | W12: =$C$4*C12+$E$4*E12+$G$4*G12+$I$4*I12+$K$4*K12+$M$4*M12+$O$4*O12+$Q$4*Q12+$S$4*S12+$U$4*U12 -> 0 | X12: =$C$4*D12+$E$4*F12+$G$4*H12+$I$4*J12+$K$4*L12+$M$4*N12+$O$4*P12+$Q$4*R12+$S$4*T12+$U$4*V12 -> 214
A13: 46212 | B13: 2 | D13: 3 | F13: 0 | H13: 0 | J13: 1 | L13: 1 | N13: 0 | P13: 0 | R13: 0 | T13: 0 | V13: =$C$4*B13+$E$4*D13+$G$4*F13+$I$4*H13+$K$4*J13+$M$4*L13+$O$4*N13+$Q$4*P13+$S$4*R13+$U$4*T13 -> 25 | W13: =$C$4*C13+$E$4*E13+$G$4*G13+$I$4*I13+$K$4*K13+$M$4*M13+$O$4*O13+$Q$4*Q13+$S$4*S13+$U$4*U13 -> 0 | X13: =$C$4*D13+$E$4*F13+$G$4*H13+$I$4*J13+$K$4*L13+$M$4*N13+$O$4*P13+$Q$4*R13+$S$4*T13+$U$4*V13 -> 112
A14: 46213 | B14: 3 | D14: 0 | F14: 5 | H14: 0 | J14: 1 | L14: 1 | N14: 0 | P14: 0 | R14: 1 | T14: 0 | V14: =$C$4*B14+$E$4*D14+$G$4*F14+$I$4*H14+$K$4*J14+$M$4*L14+$O$4*N14+$Q$4*P14+$S$4*R14+$U$4*T14 -> 52 | W14: =$C$4*C14+$E$4*E14+$G$4*G14+$I$4*I14+$K$4*K14+$M$4*M14+$O$4*O14+$Q$4*Q14+$S$4*S14+$U$4*U14 -> 0 | X14: =$C$4*D14+$E$4*F14+$G$4*H14+$I$4*J14+$K$4*L14+$M$4*N14+$O$4*P14+$Q$4*R14+$S$4*T14+$U$4*V14 -> 242
A15: 46214 | B15: 0 | D15: 0 | F15: 0 | H15: 0 | J15: 1 | L15: 1 | N15: 0 | P15: 0 | R15: 0 | T15: 0 | V15: =$C$4*B15+$E$4*D15+$G$4*F15+$I$4*H15+$K$4*J15+$M$4*L15+$O$4*N15+$Q$4*P15+$S$4*R15+$U$4*T15 -> 6 | W15: =$C$4*C15+$E$4*E15+$G$4*G15+$I$4*I15+$K$4*K15+$M$4*M15+$O$4*O15+$Q$4*Q15+$S$4*S15+$U$4*U15 -> 0 | X15: =$C$4*D15+$E$4*F15+$G$4*H15+$I$4*J15+$K$4*L15+$M$4*N15+$O$4*P15+$Q$4*R15+$S$4*T15+$U$4*V15 -> 30
A16: 46215 | B16: 2 | D16: 0 | F16: 1 | H16: 0 | J16: 0 | L16: 0 | N16: 0 | P16: 0 | R16: 0 | T16: 0 | V16: =$C$4*B16+$E$4*D16+$G$4*F16+$I$4*H16+$K$4*J16+$M$4*L16+$O$4*N16+$Q$4*P16+$S$4*R16+$U$4*T16 -> 11 | W16: =$C$4*C16+$E$4*E16+$G$4*G16+$I$4*I16+$K$4*K16+$M$4*M16+$O$4*O16+$Q$4*Q16+$S$4*S16+$U$4*U16 -> 0 | X16: =$C$4*D16+$E$4*F16+$G$4*H16+$I$4*J16+$K$4*L16+$M$4*N16+$O$4*P16+$Q$4*R16+$S$4*T16+$U$4*V16 -> 49
A17: 46216 | V17: =$C$4*B17+$E$4*D17+$G$4*F17+$I$4*H17+$K$4*J17+$M$4*L17+$O$4*N17+$Q$4*P17+$S$4*R17+$U$4*T17 -> 0 | W17: =$C$4*C17+$E$4*E17+$G$4*G17+$I$4*I17+$K$4*K17+$M$4*M17+$O$4*O17+$Q$4*Q17+$S$4*S17+$U$4*U17 -> 0 | X17: =$C$4*D17+$E$4*F17+$G$4*H17+$I$4*J17+$K$4*L17+$M$4*N17+$O$4*P17+$Q$4*R17+$S$4*T17+$U$4*V17 -> 0
A18: 46217 | V18: =$C$4*B18+$E$4*D18+$G$4*F18+$I$4*H18+$K$4*J18+$M$4*L18+$O$4*N18+$Q$4*P18+$S$4*R18+$U$4*T18 -> 0 | W18: =$C$4*C18+$E$4*E18+$G$4*G18+$I$4*I18+$K$4*K18+$M$4*M18+$O$4*O18+$Q$4*Q18+$S$4*S18+$U$4*U18 -> 0 | X18: =$C$4*D18+$E$4*F18+$G$4*H18+$I$4*J18+$K$4*L18+$M$4*N18+$O$4*P18+$Q$4*R18+$S$4*T18+$U$4*V18 -> 0
A19: 46218 | V19: =$C$4*B19+$E$4*D19+$G$4*F19+$I$4*H19+$K$4*J19+$M$4*L19+$O$4*N19+$Q$4*P19+$S$4*R19+$U$4*T19 -> 0 | W19: =$C$4*C19+$E$4*E19+$G$4*G19+$I$4*I19+$K$4*K19+$M$4*M19+$O$4*O19+$Q$4*Q19+$S$4*S19+$U$4*U19 -> 0 | X19: =$C$4*D19+$E$4*F19+$G$4*H19+$I$4*J19+$K$4*L19+$M$4*N19+$O$4*P19+$Q$4*R19+$S$4*T19+$U$4*V19 -> 0
A20: 46219 | V20: =$C$4*B20+$E$4*D20+$G$4*F20+$I$4*H20+$K$4*J20+$M$4*L20+$O$4*N20+$Q$4*P20+$S$4*R20+$U$4*T20 -> 0 | W20: =$C$4*C20+$E$4*E20+$G$4*G20+$I$4*I20+$K$4*K20+$M$4*M20+$O$4*O20+$Q$4*Q20+$S$4*S20+$U$4*U20 -> 0 | X20: =$C$4*D20+$E$4*F20+$G$4*H20+$I$4*J20+$K$4*L20+$M$4*N20+$O$4*P20+$Q$4*R20+$S$4*T20+$U$4*V20 -> 0
A21: 46220 | V21: =$C$4*B21+$E$4*D21+$G$4*F21+$I$4*H21+$K$4*J21+$M$4*L21+$O$4*N21+$Q$4*P21+$S$4*R21+$U$4*T21 -> 0 | W21: =$C$4*C21+$E$4*E21+$G$4*G21+$I$4*I21+$K$4*K21+$M$4*M21+$O$4*O21+$Q$4*Q21+$S$4*S21+$U$4*U21 -> 0 | X21: =$C$4*D21+$E$4*F21+$G$4*H21+$I$4*J21+$K$4*L21+$M$4*N21+$O$4*P21+$Q$4*R21+$S$4*T21+$U$4*V21 -> 0
A22: 46221 | V22: =$C$4*B22+$E$4*D22+$G$4*F22+$I$4*H22+$K$4*J22+$M$4*L22+$O$4*N22+$Q$4*P22+$S$4*R22+$U$4*T22 -> 0 | W22: =$C$4*C22+$E$4*E22+$G$4*G22+$I$4*I22+$K$4*K22+$M$4*M22+$O$4*O22+$Q$4*Q22+$S$4*S22+$U$4*U22 -> 0 | X22: =$C$4*D22+$E$4*F22+$G$4*H22+$I$4*J22+$K$4*L22+$M$4*N22+$O$4*P22+$Q$4*R22+$S$4*T22+$U$4*V22 -> 0
A23: 46222 | V23: =$C$4*B23+$E$4*D23+$G$4*F23+$I$4*H23+$K$4*J23+$M$4*L23+$O$4*N23+$Q$4*P23+$S$4*R23+$U$4*T23 -> 0 | W23: =$C$4*C23+$E$4*E23+$G$4*G23+$I$4*I23+$K$4*K23+$M$4*M23+$O$4*O23+$Q$4*Q23+$S$4*S23+$U$4*U23 -> 0 | X23: =$C$4*D23+$E$4*F23+$G$4*H23+$I$4*J23+$K$4*L23+$M$4*N23+$O$4*P23+$Q$4*R23+$S$4*T23+$U$4*V23 -> 0
A24: 46223 | V24: =$C$4*B24+$E$4*D24+$G$4*F24+$I$4*H24+$K$4*J24+$M$4*L24+$O$4*N24+$Q$4*P24+$S$4*R24+$U$4*T24 -> 0 | W24: =$C$4*C24+$E$4*E24+$G$4*G24+$I$4*I24+$K$4*K24+$M$4*M24+$O$4*O24+$Q$4*Q24+$S$4*S24+$U$4*U24 -> 0 | X24: =$C$4*D24+$E$4*F24+$G$4*H24+$I$4*J24+$K$4*L24+$M$4*N24+$O$4*P24+$Q$4*R24+$S$4*T24+$U$4*V24 -> 0
A25: 46224 | V25: =$C$4*B25+$E$4*D25+$G$4*F25+$I$4*H25+$K$4*J25+$M$4*L25+$O$4*N25+$Q$4*P25+$S$4*R25+$U$4*T25 -> 0 | W25: =$C$4*C25+$E$4*E25+$G$4*G25+$I$4*I25+$K$4*K25+$M$4*M25+$O$4*O25+$Q$4*Q25+$S$4*S25+$U$4*U25 -> 0 | X25: =$C$4*D25+$E$4*F25+$G$4*H25+$I$4*J25+$K$4*L25+$M$4*N25+$O$4*P25+$Q$4*R25+$S$4*T25+$U$4*V25 -> 0
A26: 46225 | V26: =$C$4*B26+$E$4*D26+$G$4*F26+$I$4*H26+$K$4*J26+$M$4*L26+$O$4*N26+$Q$4*P26+$S$4*R26+$U$4*T26 -> 0 | W26: =$C$4*C26+$E$4*E26+$G$4*G26+$I$4*I26+$K$4*K26+$M$4*M26+$O$4*O26+$Q$4*Q26+$S$4*S26+$U$4*U26 -> 0 | X26: =$C$4*D26+$E$4*F26+$G$4*H26+$I$4*J26+$K$4*L26+$M$4*N26+$O$4*P26+$Q$4*R26+$S$4*T26+$U$4*V26 -> 0
A27: 46226 | V27: =$C$4*B27+$E$4*D27+$G$4*F27+$I$4*H27+$K$4*J27+$M$4*L27+$O$4*N27+$Q$4*P27+$S$4*R27+$U$4*T27 -> 0 | W27: =$C$4*C27+$E$4*E27+$G$4*G27+$I$4*I27+$K$4*K27+$M$4*M27+$O$4*O27+$Q$4*Q27+$S$4*S27+$U$4*U27 -> 0 | X27: =$C$4*D27+$E$4*F27+$G$4*H27+$I$4*J27+$K$4*L27+$M$4*N27+$O$4*P27+$Q$4*R27+$S$4*T27+$U$4*V27 -> 0
A28: 46227 | V28: =$C$4*B28+$E$4*D28+$G$4*F28+$I$4*H28+$K$4*J28+$M$4*L28+$O$4*N28+$Q$4*P28+$S$4*R28+$U$4*T28 -> 0 | W28: =$C$4*C28+$E$4*E28+$G$4*G28+$I$4*I28+$K$4*K28+$M$4*M28+$O$4*O28+$Q$4*Q28+$S$4*S28+$U$4*U28 -> 0 | X28: =$C$4*D28+$E$4*F28+$G$4*H28+$I$4*J28+$K$4*L28+$M$4*N28+$O$4*P28+$Q$4*R28+$S$4*T28+$U$4*V28 -> 0
... A35: 46234 | V35: =$C$4*B35+$E$4*D35+$G$4*F35+$I$4*H35+$K$4*J35+$M$4*L35+$O$4*N35+$Q$4*P35+$S$4*R35+$U$4*T35 -> 0 | W35: =$C$4*C35+$E$4*E35+$G$4*G35+$I$4*I35+$K$4*K35+$M$4*M35+$O$4*O35+$Q$4*Q35+$S$4*S35+$U$4*U35 -> 0 | X35: =$C$4*D35+$E$4*F35+$G$4*H35+$I$4*J35+$K$4*L35+$M$4*N35+$O$4*P35+$Q$4*R35+$S$4*T35+$U$4*V35 -> 0
A36: 7月合计 | B36: =SUM(B5:C35) -> 42 | D36: =SUM(D5:E35) -> 24 | F36: =SUM(F5:G35) -> 12 | H36: =SUM(H5:I35) -> 0 | J36: =SUM(J5:K35) -> 11 | L36: =SUM(L5:M35) -> 6 | N36: =SUM(N5:O35) -> 0 | P36: =SUM(P5:Q35) -> 0 | R36: =SUM(R5:S35) -> 5 | T36: =SUM(T5:U35) -> 0 | V36: =SUM(V5:V35) -> 354 | W36: =SUM(W5:W35) -> 0 | X36: =SUM(X5:X35) -> 1600
Q39: 3

Sheet 发票信息登记表
A1: 日期 | B1: 会员姓名 | C1: 联系方式 | D1: 发票抬头 | H1: 开票金额 | I1: 开票情况
D2: 开票名称 | E2: 开票税号 | F2: 开票地址、电话 | G2: 开票账户
A3: 45539 | B3: 张利利 | C3: 13923808320 | D3: 武汉欧瑞景环保科技有限公司 | E3: 91420112 MA4KLDHP5M | F3: 洪山区南李路27号圣爱米伦科研部分G栋1单元1-19层地址、 电话:1205号027-87171898 | G3: 开户行及账号:中国农业银行武汉南湖支行 1703 1101040015736 | H3: 1500 | I3: 已开
A4: 45539 | B4: 张利利 | C4: 13923808320 | D4: 武汉欧瑞景环保科技有限公司 | E4: 91420112 MA4KLDHP5M | F4: 洪山区南李路27号圣爱米伦科研部分G栋1单元1-19层地址、 电话:1205号027-87171898 | G4: 开户行及账号:中国农业银行武汉南湖支行 1703 1101040015736 | H4: 1800 | I4: 已开
A5: 45539 | B5: 李尹幻 | C5: 13986684439 | D5: 薯一薯二文化传媒（武汉）有限公司 | E5: 91420100MADM5GFX7Q | F5: 湖北省武汉市东湖新技术开发区光谷三路777号移动终端产业园1号楼4层410、411、412号410-041 电 话：027-59359862 | G5: 招商银行股份有限公司武汉光谷科技支行 银行账号：127921008610009 | H5: 2000 | I5: 已开
A6: 45546 | B6: 陈玲 | C6: 13429870309 | D6: 武汉创信智谷商业地产有限公司 | E6: 91420106MA49B9F29Y | F6: 湖北省武汉市洪山区洪山街道文化大道555号融创智谷B2栋2层7号 | G6: 兴业银行武汉分行营业部 银行账户:416010100102192417 | H6: 3000 | I6: 已开
A7: 45553 | B7: 李尹幻 | C7: 13986684439 | D7: 薯一薯二文化传媒（武汉）有限公司 | E7: 91420100MADM5GFX7Q | F7: 湖北省武汉市东湖新技术开发区光谷三路777号移动终端产业园1号楼4层410、411、412号410-041 电 话：027-59359862 | G7: 银行名称：招商银行股份有限公司武汉光谷科技支行 银行账号：127921008610009 | H7: 1200 | I7: 已开
A8: 45553 | B8: 林朝举 | C8: 13871486083 | D8: 武汉海实电气有限公司 | E8: 91420100568371285T | F8: 地址、电话:武汉市东湖新技术开发区光谷大道62号关南福星 医药园8幢3层5号房 07-87207853 | G8: 开户行:工行武汉黄金山支行不平 帐号:3202162919060003497 | H8: 1500 | I8: 已开
A9: 45554 | B9: 方片 | C9: 18601945242 | D9: 薯一薯二文化传媒（武汉）有限公司 | E9: 91420100MADM5GFX7Q | F9: 湖北省武汉市东湖新技术开发区光谷三路777号移动终端产业园 1号楼4层410、411、412号410-041 电 话：027-59359862 | G9: 招商银行股份有限公司武汉光谷科技支行 银行账号：127921008610009 | H9: 2400 | I9: 已开
A10: 45554 | B10: Daniel | C10: 18462102737 | D10: 上海艾奚科技有限公司 | E10: 91310116MADBJW909U | F10: 上海市金山区亭林镇兴工路225号1幢 | G10: 开户银行：招商银行股份有限公司上 海安亭支行银行账户：121953754310000 | H10: 4599 | I10: 已开
A11: 45556 | B11: 胡珺玲 | C11: 13986275913 | D11: 武汉杰睿斯科生物科技有限公司 | E11: 91420106MA4KRF406N | F11: 武昌区南湖街北港村南国南湖城市广场3栋19层1室15972902427 | G11: 华夏银行武汉雄楚 支行11161000000956085 | H11: 1000 | I11: 已开
A12: 45577 | B12: 王淑琴 | C12: 15527172405 | D12: 朗新科技集团股份有限公司 | E12: 91320200747189665N | F12: 无锡新吴区净慧东道118号1楼 | G12: 开户行及账号:中国工商银行股份有限公司无锡新吴支行 1103020819200405492 | H12: 2000 | I12: 已开
A13: 45590 | B13: 李尹幻 | C13: 13986684439 | D13: 薯一薯二文化传媒（武汉）有限公司 | E13: 91420100MADM5GFX7Q | F13: 湖北省武汉市东湖新技术开发区光谷三路777号移动终端产业园 1号楼4层410、411、412号410-041 电 话：027-59359862 | G13: 招商银行股份有限公司武汉光谷科技支行 银行账号：127921008610009 | H13: 1200 | I13: 已开
A14: 45590 | B14: 黄宇轩 | C14: 15970272771 | D14: 薯一薯二文化传媒（武汉）有限公司 | E14: 91420100MADM5GFX7Q | F14: 湖北省武汉市东湖新技术开发区光谷三路777号移动终端产业园 1号楼4层410、411、412号410-041 电 话：027-59359862 | G14: 招商银行股份有限公司武汉光谷科技支行 银行账号：127921008610009 | H14: 260 | I14: 已开
A15: 45593 | B15: 舒月 | C15: 18007176848 | D15: 武汉潍动机电设备有限公司 | E15: 91420104MA49ML6Q0N | F15: 武汉市硚口区汉西新村保利香槟国际（ B 区） 10 栋 10 层 5 号 电话： 027-85834655 | G15: 开户行： 中国银行武汉万松支行 账号： 5755 7965 4099 | H15: 1699 | I15: 已开
A16: 45594 | B16: 余家豪 | C16: 18773790598 | D16: 南拳互娱(武汉)文化传媒有限公司 | E16: 91420100MA4KYH1C9R | H16: 200 | I16: 已开
A17: 45597 | B17: 李尹幻 | C17: 13986684439 | D17: 薯一薯二文化传媒（武汉）有限公司 | E17: 91420100MADM5GFX7Q | F17: 湖北省武汉市东湖新技术开发区光谷三路777号移动终 端产业园1号楼4层410、411、412号410-041电 话：027-59359862 | G17: 银行名称：招商银行股份有限公司武汉光谷科技支行银行账号：127921008610009 | H17: 3000 | I17: 已开
A18: 45601 | B18: 方芳 | C18: 13554308155 | D18: 薯一薯二文化传媒（武汉）有限公司 | E18: 91420100MADM5GFX7Q | F18: 地 址：湖北省武汉市东湖新技术开发区光谷三路777号移动终端产业园1号楼4层410、411、412号410-041 电 话：027-59359862 | G18: 银行名称：招商银行股份有限公司武汉光谷科技支行 银行账号：127921008610009 | H18: 2250 | I18: 已开
A19: 45610 | B19: 汪娟 | C19: 18271944820 | D19: 武汉奥浦信息技术有限公司 | E19: 9142010057490421X6 | F19: 地址电话:武汉市东湖新技术开发区黄龙山南路2号 光谷光电信息产业创新创业基地一期2幢13层1301 027-87581008 | G19: 开户行及账号:工商银行武汉软件园支行 3202105809100010890 | H19: 1111 | I19: 已开
A20: 45622 | B20: 张利利 | C20: 13923808320 | D20: 武汉欧瑞景环保科技有限公司 | E20: 91420112 MA4KLDHP5M | F20: 洪山区南李路27号圣爱米伦科研部分G栋1单元1-19层地址、 电话:1205号027-87171898 | G20: 开户行及账号:中国农业银行武汉南湖支行 1703 1101040015736 | H20: 3600 | I20: 已开
A21: 45622 | B21: 张利利 | C21: 13923808320 | D21: 武汉欧瑞景环保科技有限公司 | E21: 91420112 MA4KLDHP5M | F21: 洪山区南李路27号圣爱米伦科研部分G栋1单元1-19层地址、 电话:1205号027-87171898 | G21: 开户行及账号:中国农业银行武汉南湖支行 1703 1101040015736 | H21: 3400 | I21: 已开
A22: 45626 | B22: 金凌云 | C22: 13545090900 | H22: 1500 | I22: 已开
A23: 45627 | B23: 黄锦跃 | C23: 13007102777 | D23: 武汉世凡宜美建筑工程有限公司 | E23: 91420111MA49H8E815 | G23: 开户银行:中国农业银行股份有限公司武汉佳丽广场支行 银行账号号:17008801040019195 | H23: 1111 | I23: 已开
A24: 45628 | B24: 郭文 | C24: 18530021868 | H24: 2650 | I24: 已开
A25: 45631 | B25: 蒋丽云 | C25: 13971547428 | H25: 3580 | I25: 已开
A26: 45649 | B26: 李文麒 | C26: 18672329706 | D26: 湖北富瑞尔科技有限公司 | F26: 电话027-81822188 | H26: 3000 | I26: 已开
A27: 45651 | B27: 王龙英 | C27: 18963970563 | D27: 北京路宇葛务虚文化传播有限公司 | E27: 91110112MACWMY2K7M | H27: 1500 | I27: 已开
A28: 45651 | B28: 吴璇卿 | C28: 18772819313 | D28: 北京路宇葛务虚文化传播有限公司 | E28: 91110112MACWMY2K7M | H28: 1611 | I28: 已开
A29: 45651 | B29: 黄霞 | C29: 18971529929 | D29: 北京路宇葛务虚文化传播有限公司 | E29: 91110112MACWMY2K7M | H29: 1611 | I29: 已开
A30: 45656 | B30: 胡润 | C30: 13675691174 | D30: 北京路宇葛务虚文化传播有限公司 | E30: 91110112MACWMY2K7M | H30: 1611 | I30: 已开
A31: 45663 | B31: 王淑琴 | C31: 15527172405 | D31: 朗新科技集团股份有限公司 | E31: 91320200747189665N | F31: 无锡新吴区净慧东道118号1楼 0510-66676999 | G31: 中国工商银行股份有限公司无锡新吴支行 1103020819200405492 | H31: 2000 | I31: 已开
A32: 45670 | B32: 陈欢 | C32: 15527354576 | D32: 薯一薯二文化传媒（武汉）有限公司 | E32: 91420100MADM5GFX7Q | F32: 地 址：湖北省武汉市东湖新技术开发区光谷三路777号移动终端产业园1号楼4层410、411、412号410-041 电 话：027-59359862 | G32: 银行名称：招商银行股份有限公司武汉光谷科技支行 银行账号：127921008610009 | H32: 2250 | I32: 已开
A33: 45697 | B33: 邵钰琳 | C33: 13080618621 | D33: 青岛惠都食品有限公司 | E33: 913702006143165798 | F33: 单位地址 青岛市市南区闽江路2号1单元701户 电话号码 053285757939 | G33: 开户银行 光大银行青岛分行 银行账户 083801120100305013287 | H33: 1299 | I33: 已开
A34: 45706 | B34: 韩园 | C34: 18707150628 | D34: 武汉银楚物资有限公司 | E34: 914201020744903216 | F34: 武汉市江岸区解放大道2020号中储物流服务中心大楼2层06室 027-82823862 | G34: 农行武汉丹水池支行 17-000901040020496 | H34: 1499 | I34: 已开
A35: 45708 | B35: 韩园 | C35: 18707150628 | D35: 武汉银楚物资有限公司 | E35: 914201020744903216 | F35: 武汉市江岸区解放大道2020号中储物流服务中心大楼2层06室 027-82823862 | G35: 农行武汉丹水池支行 17-000901040020496 | H35: 5400 | I35: 已开
A36: 45713 | B36: 罗舒涵 | C36: 18627107660 | D36: 湖北和之源园林市政工程有限公司 | E36: 91420111090817603N | F36: 单位地址：洪山区马湖路2号保利·心语8栋1单元6层01号 电话：13971177028 | G36: 开户银行：中国建设银行股份有限公司武汉中北路支行 银行账户：42001165028053003918 | H36: 499 | I36: 已开
A37: 45714 | B37: 罗舒涵 | C37: 18627107660 | D37: 湖北和之源园林市政工程有限公司 | E37: 91420111090817603N | F37: 单位地址：洪山区马湖路2号保利·心语8栋1单元6层01号 电话：13971177028 | G37: 开户银行：中国建设银行股份有限公司武汉中北路支行 银行账户：42001165028053003918 | H37: 1320 | I37: 已开
A38: 45715 | B38: 李尹幻 | C38: 13986684439 | D38: 薯一薯二文化传媒（武汉）有限公司 | E38: 91420100MADM5GFX7Q | F38: 地 址：湖北省武汉市东湖新技术开发区光谷三路777号移动终端产业园1号楼4层410、411、412号410-041 电 话：027-59359862 | G38: 银行名称：招商银行股份有限公司武汉光谷科技支行 银行账号：127921008610009 | H38: 1200 | I38: 已开
A39: 45716 | B39: 黄菊容 | C39: 13476190674 | D39: 葛洲坝集团供应链管理有限 公司工会委员会 | E39: 8142 0000 MC91 6381 1Y | F39: 单位地址：武汉市硚口区桥口路162号葛洲坝城市花园二期11栋12层 电话：027-83778185 | G39: 开户银行：交通银行武汉太平洋支行 银行账户：4214 2108 2012 0010 8903 0 | H39: 119 | I39: 已开
A40: 45716 | B40: 张芷苓 | C40: 15007109316 | D40: 武汉渲奇旅游文化有限公司 | E40: 91420100MA4KNDC85W | F40: 电话号码: 15007109316邮箱: 364942451@qq.com | H40: 1099 | I40: 已开
A41: 45719 | B41: 罗舒涵 | C41: 18627107660 | D41: 湖北和之源园林市政工程有限公司 | E41: 91420111090817603N | F41: 单位地址：洪山区马湖路2号保利·心语8栋1单元6层01号 电话：13971177028 | G41: 开户银行：中国建设银行股份有限公司武汉中北路支行 银行账户：42001165028053003918 | H41: 1320 | I41: 已开
A42: 45720 | B42: 张朝冲 | C42: 18162698412 | D42: 薯一薯二文化传媒（武汉）有限公司 | E42: 91420100MADM5GFX7Q | F42: 地 址：湖北省武汉市东湖新技术开发区光谷三路777号移动终端产业园1号楼4层410、411、412号410-041 电 话：027-59359862 | G42: 银行名称：招商银行股份有限公司武汉光谷科技支行 银行账号：127921008610009 | H42: 2100 | I42: 已开
A43: 45722 | B43: 李尹幻 | C43: 13986684439 | D43: 薯一薯二文化传媒（武汉）有限公司 | E43: 91420100MADM5GFX7Q | F43: 湖北省武汉市东湖新技术开发区光谷三路777号移动终端产业园1号楼4层410、411、412号410-041 电 话：027-59359862 | G43: 招商银行股份有限公司武汉光谷科技支行 | H43: 5000 | I43: 已开
A44: 45729 | B44: 罗舒涵 | C44: 18627107660 | D44: 武汉沄景涵喷泉设备有限公司 | E44: 9142 0107 6888 1588 0D | F44: 单位地址：武汉市青山区冶金大道65号 电话：13971177028 | G44: 中国银行武汉新江大支行 银行账户：5716795 6738 | H44: 1920 | I44: 已开
A45: 45733 | B45: 鲁钰仪 | C45: 17784152396 | D45: 常熟市祥安织造有限公司 | E45: 9132058133107619XW | F45: 常熟市海虞镇通江路179号 电话:0512-52170826 | G45: 农行常熟谢桥支行 账 号:10523301040009623 | H45: 1000 | I45: 已开
A46: 45733 | B46: 王艳玲 | C46: 13082521500 | D46: 常熟市祥安织造有限公司 | E46: 9132058133107619XW | F46: 常熟市海虞镇通江路179号 电话:0512-52170826 | G46: 农行常熟谢桥支行 账 号:10523301040009623 | H46: 1000 | I46: 已开
A47: 45733 | B47: 王倩 | C47: 18571684464 | H47: 800 | I47: 已开
A48: 45735 | B48: 魏雨尧 | C48: 13387633167 | D48: 南拳互娱(武汉)文化传媒有限公司 | E48: 91420100MA4KYH1C9R | H48: 250 | I48: 已开
A49: 45737 | B49: 章杰 | C49: 18727136761 | H49: 4038 | I49: 已开
A50: 45744 | B50: 王捷 | C50: 13294156129 | D50: 武汉艺画开天文化传播有限公司 | E50: 914201003334378762 | H50: 1800 | I50: 已开
A51: 45746 | B51: 李喆 | C51: 15387055588 | D51: 深圳市卓文华利电子有限公司 | E51: 91440300MA5HDYBW7T | F51: 深圳市福田区莲花街道福中社区深南大道 2008中国凤凰大厦2 栋15A | G51: 交通银行深圳香洲支行 4430 6606 5013 0061 2098 0 | H51: 1500 | I51: 已开
A52: 45746 | B52: 胡汉桥 | C52: 15327319793 | D52: 深圳市卓文华利电子有限公司 | E52: 91440300MA5HDYBW7T | F52: 深圳市福田区莲花街道福中社区深南大道 2008中国凤凰大厦2 栋15A | G52: 交通银行深圳香洲支行 4430 6606 5013 0061 2098 0 | H52: 1600 | I52: 已开
A53: 45747 | B53: 杨武 | C53: 13907183605 | H53: 1000 | I53: 已开
A54: 45756 | B54: 张利利 | C54: 13923808320 | D54: 武汉欧瑞景环保科技有限公司 | E54: 9142 0112 MA4K LDHP 5M | F54: 洪山区南李路27号圣爱米伦科研部分G栋1单元1-19层1205号 027-88076668 | G54: 中国农业银行武汉南湖支行 1703 1101 0400 15736 | H54: 1000 | I54: 已开
A55: 45756 | B55: 张利利 | C55: 13923808320 | D55: 武汉欧瑞景环保科技有限公司 | E55: 9142 0112 MA4K LDHP 5M | F55: 洪山区南李路27号圣爱米伦科研部分G栋1单元1-19层1205号 027-88076668 | G55: 中国农业银行武汉南湖支行 1703 1101 0400 15736 | H55: 500 | I55: 已开
A56: 45757 | B56: 王淑琴 | C56: 15527172405 | D56: 朗新科技集团股份有限公司 | E56: 91320200747189665N | F56: 无锡新吴区净慧东道118号1楼 0510-66676999 | G56: 中国工商银行股份有限公司无锡新吴支行 1103020819200405492 | H56: 2000 | I56: 已开
A57: 45757 | B57: 张宇晨 尹辰夏 | C57: 15072357003 | D57: 武汉清江建筑装饰工程有限公司 | E57: 914201007646357783 | F57: 地址、电话：武汉市东湖新技术开发区高新六路8号 027-81303159 | G57: 开户行及帐号：建设银行武汉藏龙岛支行 42001140042052501559 | H57: 1900 | I57: 已开
A58: 45766 | B58: 李尹幻 | C58: 13986684439 | D58: 薯一薯二文化传媒（武汉）有限公司 | E58: 91420100MADM5GFX7Q | F58: 湖北省武汉市东湖新技术开发区光谷三路777号移动终端产业园1号楼4层410、411、412号410-041 电 话：027-59359862 | G58: 招商银行股份有限公司武汉光谷科技支行 银行账号：127921008610009 | H58: 1200 | I58: 已开
A59: 45777 | B59: 徐湘 | C59: 15926202077 | D59: 武汉佰钧成技术有限责任公司 | E59: 91420100789324669U | H59: 2800
A60: 45778 | B60: 张雨婷 | C60: 15527240331 | H60: 4800 | I60: 已开
A61: 45783 | B61: 刘宇霖 | C61: 15927002595 | D61: 悦莱（武汉）建筑安装工程有限公司 | E61: 91420112MA4K257B1Y | F61: 武汉市东西湖区走马岭打靶堤12号1层027-85859566 | G61: 交通银行武汉东西湖支行 421868088018800094077 | H61: 15000 | I61: 已开
A62: 45786 | B62: 李望 | C62: 18770507582 | D62: 薯一薯二文化传媒（武汉）有限公司 | E62: 91420100MADM5GFX7Q | F62: 湖北省武汉市东湖新技术开发区光谷三路777号移动 终端产业园1号楼4层410、411、412号410-041 电 话：027-59359862 | G62: 招商银行股份有限公司武汉光谷科技支行 | H62: 2713.4 | I62: 已开
A63: 45786 | B63: 刘妍文 | C63: 13260651615 | D63: 薯一薯二文化传媒（武汉）有限公司 | E63: 91420100MADM5GFX7Q | F63: 湖北省武汉市东湖新技术开发区光谷三路777号移动终端产业园1号楼4层410、411、412号410-041 电 话：027-59359862 | G63: 招商银行股份有限公司武汉光谷科技支行 | H63: 2100 | I63: 已开
A64: 45794 | B64: 张雨婷 | C64: 15527240331 | H64: 3000 | I64: 已开
A65: 45794 | B65: 李尹幻 | C65: 13986684439 | D65: 薯一薯二文化传媒（武汉）有限公司 | E65: 91420100MADM5GFX7Q | F65: 湖北省武汉市东湖新技术开发区光谷三路 777号移动终端产业园1号楼4层410、411、412号410-041 电 话：027-59359862 | G65: 招商银行股份有限公司武汉光谷科技支行 银行账号：127921008610009 | H65: 1200 | I65: 已开
A66: 45795 | B66: 陈徐昕 | C66: 13616601270 | D66: 武汉金安格印刷技术有限公司 | E66: 91420105672791511J | F66: 单位地址：武汉市东西湖区走马岭兴工十二路明典工业园C型A区、C区 电话号码：027-87715743 | G66: 开户银行：中国工商银行武汉武珞路支行 开户账号：3202006019200053803 | H66: 3500 | I66: 已开
A67: 45800 | B67: 王天依 | C67: 13427566685 | D67: 武汉拓源物业管理有限公司 | E67: 91420100MA49GDP71M | F67: 武汉东湖新技术开发区雄庄路曙光星城D区1号楼2层201-2 电话： 13886112001 | G67: 招商银行武汉岳家嘴支行 127913914010401 | H67: 995 | I67: 已开
A68: 45801 | B68: 叶立君 | C68: 15971472119 | D68: 武汉文希文化传播有限公司 | E68: 91420106MA4F2NX60E | H68: 2000 | I68: 已开
A69: 45804 | B69: 李尹幻 | C69: 13986684439 | D69: 薯一薯二文化传媒（武汉）有限公司 | E69: 91420100MADM5GFX7Q | F69: 地 址：湖北省武汉市东湖新技术开发区光谷三路777号移动终端产业园1号楼4层410、411、412号410-041 电 话：027-59359862 | G69: 银行名称：招商银行股份有限公司武汉光谷科技支行 银行账号：127921008610009 | H69: 3000 | I69: 已开
A70: 45807 | B70: 赵瑾朝 | C70: 15926263101 | H70: 6000 | I70: 已开
A71: 45824 | B71: 韩园 | C71: 18707150628 | D71: 武汉银楚物资有限公司 | E71: 914201020744903216 | F71: 027-82823862 | G71: 农行武汉丹水池支行 17-000901040020496 | H71: 5400 | I71: 已开
A72: 45833 | B72: 彭靖 | C72: 17707434742 | D72: 南拳互娱(武汉)文化传媒有限公司 | E72: 91420100MA4KYH1C9R | H72: 200 | I72: 已开
A73: 45838 | B73: 熊明德 | C73: 18986188780 | H73: 1000 | I73: 已开
A74: 45839 | B74: 詹琦龙 詹崧艺 | C74: 18126289365 | D74: 上海成煦科技有限公司 | E74: 91310120MA1HYUP94Q | H74: 1800 | I74: 已开
A75: 45843 | B75: 李尹幻 | C75: 13986684439 | D75: 薯一薯二文化传媒（武汉）有限公司 | E75: 91420100MADM5GFX7Q | F75: 湖北省武汉市东湖新技术开发区光谷三路777号移动终端产业园 1号楼4层410、411、412号410-041 电 话：027-59359862 | G75: 招商银行股份有限公司武汉光谷科技支行 银行账号：127921008610009 | H75: 1200 | I75: 已开
A76: 45847 | B76: 李星河 | C76: 15392850579 | D76: 薯一薯二文化传媒（武汉）有限公司 | E76: 91420100MADM5GFX7Q | F76: 湖北省武汉市东湖新技术开发区光谷三路777号移动终端产业园1号楼4层410、411、412号410-041电 话：027-59359862 | G76: 招商银行股份有限公司武汉光谷科技支行 银行账号：127921008610009 | H76: 2250 | I76: 已开
A77: 45849 | B77: 胥靖维 | C77: 15871484306 | D77: 武汉中元华电电力设备有限公司 | E77: 9142 0100 6854 31371K | H77: 1500 | I77: 已开
A78: 45873 | B78: 刘嘉雯 | C78: 13451202480 | D78: 薯一薯二文化传媒（武汉）有限公司 | E78: 91420100MADM5GFX7Q | F78: 湖北省武汉市东湖新技术开发区光谷三路777号移动终端产业园 1号楼4层410、411、412号410-041 电 话：027-59359862 | G78: 招商银行股份有限公司武汉光谷科技支行 银行账号：127921008610009 | H78: 5953.86 | I78: 已开
A79: 45888 | B79: 汪牧远 许媛 | C79: 17771794992 | D79: 武汉光基科技有限公司 | E79: 91420106MA4F2CXG2N | F79: 邮箱:wangjie71@126.com | H79: 2000 | I79: 已开
A80: 45911 | B80: 江思宇 廖春燕 | C80: 15604317537 18974564274 | D80: 薯一薯二文化传媒（武汉）有限公司 | E80: 91420100MADM5GFX7Q | F80: 湖北省武汉市东湖新技术开发区光谷三路777号移动终端产业园1号楼4层410、411、412号410-041 | G80: 招商银行股份有限公司武汉光谷科技支行 127921008610009 | H80: 2250 | I80: 已开
A81: 45929 | B81: 方牧云 林安 卢兴运 程旭 | C81: 19968099566 15575739108 13072702018 13896809961 | D81: 广西翔正项目管理有限公司钦州分公司 | E81: 914507035572330392 | F81: 钦州市新华路268号江滨豪园10 | G81: 开户行：中国农业银行股份有限公司钦州新兴支行 账号：20733501040007396 | H81: 1600 | I81: 已开
A82: 45939 | B82: 李尹幻 | C82: 13986684439 | D82: 薯一薯二文化传媒（武汉）有限公司 | E82: 91420100MADM5GFX7Q | F82: 地 址：湖北省武汉市东湖新技术开发区光谷三路777号移动终 端产业园1号楼4层410、411、412号410-041 电 话：027-59359862 | G82: 招商银行股份有限公司武汉光谷科技支行 银行账号：127921008610009 | H82: 3000 | I82: 已开
A83: 45950 | B83: 郝晋旋 | C83: 18745095670 | D83: 重庆皖飞电子技术有限公司 | E83: 915001076889409139 | F83: 重庆市九龙坡区渝州路4号21-1号/邮编：400039 电话：023-68140104 传真：023-68140074 | G83: 开户行：重庆工行高科技支行 账号：3100020409200333276 开户行行号（银行代码）：102653000128 | H83: 2800 | I83: 已开
B84: 马徽元 | C84: 15902356762
B85: 张诺皓 | C85: 13072703101
A86: 45969 | B86: 罗宇航 | C86: 19907145739 | D86: 湖北腾聚建设工程有限公司 | E86: 91420281MA4968XB7C | F86: 大冶市城北开发区上冯路5号2栋四单元501 0714-8767886 | G86: 开 户 账 号：1716520104001158 2 中国农业银行大冶支行营业室（103522116524） | H86: 1100 | I86: 已开
A87: 45978 | B87: 邹晓庆 | C87: 13277401415 | D87: 薯一薯二文化传媒（武汉）有限公司 | E87: 91420100MADM5GFX7Q | F87: 湖北省武汉市东湖新技术开发区光谷三路777号移动终端产业园1号楼4层410、411、412号410-041 | G87: 银行名称：招商银行股份有限公司武汉光谷科技支行 银行账号：127921008610009 | H87: 2250 | I87: 已开
A88: 45978 | B88: 方娜 | C88: 18873085021 | D88: 薯一薯二文化传媒（武汉）有限公司 | E88: 91420100MADM5GFX7Q | F88: 湖北省武汉市东湖新技术开发区光谷三路777号移动终端产业园1号楼4层410、411、412号410-041 | G88: 银行名称：招商银行股份有限公司武汉光谷科技支行 银行账号：127921008610009 | H88: 263 | I88: 已开
A89: 45996 | B89: 李思思 | C89: 15072357003 | D89: 武汉清江建筑装饰工程有限公司 | E89: 914201007646357783 | F89: 武汉市东湖新技术开发区高新六路8号 027-81303159 | G89: 建设银行武汉藏龙岛支行42001140042052501559 | H89: 1800 | I89: 已开
A90: 45999 | B90: 赵瑾朝 | C90: 15926263101 | H90: 13711 | I90: 已开
A91: 46006 | B91: 汪楠 | C91: 18271460820 | D91: 薯一薯二文化传媒（武汉）有限公司 | E91: 91420100MADM5GFX7Q | F91: 湖北省武汉市东湖新技术开发区光谷三路777号移动终端产业园1号楼4层410、411、412号410-041 | G91: 招商银行股份有限公司武汉光谷科技支行 银行账号：127921008610009 | H91: 2400 | I91: 已开
A92: 46007 | B92: 李尹幻 | C92: 13986684439 | D92: 薯一薯二文化传媒（武汉）有限公司 | E92: 91420100MADM5GFX7Q | F92: 湖北省武汉市东湖新技术开发区光谷三路777号移动终端产业园1号楼4层410、411、412号410-041 | G92: 招商银行股份有限公司武汉光谷科技支行 银行账号：127921008610009 | H92: 3000 | I92: 已开
A93: 46008 | B93: 李琴 | C93: 13212781002 | H93: 1200 | I93: 已开
A94: 46015 | B94: 张丽 肖博 | C94: 13277063378 18507135880 | D94: 义乌市留屿贸易商行 | E94: 92330782MAC6GU943A | F94: 浙江省金华市义乌市江东街道九联 地横头43幢1单元402室 | H94: 2980 | I94: 已开
A95: 46017 | B95: 刘笑彤 | C95: 13839516175 | D95: 薯一薯二文化传媒（武汉）有限公司 | E95: 91420100MADM5GFX7Q | F95: 湖北省武汉市东湖新技术开发区光谷三路777号移动终端产业园1号楼4层410、411、412号410-041电 话：027-59359862 | G95: 招商银行股份有限公司武汉光谷科技支行 银行账号：127921008610009 | H95: 2904.69 | I95: 已开
A96: 46018 | B96: 向怀诚 | C96: 17673012952 | D96: 薯一薯二文化传媒（武汉）有限公司 | E96: 91420100MADM5GFX7Q | F96: 湖北省武汉市东湖新技术开发区光谷三路777号移动终端产业园1号楼4层410、411、412号410-041 电 话：027-59359862 | G96: 招商银行股份有限公司武汉光谷科技支行 银行账号：127921008610009 | H96: 3233.13 | I96: 已开
A97: 46020 | B97: 杨芳芳 | C97: 15205187072 | D97: 武汉康成百澳生物科技有限公司 | E97: 91420111MABWG3G97L | F97: 湖北省武汉东湖新技术开发区南湖大道116号南湖时尚城K5经济型酒店1-16层3层306室 | G97: 中国工商银行武汉民族大道支行 帐号：3202163809060145860 | H97: 400 | I97: 已开
A98: 46029 | B98: 黄宸熹 | C98: 18971542748 | D98: 薯一薯二文化传媒（武汉）有限公司 | E98: 91420100MADM5GFX7Q | F98: 湖北省武汉市东湖新技术开发区光谷三路777号移动终端产业园1号楼4层410、411、412号410-041 电 话：027-59359862 | G98: 招商银行股份有限公司武汉光谷科技支行 银行账号：127921008610009 | H98: 2400 | I98: 已开
A99: 46055 | B99: 毛雯 | C99: 15927077690 | D99: 中管辰化石油工程有限公司 | E99: 91420100MA4L0QKYXD | F99: 武汉东湖新技术开发区武汉大学科技园3S地球空间信息产业基地三区第24#座4层1号、5层1号 电 话：027-87333387 | G99: 中国银行股份有限公司武汉藏龙岛科技支行 账号：5703 7537 1325 | H99: 1490 | I99: 已开
A100: 46055 | B100: 毛雯 | C100: 15927077690 | D100: 中管辰化石油工程有限公司 | E100: 91420100MA4L0QKYXD | F100: 武汉东湖新技术开发区武汉大学科技园3S地球空间信息产业基地三区第24#座4层1号、5层1号 电 话：027-87333387 | G100: 中国银行股份有限公司武汉藏龙岛科技支行 账号：5703 7537 1325 | H100: 1490 | I100: 已开
...

Sheet 礼品赠送明细表
A1: 礼品赠送明细表
A2: 日期 | B2: 会员姓名 | C2: 会员电话 | D2: 办卡金额 | E2: 礼品 | F2: 数量
A3: 45598 | B3: 李开来 | C3: 19180954170 | D3: 1300 | E3: 包 水杯 | F3: 2
A4: 45599 | B4: 胡思闽 | C4: 13227653280 | D4: 1840 | E4: 包 水杯 | F4: 2
A5: 45599 | B5: 敖宇鹏 | C5: 15279033613 | D5: 1099 | E5: 包 水杯 | F5: 2
A6: 45600 | B6: 苗丰宇 | C6: 15722746022 | D6: 1099 | E6: 包 水杯 | F6: 2
A7: 45600 | B7: 李俊杰 | C7: 18256906149 | D7: 1299 | E7: 包 水杯 | F7: 2
A8: 45600 | B8: 侯占岭 | C8: 18347702202 | D8: 1200 | E8: 包 水杯 | F8: 2
A9: 45600 | B9: 冉再 | C9: 13251261567 | D9: 750 | E9: 包 水杯 周卡 | F9: 3
A10: 45600 | B10: 朱贤奇 | C10: 15272294432 | D10: 400 | E10: 包 水杯 小电锅 | F10: 3
A11: 45600 | B11: 洪先龙 | C11: 15690837586 | D11: 500 | E11: 包 水杯 | F11: 2
A12: 45600 | B12: 汪岱原 | C12: 15037588659 | D12: 500 | E12: 包 水杯 | F12: 2
A13: 45601 | B13: 鲜于非凡 | C13: 16671742287 | D13: 500 | E13: 包 水杯 | F13: 2
A14: 45601 | B14: 艾圣茗 | C14: 15841692839 | D14: 600 | E14: 包 水杯 | F14: 2
... A33: 45605 | B33: 田书耘 | C33: 1388603134 | D33: 800 | E33: 6.6元现金红包 | F33: 1
A34: 45605 | B34: 樊嘉琪 | C34: 15623090185 | D34: 1100 | E34: 周卡*1
A35: 45605 | B35: 朱运樱 | C35: 15533938515 | D35: 800 | E35: 瑜伽垫 水杯 | F35: 2
A36: 45605 | B36: 胡诗睿 | C36: 15527950717 | D36: 800 | E36: 瑜伽垫 水杯 | F36: 2
A37: 45605 | B37: 刘明 | C37: 18607118123 | D37: 1100 | E37: 6.6元现金红包 | F37: 1
A38: 45605 | B38: 马梓晨 | C38: 18997407591 | D38: 500 | E38: 杯子 | F38: 1
A39: 45605 | B39: 小美 | C39: 18627860686 | D39: 1777 | E39: 6.6元现金红包 | F39: 1
A40: 45605 | B40: 冉再 | C40: 13251261567 | D40: 750 | E40: 6.6元现金红包 | F40: 1
A41: 45605 | B41: 王寅 | C41: 13971508564 | D41: 1111 | E41: 6.6元现金红包 | F41: 1
A42: 45605 | B42: 周瑾瑜 | C42: 15927306906 | D42: 1111 | E42: 8.8元现金红包 | F42: 1
A43: 45605 | B43: 朱贤奇 | C43: 15272294432 | D43: 400 | E43: 热水壶 | F43: 1
A44: 45605 | B44: 肖恩博 | C44: 18849218812 | D44: 400 | E44: 杯子 | F44: 1
A45: 45606 | B45: 王丽霞 | C45: 13673043407 | D45: 1111 | E45: 6.6元现金红包 | F45: 1
A46: 45606 | B46: 毕帆 | C46: 17387707507 | D46: 1599 | E46: 8.8元现金红包 | F46: 1
... A110: 45622 | B110: 王宇航 | C110: 18827096501 | D110: 799 | E110: 包 水杯 | F110: 2
A111: 45624 | B111: 华农店 | E111: 包*20 | F111: 20
A112: 45624 | B112: 毛卫宇 | C112: 17754403623 | D112: 500 | E112: 包 水杯 | F112: 2
A113: 45625 | B113: 蔡显特 | C113: 13296359922 | D113: 1099 | E113: 包 水杯 | F113: 2
A114: 45625 | B114: 俞泓宇 | C114: 15307126592 | D114: 1600 | E114: 杯子 | F114: 1
A115: 45626 | B115: 周浩然 | C115: 13477051132 | D115: 500 | E115: 包 水杯 | F115: 2
A116: 45627 | B116: 姚佳豪 | C116: 18120266179 | D116: 149 | E116: 包 水杯 | F116: 1
A117: 45627 | B117: 朱运樱 | C117: 15533938515 | D117: 800 | E117: 包 周卡*4 | F117: 2
A118: 45628 | B118: 赵劲潮 | C118: 17764009483 | D118: 500 | E118: 包 水杯 | F118: 2
A119: 45628 | B119: 王广俅 | C119: 15926287362 | D119: 250 | E119: 包 水杯 | F119: 2
A120: 45628 | B120: 胡傲一 | C120: 19871827160 | D120: 250 | E120: 包 水杯 | F120: 2
A121: 45628 | B121: 董创 | C121: 13554237230 | D121: 250 | E121: 包 水杯 | F121: 2
A122: 45628 | B122: 董汉雄 | C122: 13476628316 | D122: 500 | E122: 包 水杯 | F122: 2
A123: 45629 | B123: 郭奕威 | C123: 15629648710 | D123: 780 | E123: 包 水杯 | F123: 2
... A125: 45630 | B125: 马龙 | C125: 17395401602 | D125: 700 | E125: 蛋白粉 | F125: 1
A126: 45630 | C126: 13890605156 | E126: 蛋白粉 | F126: 1
A127: 45631 | B127: 何子涵 | C127: 17280360486 | D127: 1299 | E127: 包 | F127: 1
A128: 45632 | B128: 孙林方 | C128: 15810858806 | D128: 1200 | E128: 包 | F128: 1
A129: 45632 | B129: 小红书活动 | E129: 次卡*200
A130: 45632 | B130: 小红书活动 | E130: 农夫*5箱
A131: 45632 | B131: 小红书活动 | E131: 外星人wave*1箱
A132: 45633 | B132: 秦俊蓉 | C132: 18007144725 | D132: 1212 | E132: 包 水杯 | F132: 2
A133: 45633 | B133: 刘慧斌 | C133: 18830121633 | D133: 1500 | E133: 包 水杯 | F133: 2
A134: 45634 | B134: 吴茂林 | C134: 17852841739 | D134: 1099 | E134: 包 水杯 | F134: 2
A135: 45634 | B135: 韩鹏 | C135: 17689789130 | D135: 1299 | E135: 包 水杯 | F135: 2
A136: 45634 | B136: 朱** | C136: 没填 | E136: 包 水杯 | F136: 2
A137: 45635 | B137: 王杰 | C137: 19945028250 | D137: 1499 | E137: 包 水杯 | F137: 2
A138: 45636 | B138: 黄升栋 | C138: 15723992024 | D138: 1399 | E138: 包 水杯 | F138: 2
A139: 45636 | B139: 张润 | C139: 13955775950 | D139: 700 | E139: 包 水杯 | F139: 2
A140: 45637 | B140: 谢盼 | C140: 15827067806 | D140: 1212 | E140: 6.6元现金红包 | F140: 1
A141: 45637 | B141: 刘洋 | C141: 15377575702 | D141: 251 | E141: 包 水杯 | F141: 2
A142: 45637 | B142: 王倩 | C142: 18571684464 | D142: 1212 | E142: 弹力带 | F142: 1
A143: 45637 | B143: 段继来 | C143: 17866227037 | D143: 400 | E143: 包 水杯 | F143: 2
A144: 45637 | B144: 许悦 | C144: 18255700917 | D144: 500 | E144: 8.8元现金红包 | F144: 1
A145: 45637 | B145: 郑家乐 | C145: 15527691939 | D145: 500 | E145: 8.8元现金红包 | F145: 1
A146: 45637 | B146: 易婧妧 | C146: 18025302165 | D146: 1490 | E146: 乳胶枕 | F146: 1
A147: 45638 | B147: 秦俊蓉 | C147: 18007144725 | D147: 1212 | E147: 乳胶枕 | F147: 1
A148: 45638 | B148: 李雅琴 | C148: 13667224578 | D148: 1000 | E148: 8.8元现金红包 | F148: 1
... A183: 45658 | B183: 吴思庆 | C183: 18971254875 | D183: 1500 | E183: 包 | F183: 1
A184: 45676 | B184: 余威 | C184: 杨家湾店 | E184: 玩具 | F184: 6
A185: 45667 | B185: 龚程程 | C185: 15884437838 | D185: 399 | E185: 包，水杯 | F185: 2
A186: 45694 | B186: 陈文龙 | C186: 18402742420 | D186: 1000 | E186: 体重秤 | F186: 1
A187: 45695 | B187: 刘清伟 | C187: 18229601468 | D187: 800 | E187: 充电宝 | F187: 1
A188: 45695 | B188: 江海洋 | C188: 18402744420 | E188: 包 水杯 | F188: 2
A189: 45696 | B189: 张澳 | C189: 18571515186 | D189: 1499 | E189: 体重秤 | F189: 1
A190: 45697 | B190: 黄凝馨 | C190: 15623893558 | D190: 1299 | E190: 茶具套装 | F190: 1
A191: 45697 | B191: 王柏洋 | C191: 13559055226 | D191: 1100 | E191: 蒸蛋器 | F191: 1
A192: 45698 | B192: 陈先萍 | C192: 17764220631 | D192: 600 | E192: 筋膜枪 | F192: 1
A193: 45698 | B193: 桑艳茹 | C193: 15927700351 | D193: 1500 | E193: 枕头 | F193: 1
A194: 45699 | B194: 吉祥 | C194: 18086663119 | D194: 600 | E194: 水杯 | F194: 1
A195: 45699 | B195: 周娴 | C195: 13118038417 | D195: 800 | E195: 瑜伽垫 | F195: 1
A196: 45699 | B196: 张腾 | C196: 17671054576 | D196: 1299 | E196: 瑜伽垫 | F196: 1
A197: 45699 | B197: 黄肖 | C197: 13797226482 | D197: 600 | E197: 筋膜枪 | F197: 1
A198: 45699 | B198: 彭珂 | C198: 18771003583 | D198: 1599 | E198: 蒸蛋器 | F198: 1
A199: 45700 | B199: 张露 郭冲 | C199: 15827567020 17399981341 | D199: 2998 | E199: 蓝牙耳机 吨吨桶 | F199: 2
A200: 45701 | B200: 黎明 | C200: 18995605787 | D200: 1600 | E200: 瑜伽垫 | F200: 1
A201: 45701 | B201: 张蓓 | C201: 1322733076 | D201: 1431 | E201: 雨伞 | F201: 1
A202: 45700 | B202: 郑博 | C202: 15926809020 | D202: 499 | E202: 镜子 | F202: 1
A203: 45702 | B203: 赵晨崴 | C203: 18186279579 | D203: 1000 | E203: 耳机包杯子 | F203: 3
A204: 45702 | B204: 孙华杰 | C204: 18995629679 | D204: 1117 | E204: 包杯子梳子 | F204: 3
A205: 45702 | B205: 李宪 | C205: 15827223140 | D205: 888 | E205: 耳机 | F205: 1
A206: 45702 | B206: 吴问 | C206: 13696793585 | D206: 900 | E206: 筋膜枪 | F206: 1
A207: 45702 | B207: 邱晨辉 | C207: 13367142249 | D207: 1499 | E207: 雨伞包杯子 | F207: 3
A208: 45702 | B208: 温家慧 | C208: 18169031213 | D208: 1000 | E208: 体重秤 | F208: 1
A209: 45702 | B209: 董奕石 | C209: 18147164109 | D209: 1000 | E209: 电风扇 | F209: 1
A210: 45702 | B210: 董雨桐 | C210: 15071517987 | E210: 瑜伽垫包杯子 | F210: 3
A211: 45702 | B211: 宫徐飞 | C211: 19078908919 | E211: 杯子雨伞 | F211: 2
A212: 45703 | B212: 张腾 | C212: 17671054576 | D212: 1299 | E212: 包 | F212: 1
A213: 45703 | B213: 吴伟垄 | C213: 13328558295 | D213: 499 | E213: 吨吨桶 | F213: 1
A214: 45703 | B214: 陈 | C214: 17839516786 | E214: 瑜伽垫 | F214: 1
A215: 45703 | B215: 郭蔷 | C215: 17839516786 | E215: 养生壶 | F215: 1
A216: 45703 | B216: 刘逸康 | E216: 养生壶 | F216: 1
...

Sheet 固定资产盘点表
A1: 固定资产盘点表
A2: 类别 | B2: 器械名称 | C2: 规格 | D2: 期初库存 | E2: 2025年7月 | F2: 2025年8月 | G2: 2025年9月 | H2: 2025年8月 | I2: 2025年8月 | J2: 2025年8月
E3: 本月库存量 | F3: 本月库存量 | G3: 本月库存量 | H3: 本月库存量 | I3: 本月库存量 | J3: 本月库存量
A4: 操房用品 | B4: 蹦床 | C4: 个 | D4: 12 | E4: 12 | F4: 12 | G4: 12
B5: 杠铃 | C5: 个 | D5: 10 | E5: 10 | F5: 10 | G5: 10
B6: 杠铃片1.25kg | C6: 个 | D6: 16 | E6: 16 | F6: 16 | G6: 16
B7: 杠铃片2.5kg | C7: 个 | D7: 16 | E7: 16 | F7: 16 | G7: 16
B8: 杠铃片5kg | C8: 个 | D8: 16 | E8: 16 | F8: 16 | G8: 16
B9: 杠铃片收纳架 | C9: 个 | D9: 1 | E9: 1 | F9: 1 | G9: 1
B10: 1kg哑铃 | C10: 个 | D10: 34 | E10: 34 | F10: 34 | G10: 34
B11: 踏板 | C11: 个 | D11: 19 | E11: 19 | F11: 19 | G11: 19
B12: 踏板支架 | C12: 个 | D12: 78 | E12: 78 | F12: 78 | G12: 78
B13: 泡沫轴 | C13: 个 | D13: 15 | E13: 15 | F13: 15 | G13: 15
B14: 小跳栏 | C14: 个 | D14: 8 | E14: 8 | F14: 8 | G14: 8
B15: 小篮球 | C15: 个 | D15: 3 | E15: 3 | F15: 3 | G15: 3
B16: 跳绳 | C16: 个 | D16: 6 | E16: 6 | F16: 6 | G16: 6
... B21: 固定单车 | C21: 台 | D21: 22 | E21: 22 | F21: 22 | G21: 22
A22: 器械区 | B22: 跑步机 | C22: 个 | D22: 20 | E22: 20 | F22: 20 | G22: 20
B23: 椭圆仪 | C23: 个 | D23: 6 | E23: 6 | F23: 6 | G23: 6
B24: 爬楼机 | C24: 个 | D24: 1 | E24: 1 | F24: 1 | G24: 1
B25: 坐姿推肩 | C25: 个 | D25: 2 | E25: 2 | F25: 2 | G25: 2
B26: 倒蹲机 | C26: 个 | D26: 2 | E26: 2 | F26: 2 | G26: 2
B27: 蝴蝶机 | C27: 个 | D27: 1 | E27: 1 | F27: 1 | G27: 1
B28: 坐姿推开合 | C28: 个 | D28: 1 | E28: 1 | F28: 1 | G28: 1
B29: 小杠铃架 | C29: 个 | D29: 1 | E29: 1 | F29: 1 | G29: 1
B30: 坐姿推胸 | C30: 个 | D30: 4 | E30: 4 | F30: 4 | G30: 4
B31: 坐姿划船 | C31: 个 | D31: 3 | E31: 3 | F31: 3 | G31: 3
B32: 助力引体向上 | C32: 个 | D32: 1 | E32: 1 | F32: 1 | G32: 1
B33: 坐姿腿弯举 | C33: 个 | D33: 1 | E33: 1 | F33: 1 | G33: 1
B34: 坐姿腿曲伸 | C34: 个 | D34: 1 | E34: 1 | F34: 1 | G34: 1
... B59: 二头弯举椅 | C59: 个 | D59: 2 | E59: 2 | F59: 2 | G59: 2
A60: 杠铃片 | B60: 2.5kg | C60: 个 | D60: 16 | E60: 16 | F60: 16 | G60: 16
B61: 1.25kg | C61: 个 | D61: 4 | E61: 4 | F61: 4 | G61: 4
B62: 5.0kg | C62: 个 | D62: 20 | E62: 20 | F62: 20 | G62: 20
B63: 10kg | C63: 个 | D63: 40 | E63: 40 | F63: 40 | G63: 40
B64: 15kg | C64: 个 | D64: 36 | E64: 36 | F64: 36 | G64: 36
B65: 20kg | C65: 个 | D65: 32 | E65: 32 | F65: 32 | G65: 32
B66: 25kg | C66: 个 | D66: 12 | E66: 12 | F66: 12 | G66: 12
B67: 2.5kg | C67: 个 | D67: 8 | E67: 8 | F67: 9 | G67: 9
B68: 5kg | C68: 个 | D68: 6 | E68: 6 | F68: 6 | G68: 6
B69: 7.5kg | C69: 个 | D69: 5 | E69: 5 | F69: 4 | G69: 5
B70: 10kg | C70: 个 | D70: 5 | E70: 5 | F70: 4 | G70: 5
B71: 12.5kg | C71: 个 | D71: 3 | E71: 3 | F71: 2 | G71: 5
B72: 15kg | C72: 个 | D72: 4 | E72: 4 | F72: 4 | G72: 3
... B82: 50kg | C82: 个 | D82: 0 | E82: 0 | F82: 0 | G82: 0
A83: 拳击 | B83: 拳击台 | C83: 个 | D83: 1 | E83: 1 | F83: 1 | G83: 1
A84: 女子训练区 | B84: 四站位组合训练机 | C84: 个 | D84: 1 | E84: 1 | F84: 1 | G84: 1
B85: 大扩胸/背部训练机 | C85: 个 | D85: 1 | E85: 1 | F85: 1 | G85: 1
B86: 臀部机 | C86: 个 | D86: 2 | E86: 2 | F86: 2 | G86: 2
B87: 髋臀部训练机 | C87: 个 | D87: 1 | E87: 1 | F87: 1 | G87: 1
B88: 坐式三头下压肌训练机 | C88: 个 | D88: 1 | E88: 1 | F88: 1 | G88: 1
