Workbook

Sheet 财务报表填写要求
A1: 财务报表填写要求
A2: 报表 | C2: 明细 | D2: 所属位置 | E2: 填写要求 | F2: 发表时间
A3: 每日登记 | B3: XX店财务报表 | C3: 收入汇总表 | D3: 收入汇总表!A1 | E3: 有公式自动计算，不允许手动更改 | F3: 每天下班前前台发送到财务邮箱
C4: 收据流水表 | D4: 收入流水表!A1 | E4: 1、根据真实情况填写，每一列都需要写清楚，与SASS后台系统保持一致（收据合约号必须按顺序填写，不允许跳号使用。） 2、填写日期格式与汇总保持表一致 3、收入类别从下拉框中勾选，不允许随意增加 4、对应实际情况，填写对应会籍和私教姓名（以最终成交为准）。
C5: 水吧销售明细表 | D5: 水吧销售明细表!A1 | E5: 早晚班只需要统计当天的销售数量（以瓶为单位，只写数字）， 收入和利润有公式可自动统计。
C6: 游泳装备销售明细表 | D6: 游泳装备销售明细表!A1 | E6: 早晚班只需要统计当天的销售数量（以件为单位，只写数字）， 收入和利润有公式可自动统计。
A7: 每周登记 | B7: 发票信息登记表 | C7: 发票信息登记表 | D7: 发票信息登记表!A1 | E7: 请核对需开票的会员真实性， 若当月会员未能领取的及时将发票退回财务部门。 | F7: 每周四晚下班前发送到财务邮箱
A8: 每月登记 | B8: 礼品盘点表 | C8: 礼品盘点表 | D8: 礼品盘点表!A1 | E8: 以公司实际采购、赠送来填写礼品当月的情况。 | F8: 次月1号下午发送到财务邮箱
B9: 固定资产盘点 | C9: 固定资产盘点表 | D9: 固定资产盘点表!A1 | E9: 以公司实际购入、报损来填写器械当月的情况。

Sheet 收入汇总表
A1: 2026年山道健身营业收入统计总表
B2: 主营业务 | G2: 其它业务 | M2: 当日收入 | N2: 付款方式 | R2: 当日现金情况 | U2: 备注
A3: 日期 | B3: 会籍收入 | C3: 私教收入 | D3: 教练班收入 | E3: 其他收入 | F3: 小计 | G3: 水吧收入 | H3: 游泳装备 | I3: 美团收入 | J3: 抖音收入 | K3: 刷单 | L3: 小计 | M3: 合计 | N3: 微信 | O3: 支付宝 | P3: POS | Q3: 现金 | R3: 存入 | S3: 备用金 | T3: 经办人
A4: 46204 | B4: =SUMIFS(收入流水表!J:J,收入流水表!C:C,$B$3,收入流水表!A:A,A4) -> 297 | C4: =SUMIFS(收入流水表!J:J,收入流水表!C:C,$C$3,收入流水表!A:A,A4) -> 0 | D4: =SUMIFS(收入流水表!J:J,收入流水表!C:C,$D$3,收入流水表!A:A,A4) -> 0 | E4: =SUMIFS(收入流水表!J:J,收入流水表!C:C,$E$3,收入流水表!A:A,A4) -> 0 | F4: =SUM(B4:E4) -> 297 | G4: =SUMIFS(收入流水表!J:J,收入流水表!C:C,$G$3,收入流水表!A:A,A4) -> 51 | H4: =SUMIFS(收入流水表!J:J,收入流水表!C:C,$H$3,收入流水表!A:A,A4) -> 0 | I4: =SUMIFS(收入流水表!J:J,收入流水表!C:C,$I$3,收入流水表!A:A,A4) -> 49.7 | J4: =SUMIFS(收入流水表!J:J,收入流水表!C:C,$J$3,收入流水表!A:A,A4) -> 19.9 | K4: =SUMIFS(收入流水表!J:J,收入流水表!C:C,$K$3,收入流水表!A:A,A4) -> 0 | L4: =SUM(G4:K4) -> 120.6 | M4: =F4+L4-K4 -> 417.6 | N4: =SUMIFS(收入流水表!J:J,收入流水表!I:I,$N$3,收入流水表!A:A,A4) -> 297 | O4: =SUMIFS(收入流水表!J:J,收入流水表!I:I,$O$3,收入流水表!A:A,A4) -> 0 | P4: =SUMIFS(收入流水表!J:J,收入流水表!I:I,$P$3,收入流水表!A:A,A4) -> 0 | Q4: =SUMIFS(收入流水表!J:J,收入流水表!I:I,$Q$3,收入流水表!A:A,A4) -> 0
A5: 46205 | B5: =SUMIFS(收入流水表!J:J,收入流水表!C:C,$B$3,收入流水表!A:A,A5) -> 574 | C5: =SUMIFS(收入流水表!J:J,收入流水表!C:C,$C$3,收入流水表!A:A,A5) -> 0 | D5: =SUMIFS(收入流水表!J:J,收入流水表!C:C,$D$3,收入流水表!A:A,A5) -> 880 | E5: =SUMIFS(收入流水表!J:J,收入流水表!C:C,$E$3,收入流水表!A:A,A5) -> 0 | F5: =SUM(B5:E5) -> 1454 | G5: =SUMIFS(收入流水表!J:J,收入流水表!C:C,$G$3,收入流水表!A:A,A5) -> 61 | H5: =SUMIFS(收入流水表!J:J,收入流水表!C:C,$H$3,收入流水表!A:A,A5) -> 0 | I5: =SUMIFS(收入流水表!J:J,收入流水表!C:C,$I$3,收入流水表!A:A,A5) -> 19.9 | J5: =SUMIFS(收入流水表!J:J,收入流水表!C:C,$J$3,收入流水表!A:A,A5) -> 19.9 | K5: =SUMIFS(收入流水表!J:J,收入流水表!C:C,$K$3,收入流水表!A:A,A5) -> 0 | L5: =SUM(G5:K5) -> 100.8 | M5: =F5+L5 -> 1554.8 | N5: =SUMIFS(收入流水表!J:J,收入流水表!I:I,$N$3,收入流水表!A:A,A5) -> 1454 | O5: =SUMIFS(收入流水表!J:J,收入流水表!I:I,$O$3,收入流水表!A:A,A5) -> 0 | P5: =SUMIFS(收入流水表!J:J,收入流水表!I:I,$P$3,收入流水表!A:A,A5) -> 0 | Q5: =SUMIFS(收入流水表!J:J,收入流水表!I:I,$Q$3,收入流水表!A:A,A5) -> 0
A6: 46206 | B6: =SUMIFS(收入流水表!J:J,收入流水表!C:C,$B$3,收入流水表!A:A,A6) -> 1298 | C6: =SUMIFS(收入流水表!J:J,收入流水表!C:C,$C$3,收入流水表!A:A,A6) -> 0 | D6: =SUMIFS(收入流水表!J:J,收入流水表!C:C,$D$3,收入流水表!A:A,A6) -> 3680 | E6: =SUMIFS(收入流水表!J:J,收入流水表!C:C,$E$3,收入流水表!A:A,A6) -> 0 | F6: =SUM(B6:E6) -> 4978 | G6: =SUMIFS(收入流水表!J:J,收入流水表!C:C,$G$3,收入流水表!A:A,A6) -> 87 | H6: =SUMIFS(收入流水表!J:J,收入流水表!C:C,$H$3,收入流水表!A:A,A6) -> 0 | I6: =SUMIFS(收入流水表!J:J,收入流水表!C:C,$I$3,收入流水表!A:A,A6) -> 19.9 | J6: =SUMIFS(收入流水表!J:J,收入流水表!C:C,$J$3,收入流水表!A:A,A6) -> 19.9 | K6: =SUMIFS(收入流水表!J:J,收入流水表!C:C,$K$3,收入流水表!A:A,A6) -> 0 | L6: =SUM(G6:K6) -> 126.8 | M6: =F6+L6-K6 -> 5104.8 | N6: =SUMIFS(收入流水表!J:J,收入流水表!I:I,$N$3,收入流水表!A:A,A6) -> 4679 | O6: =SUMIFS(收入流水表!J:J,收入流水表!I:I,$O$3,收入流水表!A:A,A6) -> 299 | P6: =SUMIFS(收入流水表!J:J,收入流水表!I:I,$P$3,收入流水表!A:A,A6) -> 0 | Q6: =SUMIFS(收入流水表!J:J,收入流水表!I:I,$Q$3,收入流水表!A:A,A6) -> 0
A7: 46207 | B7: =SUMIFS(收入流水表!J:J,收入流水表!C:C,$B$3,收入流水表!A:A,A7) -> 1720 | C7: =SUMIFS(收入流水表!J:J,收入流水表!C:C,$C$3,收入流水表!A:A,A7) -> 0 | D7: =SUMIFS(收入流水表!J:J,收入流水表!C:C,$D$3,收入流水表!A:A,A7) -> 5738 | E7: =SUMIFS(收入流水表!J:J,收入流水表!C:C,$E$3,收入流水表!A:A,A7) -> 0 | F7: =SUM(B7:E7) -> 7458 | G7: =SUMIFS(收入流水表!J:J,收入流水表!C:C,$G$3,收入流水表!A:A,A7) -> 48 | H7: =SUMIFS(收入流水表!J:J,收入流水表!C:C,$H$3,收入流水表!A:A,A7) -> 35 | I7: =SUMIFS(收入流水表!J:J,收入流水表!C:C,$I$3,收入流水表!A:A,A7) -> 0 | J7: =SUMIFS(收入流水表!J:J,收入流水表!C:C,$J$3,收入流水表!A:A,A7) -> 190 | K7: =SUMIFS(收入流水表!J:J,收入流水表!C:C,$K$3,收入流水表!A:A,A7) -> 0 | L7: =SUM(G7:K7) -> 273 | M7: =F7+L7 -> 7731 | N7: =SUMIFS(收入流水表!J:J,收入流水表!I:I,$N$3,收入流水表!A:A,A7) -> 7458 | O7: =SUMIFS(收入流水表!J:J,收入流水表!I:I,$O$3,收入流水表!A:A,A7) -> 0 | P7: =SUMIFS(收入流水表!J:J,收入流水表!I:I,$P$3,收入流水表!A:A,A7) -> 0 | Q7: =SUMIFS(收入流水表!J:J,收入流水表!I:I,$Q$3,收入流水表!A:A,A7) -> 0
A8: 46208 | B8: =SUMIFS(收入流水表!J:J,收入流水表!C:C,$B$3,收入流水表!A:A,A8) -> 2517 | C8: =SUMIFS(收入流水表!J:J,收入流水表!C:C,$C$3,收入流水表!A:A,A8) -> 0 | D8: =SUMIFS(收入流水表!J:J,收入流水表!C:C,$D$3,收入流水表!A:A,A8) -> 6320 | E8: =SUMIFS(收入流水表!J:J,收入流水表!C:C,$E$3,收入流水表!A:A,A8) -> 0 | F8: =SUM(B8:E8) -> 8837 | G8: =SUMIFS(收入流水表!J:J,收入流水表!C:C,$G$3,收入流水表!A:A,A8) -> 58 | H8: =SUMIFS(收入流水表!J:J,收入流水表!C:C,$H$3,收入流水表!A:A,A8) -> 40 | I8: =SUMIFS(收入流水表!J:J,收入流水表!C:C,$I$3,收入流水表!A:A,A8) -> 139.5 | J8: =SUMIFS(收入流水表!J:J,收入流水表!C:C,$J$3,收入流水表!A:A,A8) -> 95 | K8: =SUMIFS(收入流水表!J:J,收入流水表!C:C,$K$3,收入流水表!A:A,A8) -> 0 | L8: =SUM(G8:K8) -> 332.5 | M8: =F8+L8 -> 9169.5 | N8: =SUMIFS(收入流水表!J:J,收入流水表!I:I,$N$3,收入流水表!A:A,A8) -> 6137 | O8: =SUMIFS(收入流水表!J:J,收入流水表!I:I,$O$3,收入流水表!A:A,A8) -> 2700 | P8: =SUMIFS(收入流水表!J:J,收入流水表!I:I,$P$3,收入流水表!A:A,A8) -> 0 | Q8: =SUMIFS(收入流水表!J:J,收入流水表!I:I,$Q$3,收入流水表!A:A,A8) -> 0
A9: 46209 | B9: =SUMIFS(收入流水表!J:J,收入流水表!C:C,$B$3,收入流水表!A:A,A9) -> 2190 | C9: =SUMIFS(收入流水表!J:J,收入流水表!C:C,$C$3,收入流水表!A:A,A9) -> 0 | D9: =SUMIFS(收入流水表!J:J,收入流水表!C:C,$D$3,收入流水表!A:A,A9) -> 4848 | E9: =SUMIFS(收入流水表!J:J,收入流水表!C:C,$E$3,收入流水表!A:A,A9) -> 0 | F9: =SUM(B9:E9) -> 7038 | G9: =SUMIFS(收入流水表!J:J,收入流水表!C:C,$G$3,收入流水表!A:A,A9) -> 76 | H9: =SUMIFS(收入流水表!J:J,收入流水表!C:C,$H$3,收入流水表!A:A,A9) -> 50 | I9: =SUMIFS(收入流水表!J:J,收入流水表!C:C,$I$3,收入流水表!A:A,A9) -> 74.6 | J9: =SUMIFS(收入流水表!J:J,收入流水表!C:C,$J$3,收入流水表!A:A,A9) -> 19.9 | K9: =SUMIFS(收入流水表!J:J,收入流水表!C:C,$K$3,收入流水表!A:A,A9) -> 0 | L9: =SUM(G9:K9) -> 220.5 | M9: =F9+L9 -> 7258.5 | N9: =SUMIFS(收入流水表!J:J,收入流水表!I:I,$N$3,收入流水表!A:A,A9) -> 7038 | O9: =SUMIFS(收入流水表!J:J,收入流水表!I:I,$O$3,收入流水表!A:A,A9) -> 0 | P9: =SUMIFS(收入流水表!J:J,收入流水表!I:I,$P$3,收入流水表!A:A,A9) -> 0 | Q9: =SUMIFS(收入流水表!J:J,收入流水表!I:I,$Q$3,收入流水表!A:A,A9) -> 0
A10: 46210 | B10: =SUMIFS(收入流水表!J:J,收入流水表!C:C,$B$3,收入流水表!A:A,A10) -> 3652 | C10: =SUMIFS(收入流水表!J:J,收入流水表!C:C,$C$3,收入流水表!A:A,A10) -> 0 | D10: =SUMIFS(收入流水表!J:J,收入流水表!C:C,$D$3,收入流水表!A:A,A10) -> 1600 | E10: =SUMIFS(收入流水表!J:J,收入流水表!C:C,$E$3,收入流水表!A:A,A10) -> 0 | F10: =SUM(B10:E10) -> 5252 | G10: =SUMIFS(收入流水表!J:J,收入流水表!C:C,$G$3,收入流水表!A:A,A10) -> 58 | H10: =SUMIFS(收入流水表!J:J,收入流水表!C:C,$H$3,收入流水表!A:A,A10) -> 45 | I10: =SUMIFS(收入流水表!J:J,收入流水表!C:C,$I$3,收入流水表!A:A,A10) -> 16.9 | J10: =SUMIFS(收入流水表!J:J,收入流水表!C:C,$J$3,收入流水表!A:A,A10) -> 249.7 | K10: =SUMIFS(收入流水表!J:J,收入流水表!C:C,$K$3,收入流水表!A:A,A10) -> 0 | L10: =SUM(G10:K10) -> 369.6 | M10: =F10+L10 -> 5621.6 | N10: =SUMIFS(收入流水表!J:J,收入流水表!I:I,$N$3,收入流水表!A:A,A10) -> 4452 | O10: =SUMIFS(收入流水表!J:J,收入流水表!I:I,$O$3,收入流水表!A:A,A10) -> 800 | P10: =SUMIFS(收入流水表!J:J,收入流水表!I:I,$P$3,收入流水表!A:A,A10) -> 0 | Q10: =SUMIFS(收入流水表!J:J,收入流水表!I:I,$Q$3,收入流水表!A:A,A10) -> 0
A11: 46211 | B11: =SUMIFS(收入流水表!J:J,收入流水表!C:C,$B$3,收入流水表!A:A,A11) -> 7318 | C11: =SUMIFS(收入流水表!J:J,收入流水表!C:C,$C$3,收入流水表!A:A,A11) -> 0 | D11: =SUMIFS(收入流水表!J:J,收入流水表!C:C,$D$3,收入流水表!A:A,A11) -> 7500 | E11: =SUMIFS(收入流水表!J:J,收入流水表!C:C,$E$3,收入流水表!A:A,A11) -> 0 | F11: =SUM(B11:E11) -> 14818 | G11: =SUMIFS(收入流水表!J:J,收入流水表!C:C,$G$3,收入流水表!A:A,A11) -> 95 | H11: =SUMIFS(收入流水表!J:J,收入流水表!C:C,$H$3,收入流水表!A:A,A11) -> 140 | I11: =SUMIFS(收入流水表!J:J,收入流水表!C:C,$I$3,收入流水表!A:A,A11) -> 0 | J11: =SUMIFS(收入流水表!J:J,收入流水表!C:C,$J$3,收入流水表!A:A,A11) -> 19.9 | K11: =SUMIFS(收入流水表!J:J,收入流水表!C:C,$K$3,收入流水表!A:A,A11) -> 0 | L11: =SUM(G11:K11) -> 254.9 | M11: =F11+L11 -> 15072.9 | N11: =SUMIFS(收入流水表!J:J,收入流水表!I:I,$N$3,收入流水表!A:A,A11) -> 14218 | O11: =SUMIFS(收入流水表!J:J,收入流水表!I:I,$O$3,收入流水表!A:A,A11) -> 450 | P11: =SUMIFS(收入流水表!J:J,收入流水表!I:I,$P$3,收入流水表!A:A,A11) -> 0 | Q11: =SUMIFS(收入流水表!J:J,收入流水表!I:I,$Q$3,收入流水表!A:A,A11) -> 160
A12: 46212 | B12: =SUMIFS(收入流水表!J:J,收入流水表!C:C,$B$3,收入流水表!A:A,A12) -> 5853 | C12: =SUMIFS(收入流水表!J:J,收入流水表!C:C,$C$3,收入流水表!A:A,A12) -> 0 | D12: =SUMIFS(收入流水表!J:J,收入流水表!C:C,$D$3,收入流水表!A:A,A12) -> 2660 | E12: =SUMIFS(收入流水表!J:J,收入流水表!C:C,$E$3,收入流水表!A:A,A12) -> 0 | F12: =SUM(B12:E12) -> 8513 | G12: =SUMIFS(收入流水表!J:J,收入流水表!C:C,$G$3,收入流水表!A:A,A12) -> 43 | H12: =SUMIFS(收入流水表!J:J,收入流水表!C:C,$H$3,收入流水表!A:A,A12) -> 105 | I12: =SUMIFS(收入流水表!J:J,收入流水表!C:C,$I$3,收入流水表!A:A,A12) -> 34.8 | J12: =SUMIFS(收入流水表!J:J,收入流水表!C:C,$J$3,收入流水表!A:A,A12) -> 39.9 | K12: =SUMIFS(收入流水表!J:J,收入流水表!C:C,$K$3,收入流水表!A:A,A12) -> 0 | L12: =SUM(G12:K12) -> 222.7 | M12: =F12+L12 -> 8735.7 | N12: =SUMIFS(收入流水表!J:J,收入流水表!I:I,$N$3,收入流水表!A:A,A12) -> 8363 | O12: =SUMIFS(收入流水表!J:J,收入流水表!I:I,$O$3,收入流水表!A:A,A12) -> 150 | P12: =SUMIFS(收入流水表!J:J,收入流水表!I:I,$P$3,收入流水表!A:A,A12) -> 0 | Q12: =SUMIFS(收入流水表!J:J,收入流水表!I:I,$Q$3,收入流水表!A:A,A12) -> 0
A13: 46213 | B13: =SUMIFS(收入流水表!J:J,收入流水表!C:C,$B$3,收入流水表!A:A,A13) -> 2474 | C13: =SUMIFS(收入流水表!J:J,收入流水表!C:C,$C$3,收入流水表!A:A,A13) -> 0 | D13: =SUMIFS(收入流水表!J:J,收入流水表!C:C,$D$3,收入流水表!A:A,A13) -> 1030 | E13: =SUMIFS(收入流水表!J:J,收入流水表!C:C,$E$3,收入流水表!A:A,A13) -> 0 | F13: =SUM(B13:E13) -> 3504 | G13: =SUMIFS(收入流水表!J:J,收入流水表!C:C,$G$3,收入流水表!A:A,A13) -> 61 | H13: =SUMIFS(收入流水表!J:J,收入流水表!C:C,$H$3,收入流水表!A:A,A13) -> 5 | I13: =SUMIFS(收入流水表!J:J,收入流水表!C:C,$I$3,收入流水表!A:A,A13) -> 19.9 | J13: =SUMIFS(收入流水表!J:J,收入流水表!C:C,$J$3,收入流水表!A:A,A13) -> 39.9 | K13: =SUMIFS(收入流水表!J:J,收入流水表!C:C,$K$3,收入流水表!A:A,A13) -> 0 | L13: =SUM(G13:K13) -> 125.8 | M13: =F13+L13 -> 3629.8 | N13: =SUMIFS(收入流水表!J:J,收入流水表!I:I,$N$3,收入流水表!A:A,A13) -> 3504 | O13: =SUMIFS(收入流水表!J:J,收入流水表!I:I,$O$3,收入流水表!A:A,A13) -> 0 | P13: =SUMIFS(收入流水表!J:J,收入流水表!I:I,$P$3,收入流水表!A:A,A13) -> 0 | Q13: =SUMIFS(收入流水表!J:J,收入流水表!I:I,$Q$3,收入流水表!A:A,A13) -> 0
A14: 46214 | B14: =SUMIFS(收入流水表!J:J,收入流水表!C:C,$B$3,收入流水表!A:A,A14) -> 4163 | C14: =SUMIFS(收入流水表!J:J,收入流水表!C:C,$C$3,收入流水表!A:A,A14) -> 0 | D14: =SUMIFS(收入流水表!J:J,收入流水表!C:C,$D$3,收入流水表!A:A,A14) -> 3558 | E14: =SUMIFS(收入流水表!J:J,收入流水表!C:C,$E$3,收入流水表!A:A,A14) -> 0 | F14: =SUM(B14:E14) -> 7721 | G14: =SUMIFS(收入流水表!J:J,收入流水表!C:C,$G$3,收入流水表!A:A,A14) -> 63 | H14: =SUMIFS(收入流水表!J:J,收入流水表!C:C,$H$3,收入流水表!A:A,A14) -> 45 | I14: =SUMIFS(收入流水表!J:J,收入流水表!C:C,$I$3,收入流水表!A:A,A14) -> 34.8 | J14: =SUMIFS(收入流水表!J:J,收入流水表!C:C,$J$3,收入流水表!A:A,A14) -> 79.8 | K14: =SUMIFS(收入流水表!J:J,收入流水表!C:C,$K$3,收入流水表!A:A,A14) -> 0 | L14: =SUM(G14:K14) -> 222.6 | M14: =F14+L14 -> 7943.6 | N14: =SUMIFS(收入流水表!J:J,收入流水表!I:I,$N$3,收入流水表!A:A,A14) -> 5673 | O14: =SUMIFS(收入流水表!J:J,收入流水表!I:I,$O$3,收入流水表!A:A,A14) -> 2048 | P14: =SUMIFS(收入流水表!J:J,收入流水表!I:I,$P$3,收入流水表!A:A,A14) -> 0 | Q14: =SUMIFS(收入流水表!J:J,收入流水表!I:I,$Q$3,收入流水表!A:A,A14) -> 0
A15: 46215 | B15: =SUMIFS(收入流水表!J:J,收入流水表!C:C,$B$3,收入流水表!A:A,A15) -> 1497 | C15: =SUMIFS(收入流水表!J:J,收入流水表!C:C,$C$3,收入流水表!A:A,A15) -> 0 | D15: =SUMIFS(收入流水表!J:J,收入流水表!C:C,$D$3,收入流水表!A:A,A15) -> 2720 | E15: =SUMIFS(收入流水表!J:J,收入流水表!C:C,$E$3,收入流水表!A:A,A15) -> 0 | F15: =SUM(B15:E15) -> 4217 | G15: =SUMIFS(收入流水表!J:J,收入流水表!C:C,$G$3,收入流水表!A:A,A15) -> 17 | H15: =SUMIFS(收入流水表!J:J,收入流水表!C:C,$H$3,收入流水表!A:A,A15) -> 40 | I15: =SUMIFS(收入流水表!J:J,收入流水表!C:C,$I$3,收入流水表!A:A,A15) -> 19.9 | J15: =SUMIFS(收入流水表!J:J,收入流水表!C:C,$J$3,收入流水表!A:A,A15) -> 0 | K15: =SUMIFS(收入流水表!J:J,收入流水表!C:C,$K$3,收入流水表!A:A,A15) -> 0 | L15: =SUM(G15:K15) -> 76.9 | M15: =F15+L15 -> 4293.9 | N15: =SUMIFS(收入流水表!J:J,收入流水表!I:I,$N$3,收入流水表!A:A,A15) -> 4217 | O15: =SUMIFS(收入流水表!J:J,收入流水表!I:I,$O$3,收入流水表!A:A,A15) -> 0 | P15: =SUMIFS(收入流水表!J:J,收入流水表!I:I,$P$3,收入流水表!A:A,A15) -> 0 | Q15: =SUMIFS(收入流水表!J:J,收入流水表!I:I,$Q$3,收入流水表!A:A,A15) -> 0
A16: 46216 | B16: =SUMIFS(收入流水表!J:J,收入流水表!C:C,$B$3,收入流水表!A:A,A16) -> 0 | C16: =SUMIFS(收入流水表!J:J,收入流水表!C:C,$C$3,收入流水表!A:A,A16) -> 0 | D16: =SUMIFS(收入流水表!J:J,收入流水表!C:C,$D$3,收入流水表!A:A,A16) -> 0 | E16: =SUMIFS(收入流水表!J:J,收入流水表!C:C,$E$3,收入流水表!A:A,A16) -> 0 | F16: =SUM(B16:E16) -> 0 | G16: =SUMIFS(收入流水表!J:J,收入流水表!C:C,$G$3,收入流水表!A:A,A16) -> 0 | H16: =SUMIFS(收入流水表!J:J,收入流水表!C:C,$H$3,收入流水表!A:A,A16) -> 0 | I16: =SUMIFS(收入流水表!J:J,收入流水表!C:C,$I$3,收入流水表!A:A,A16) -> 0 | J16: =SUMIFS(收入流水表!J:J,收入流水表!C:C,$J$3,收入流水表!A:A,A16) -> 0 | K16: =SUMIFS(收入流水表!J:J,收入流水表!C:C,$K$3,收入流水表!A:A,A16) -> 0 | L16: =SUM(G16:K16) -> 0 | M16: =F16+L16 -> 0 | N16: =SUMIFS(收入流水表!J:J,收入流水表!I:I,$N$3,收入流水表!A:A,A16) -> 0 | O16: =SUMIFS(收入流水表!J:J,收入流水表!I:I,$O$3,收入流水表!A:A,A16) -> 0 | P16: =SUMIFS(收入流水表!J:J,收入流水表!I:I,$P$3,收入流水表!A:A,A16) -> 0 | Q16: =SUMIFS(收入流水表!J:J,收入流水表!I:I,$Q$3,收入流水表!A:A,A16) -> 0
A17: 46217 | B17: =SUMIFS(收入流水表!J:J,收入流水表!C:C,$B$3,收入流水表!A:A,A17) -> 0 | C17: =SUMIFS(收入流水表!J:J,收入流水表!C:C,$C$3,收入流水表!A:A,A17) -> 0 | D17: =SUMIFS(收入流水表!J:J,收入流水表!C:C,$D$3,收入流水表!A:A,A17) -> 0 | E17: =SUMIFS(收入流水表!J:J,收入流水表!C:C,$E$3,收入流水表!A:A,A17) -> 0 | F17: =SUM(B17:E17) -> 0 | G17: =SUMIFS(收入流水表!J:J,收入流水表!C:C,$G$3,收入流水表!A:A,A17) -> 0 | H17: =SUMIFS(收入流水表!J:J,收入流水表!C:C,$H$3,收入流水表!A:A,A17) -> 0 | I17: =SUMIFS(收入流水表!J:J,收入流水表!C:C,$I$3,收入流水表!A:A,A17) -> 0 | J17: =SUMIFS(收入流水表!J:J,收入流水表!C:C,$J$3,收入流水表!A:A,A17) -> 0 | K17: =SUMIFS(收入流水表!J:J,收入流水表!C:C,$K$3,收入流水表!A:A,A17) -> 0 | L17: =SUM(G17:K17) -> 0 | M17: =F17+L17 -> 0 | N17: =SUMIFS(收入流水表!J:J,收入流水表!I:I,$N$3,收入流水表!A:A,A17) -> 0 | O17: =SUMIFS(收入流水表!J:J,收入流水表!I:I,$O$3,收入流水表!A:A,A17) -> 0 | P17: =SUMIFS(收入流水表!J:J,收入流水表!I:I,$P$3,收入流水表!A:A,A17) -> 0 | Q17: =SUMIFS(收入流水表!J:J,收入流水表!I:I,$Q$3,收入流水表!A:A,A17) -> 0
A18: 46218 | B18: =SUMIFS(收入流水表!J:J,收入流水表!C:C,$B$3,收入流水表!A:A,A18) -> 0 | C18: =SUMIFS(收入流水表!J:J,收入流水表!C:C,$C$3,收入流水表!A:A,A18) -> 0 | D18: =SUMIFS(收入流水表!J:J,收入流水表!C:C,$D$3,收入流水表!A:A,A18) -> 0 | E18: =SUMIFS(收入流水表!J:J,收入流水表!C:C,$E$3,收入流水表!A:A,A18) -> 0 | F18: =SUM(B18:E18) -> 0 | G18: =SUMIFS(收入流水表!J:J,收入流水表!C:C,$G$3,收入流水表!A:A,A18) -> 0 | H18: =SUMIFS(收入流水表!J:J,收入流水表!C:C,$H$3,收入流水表!A:A,A18) -> 0 | I18: =SUMIFS(收入流水表!J:J,收入流水表!C:C,$I$3,收入流水表!A:A,A18) -> 0 | J18: =SUMIFS(收入流水表!J:J,收入流水表!C:C,$J$3,收入流水表!A:A,A18) -> 0 | K18: =SUMIFS(收入流水表!J:J,收入流水表!C:C,$K$3,收入流水表!A:A,A18) -> 0 | L18: =SUM(G18:K18) -> 0 | M18: =F18+L18-K18 -> 0 | N18: =SUMIFS(收入流水表!J:J,收入流水表!I:I,$N$3,收入流水表!A:A,A18) -> 0 | O18: =SUMIFS(收入流水表!J:J,收入流水表!I:I,$O$3,收入流水表!A:A,A18) -> 0 | P18: =SUMIFS(收入流水表!J:J,收入流水表!I:I,$P$3,收入流水表!A:A,A18) -> 0 | Q18: =SUMIFS(收入流水表!J:J,收入流水表!I:I,$Q$3,收入流水表!A:A,A18) -> 0
A19: 46219 | B19: =SUMIFS(收入流水表!J:J,收入流水表!C:C,$B$3,收入流水表!A:A,A19) -> 0 | C19: =SUMIFS(收入流水表!J:J,收入流水表!C:C,$C$3,收入流水表!A:A,A19) -> 0 | D19: =SUMIFS(收入流水表!J:J,收入流水表!C:C,$D$3,收入流水表!A:A,A19) -> 0 | E19: =SUMIFS(收入流水表!J:J,收入流水表!C:C,$E$3,收入流水表!A:A,A19) -> 0 | F19: =SUM(B19:E19) -> 0 | G19: =SUMIFS(收入流水表!J:J,收入流水表!C:C,$G$3,收入流水表!A:A,A19) -> 0 | H19: =SUMIFS(收入流水表!J:J,收入流水表!C:C,$H$3,收入流水表!A:A,A19) -> 0 | I19: =SUMIFS(收入流水表!J:J,收入流水表!C:C,$I$3,收入流水表!A:A,A19) -> 0 | J19: =SUMIFS(收入流水表!J:J,收入流水表!C:C,$J$3,收入流水表!A:A,A19) -> 0 | K19: =SUMIFS(收入流水表!J:J,收入流水表!C:C,$K$3,收入流水表!A:A,A19) -> 0 | L19: =SUM(G19:K19) -> 0 | M19: =F19+L19 -> 0 | N19: =SUMIFS(收入流水表!J:J,收入流水表!I:I,$N$3,收入流水表!A:A,A19) -> 0 | O19: =SUMIFS(收入流水表!J:J,收入流水表!I:I,$O$3,收入流水表!A:A,A19) -> 0 | P19: =SUMIFS(收入流水表!J:J,收入流水表!I:I,$P$3,收入流水表!A:A,A19) -> 0 | Q19: =SUMIFS(收入流水表!J:J,收入流水表!I:I,$Q$3,收入流水表!A:A,A19) -> 0
A20: 46220 | B20: =SUMIFS(收入流水表!J:J,收入流水表!C:C,$B$3,收入流水表!A:A,A20) -> 0 | C20: =SUMIFS(收入流水表!J:J,收入流水表!C:C,$C$3,收入流水表!A:A,A20) -> 0 | D20: =SUMIFS(收入流水表!J:J,收入流水表!C:C,$D$3,收入流水表!A:A,A20) -> 0 | E20: =SUMIFS(收入流水表!J:J,收入流水表!C:C,$E$3,收入流水表!A:A,A20) -> 0 | F20: =SUM(B20:E20) -> 0 | G20: =SUMIFS(收入流水表!J:J,收入流水表!C:C,$G$3,收入流水表!A:A,A20) -> 0 | H20: =SUMIFS(收入流水表!J:J,收入流水表!C:C,$H$3,收入流水表!A:A,A20) -> 0 | I20: =SUMIFS(收入流水表!J:J,收入流水表!C:C,$I$3,收入流水表!A:A,A20) -> 0 | J20: =SUMIFS(收入流水表!J:J,收入流水表!C:C,$J$3,收入流水表!A:A,A20) -> 0 | K20: =SUMIFS(收入流水表!J:J,收入流水表!C:C,$K$3,收入流水表!A:A,A20) -> 0 | L20: =SUM(G20:K20) -> 0 | M20: =F20+L20 -> 0 | N20: =SUMIFS(收入流水表!J:J,收入流水表!I:I,$N$3,收入流水表!A:A,A20) -> 0 | O20: =SUMIFS(收入流水表!J:J,收入流水表!I:I,$O$3,收入流水表!A:A,A20) -> 0 | P20: =SUMIFS(收入流水表!J:J,收入流水表!I:I,$P$3,收入流水表!A:A,A20) -> 0 | Q20: =SUMIFS(收入流水表!J:J,收入流水表!I:I,$Q$3,收入流水表!A:A,A20) -> 0
A21: 46221 | B21: =SUMIFS(收入流水表!J:J,收入流水表!C:C,$B$3,收入流水表!A:A,A21) -> 0 | C21: =SUMIFS(收入流水表!J:J,收入流水表!C:C,$C$3,收入流水表!A:A,A21) -> 0 | D21: =SUMIFS(收入流水表!J:J,收入流水表!C:C,$D$3,收入流水表!A:A,A21) -> 0 | E21: =SUMIFS(收入流水表!J:J,收入流水表!C:C,$E$3,收入流水表!A:A,A21) -> 0 | F21: =SUM(B21:E21) -> 0 | G21: =SUMIFS(收入流水表!J:J,收入流水表!C:C,$G$3,收入流水表!A:A,A21) -> 0 | H21: =SUMIFS(收入流水表!J:J,收入流水表!C:C,$H$3,收入流水表!A:A,A21) -> 0 | I21: =SUMIFS(收入流水表!J:J,收入流水表!C:C,$I$3,收入流水表!A:A,A21) -> 0 | J21: =SUMIFS(收入流水表!J:J,收入流水表!C:C,$J$3,收入流水表!A:A,A21) -> 0 | K21: =SUMIFS(收入流水表!J:J,收入流水表!C:C,$K$3,收入流水表!A:A,A21) -> 0 | L21: =SUM(G21:K21) -> 0 | M21: =F21+L21 -> 0 | N21: =SUMIFS(收入流水表!J:J,收入流水表!I:I,$N$3,收入流水表!A:A,A21) -> 0 | O21: =SUMIFS(收入流水表!J:J,收入流水表!I:I,$O$3,收入流水表!A:A,A21) -> 0 | P21: =SUMIFS(收入流水表!J:J,收入流水表!I:I,$P$3,收入流水表!A:A,A21) -> 0 | Q21: =SUMIFS(收入流水表!J:J,收入流水表!I:I,$Q$3,收入流水表!A:A,A21) -> 0
A22: 46222 | B22: =SUMIFS(收入流水表!J:J,收入流水表!C:C,$B$3,收入流水表!A:A,A22) -> 0 | C22: =SUMIFS(收入流水表!J:J,收入流水表!C:C,$C$3,收入流水表!A:A,A22) -> 0 | D22: =SUMIFS(收入流水表!J:J,收入流水表!C:C,$D$3,收入流水表!A:A,A22) -> 0 | E22: =SUMIFS(收入流水表!J:J,收入流水表!C:C,$E$3,收入流水表!A:A,A22) -> 0 | F22: =SUM(B22:E22) -> 0 | G22: =SUMIFS(收入流水表!J:J,收入流水表!C:C,$G$3,收入流水表!A:A,A22) -> 0 | H22: =SUMIFS(收入流水表!J:J,收入流水表!C:C,$H$3,收入流水表!A:A,A22) -> 0 | I22: =SUMIFS(收入流水表!J:J,收入流水表!C:C,$I$3,收入流水表!A:A,A22) -> 0 | J22: =SUMIFS(收入流水表!J:J,收入流水表!C:C,$J$3,收入流水表!A:A,A22) -> 0 | K22: =SUMIFS(收入流水表!J:J,收入流水表!C:C,$K$3,收入流水表!A:A,A22) -> 0 | L22: =SUM(G22:K22) -> 0 | M22: =F22+L22 -> 0 | N22: =SUMIFS(收入流水表!J:J,收入流水表!I:I,$N$3,收入流水表!A:A,A22) -> 0 | O22: =SUMIFS(收入流水表!J:J,收入流水表!I:I,$O$3,收入流水表!A:A,A22) -> 0 | P22: =SUMIFS(收入流水表!J:J,收入流水表!I:I,$P$3,收入流水表!A:A,A22) -> 0 | Q22: =SUMIFS(收入流水表!J:J,收入流水表!I:I,$Q$3,收入流水表!A:A,A22) -> 0
A23: 46223 | B23: =SUMIFS(收入流水表!J:J,收入流水表!C:C,$B$3,收入流水表!A:A,A23) -> 0 | C23: =SUMIFS(收入流水表!J:J,收入流水表!C:C,$C$3,收入流水表!A:A,A23) -> 0 | D23: =SUMIFS(收入流水表!J:J,收入流水表!C:C,$D$3,收入流水表!A:A,A23) -> 0 | E23: =SUMIFS(收入流水表!J:J,收入流水表!C:C,$E$3,收入流水表!A:A,A23) -> 0 | F23: =SUM(B23:E23) -> 0 | G23: =SUMIFS(收入流水表!J:J,收入流水表!C:C,$G$3,收入流水表!A:A,A23) -> 0 | H23: =SUMIFS(收入流水表!J:J,收入流水表!C:C,$H$3,收入流水表!A:A,A23) -> 0 | I23: =SUMIFS(收入流水表!J:J,收入流水表!C:C,$I$3,收入流水表!A:A,A23) -> 0 | J23: =SUMIFS(收入流水表!J:J,收入流水表!C:C,$J$3,收入流水表!A:A,A23) -> 0 | K23: =SUMIFS(收入流水表!J:J,收入流水表!C:C,$K$3,收入流水表!A:A,A23) -> 0 | L23: =SUM(G23:K23) -> 0 | M23: =F23+L23 -> 0 | N23: =SUMIFS(收入流水表!J:J,收入流水表!I:I,$N$3,收入流水表!A:A,A23) -> 0 | O23: =SUMIFS(收入流水表!J:J,收入流水表!I:I,$O$3,收入流水表!A:A,A23) -> 0 | P23: =SUMIFS(收入流水表!J:J,收入流水表!I:I,$P$3,收入流水表!A:A,A23) -> 0 | Q23: =SUMIFS(收入流水表!J:J,收入流水表!I:I,$Q$3,收入流水表!A:A,A23) -> 0
A24: 46224 | B24: =SUMIFS(收入流水表!J:J,收入流水表!C:C,$B$3,收入流水表!A:A,A24) -> 0 | C24: =SUMIFS(收入流水表!J:J,收入流水表!C:C,$C$3,收入流水表!A:A,A24) -> 0 | D24: =SUMIFS(收入流水表!J:J,收入流水表!C:C,$D$3,收入流水表!A:A,A24) -> 0 | E24: =SUMIFS(收入流水表!J:J,收入流水表!C:C,$E$3,收入流水表!A:A,A24) -> 0 | F24: =SUM(B24:E24) -> 0 | G24: =SUMIFS(收入流水表!J:J,收入流水表!C:C,$G$3,收入流水表!A:A,A24) -> 0 | H24: =SUMIFS(收入流水表!J:J,收入流水表!C:C,$H$3,收入流水表!A:A,A24) -> 0 | I24: =SUMIFS(收入流水表!J:J,收入流水表!C:C,$I$3,收入流水表!A:A,A24) -> 0 | J24: =SUMIFS(收入流水表!J:J,收入流水表!C:C,$J$3,收入流水表!A:A,A24) -> 0 | K24: =SUMIFS(收入流水表!J:J,收入流水表!C:C,$K$3,收入流水表!A:A,A24) -> 0 | L24: =SUM(G24:K24) -> 0 | M24: =F24+L24 -> 0 | N24: =SUMIFS(收入流水表!J:J,收入流水表!I:I,$N$3,收入流水表!A:A,A24) -> 0 | O24: =SUMIFS(收入流水表!J:J,收入流水表!I:I,$O$3,收入流水表!A:A,A24) -> 0 | P24: =SUMIFS(收入流水表!J:J,收入流水表!I:I,$P$3,收入流水表!A:A,A24) -> 0 | Q24: =SUMIFS(收入流水表!J:J,收入流水表!I:I,$Q$3,收入流水表!A:A,A24) -> 0
A25: 46225 | B25: =SUMIFS(收入流水表!J:J,收入流水表!C:C,$B$3,收入流水表!A:A,A25) -> 0 | C25: =SUMIFS(收入流水表!J:J,收入流水表!C:C,$C$3,收入流水表!A:A,A25) -> 0 | D25: =SUMIFS(收入流水表!J:J,收入流水表!C:C,$D$3,收入流水表!A:A,A25) -> 0 | E25: =SUMIFS(收入流水表!J:J,收入流水表!C:C,$E$3,收入流水表!A:A,A25) -> 0 | F25: =SUM(B25:E25) -> 0 | G25: =SUMIFS(收入流水表!J:J,收入流水表!C:C,$G$3,收入流水表!A:A,A25) -> 0 | H25: =SUMIFS(收入流水表!J:J,收入流水表!C:C,$H$3,收入流水表!A:A,A25) -> 0 | I25: =SUMIFS(收入流水表!J:J,收入流水表!C:C,$I$3,收入流水表!A:A,A25) -> 0 | J25: =SUMIFS(收入流水表!J:J,收入流水表!C:C,$J$3,收入流水表!A:A,A25) -> 0 | K25: =SUMIFS(收入流水表!J:J,收入流水表!C:C,$K$3,收入流水表!A:A,A25) -> 0 | L25: =SUM(G25:K25) -> 0 | M25: =F25+L25 -> 0 | N25: =SUMIFS(收入流水表!J:J,收入流水表!I:I,$N$3,收入流水表!A:A,A25) -> 0 | O25: =SUMIFS(收入流水表!J:J,收入流水表!I:I,$O$3,收入流水表!A:A,A25) -> 0 | P25: =SUMIFS(收入流水表!J:J,收入流水表!I:I,$P$3,收入流水表!A:A,A25) -> 0 | Q25: =SUMIFS(收入流水表!J:J,收入流水表!I:I,$Q$3,收入流水表!A:A,A25) -> 0
A26: 46226 | B26: =SUMIFS(收入流水表!J:J,收入流水表!C:C,$B$3,收入流水表!A:A,A26) -> 0 | C26: =SUMIFS(收入流水表!J:J,收入流水表!C:C,$C$3,收入流水表!A:A,A26) -> 0 | D26: =SUMIFS(收入流水表!J:J,收入流水表!C:C,$D$3,收入流水表!A:A,A26) -> 0 | E26: =SUMIFS(收入流水表!J:J,收入流水表!C:C,$E$3,收入流水表!A:A,A26) -> 0 | F26: =SUM(B26:E26) -> 0 | G26: =SUMIFS(收入流水表!J:J,收入流水表!C:C,$G$3,收入流水表!A:A,A26) -> 0 | H26: =SUMIFS(收入流水表!J:J,收入流水表!C:C,$H$3,收入流水表!A:A,A26) -> 0 | I26: =SUMIFS(收入流水表!J:J,收入流水表!C:C,$I$3,收入流水表!A:A,A26) -> 0 | J26: =SUMIFS(收入流水表!J:J,收入流水表!C:C,$J$3,收入流水表!A:A,A26) -> 0 | K26: =SUMIFS(收入流水表!J:J,收入流水表!C:C,$K$3,收入流水表!A:A,A26) -> 0 | L26: =SUM(G26:K26) -> 0 | M26: =F26+L26 -> 0 | N26: =SUMIFS(收入流水表!J:J,收入流水表!I:I,$N$3,收入流水表!A:A,A26) -> 0 | O26: =SUMIFS(收入流水表!J:J,收入流水表!I:I,$O$3,收入流水表!A:A,A26) -> 0 | P26: =SUMIFS(收入流水表!J:J,收入流水表!I:I,$P$3,收入流水表!A:A,A26) -> 0 | Q26: =SUMIFS(收入流水表!J:J,收入流水表!I:I,$Q$3,收入流水表!A:A,A26) -> 0
A27: 46227 | B27: =SUMIFS(收入流水表!J:J,收入流水表!C:C,$B$3,收入流水表!A:A,A27) -> 0 | C27: =SUMIFS(收入流水表!J:J,收入流水表!C:C,$C$3,收入流水表!A:A,A27) -> 0 | D27: =SUMIFS(收入流水表!J:J,收入流水表!C:C,$D$3,收入流水表!A:A,A27) -> 0 | E27: =SUMIFS(收入流水表!J:J,收入流水表!C:C,$E$3,收入流水表!A:A,A27) -> 0 | F27: =SUM(B27:E27) -> 0 | G27: =SUMIFS(收入流水表!J:J,收入流水表!C:C,$G$3,收入流水表!A:A,A27) -> 0 | H27: =SUMIFS(收入流水表!J:J,收入流水表!C:C,$H$3,收入流水表!A:A,A27) -> 0 | I27: =SUMIFS(收入流水表!J:J,收入流水表!C:C,$I$3,收入流水表!A:A,A27) -> 0 | J27: =SUMIFS(收入流水表!J:J,收入流水表!C:C,$J$3,收入流水表!A:A,A27) -> 0 | K27: =SUMIFS(收入流水表!J:J,收入流水表!C:C,$K$3,收入流水表!A:A,A27) -> 0 | L27: =SUM(G27:K27) -> 0 | M27: =F27+L27 -> 0 | N27: =SUMIFS(收入流水表!J:J,收入流水表!I:I,$N$3,收入流水表!A:A,A27) -> 0 | O27: =SUMIFS(收入流水表!J:J,收入流水表!I:I,$O$3,收入流水表!A:A,A27) -> 0 | P27: =SUMIFS(收入流水表!J:J,收入流水表!I:I,$P$3,收入流水表!A:A,A27) -> 0 | Q27: =SUMIFS(收入流水表!J:J,收入流水表!I:I,$Q$3,收入流水表!A:A,A27) -> 0
A28: 46228 | B28: =SUMIFS(收入流水表!J:J,收入流水表!C:C,$B$3,收入流水表!A:A,A28) -> 0 | C28: =SUMIFS(收入流水表!J:J,收入流水表!C:C,$C$3,收入流水表!A:A,A28) -> 0 | D28: =SUMIFS(收入流水表!J:J,收入流水表!C:C,$D$3,收入流水表!A:A,A28) -> 0 | E28: =SUMIFS(收入流水表!J:J,收入流水表!C:C,$E$3,收入流水表!A:A,A28) -> 0 | F28: =SUM(B28:E28) -> 0 | G28: =SUMIFS(收入流水表!J:J,收入流水表!C:C,$G$3,收入流水表!A:A,A28) -> 0 | H28: =SUMIFS(收入流水表!J:J,收入流水表!C:C,$H$3,收入流水表!A:A,A28) -> 0 | I28: =SUMIFS(收入流水表!J:J,收入流水表!C:C,$I$3,收入流水表!A:A,A28) -> 0 | J28: =SUMIFS(收入流水表!J:J,收入流水表!C:C,$J$3,收入流水表!A:A,A28) -> 0 | K28: =SUMIFS(收入流水表!J:J,收入流水表!C:C,$K$3,收入流水表!A:A,A28) -> 0 | L28: =SUM(G28:K28) -> 0 | M28: =F28+L28 -> 0 | N28: =SUMIFS(收入流水表!J:J,收入流水表!I:I,$N$3,收入流水表!A:A,A28) -> 0 | O28: =SUMIFS(收入流水表!J:J,收入流水表!I:I,$O$3,收入流水表!A:A,A28) -> 0 | P28: =SUMIFS(收入流水表!J:J,收入流水表!I:I,$P$3,收入流水表!A:A,A28) -> 0 | Q28: =SUMIFS(收入流水表!J:J,收入流水表!I:I,$Q$3,收入流水表!A:A,A28) -> 0
A29: 46229 | B29: =SUMIFS(收入流水表!J:J,收入流水表!C:C,$B$3,收入流水表!A:A,A29) -> 0 | C29: =SUMIFS(收入流水表!J:J,收入流水表!C:C,$C$3,收入流水表!A:A,A29) -> 0 | D29: =SUMIFS(收入流水表!J:J,收入流水表!C:C,$D$3,收入流水表!A:A,A29) -> 0 | E29: =SUMIFS(收入流水表!J:J,收入流水表!C:C,$E$3,收入流水表!A:A,A29) -> 0 | F29: =SUM(B29:E29) -> 0 | G29: =SUMIFS(收入流水表!J:J,收入流水表!C:C,$G$3,收入流水表!A:A,A29) -> 0 | H29: =SUMIFS(收入流水表!J:J,收入流水表!C:C,$H$3,收入流水表!A:A,A29) -> 0 | I29: =SUMIFS(收入流水表!J:J,收入流水表!C:C,$I$3,收入流水表!A:A,A29) -> 0 | J29: =SUMIFS(收入流水表!J:J,收入流水表!C:C,$J$3,收入流水表!A:A,A29) -> 0 | K29: =SUMIFS(收入流水表!J:J,收入流水表!C:C,$K$3,收入流水表!A:A,A29) -> 0 | L29: =SUM(G29:K29) -> 0 | M29: =F29+L29 -> 0 | N29: =SUMIFS(收入流水表!J:J,收入流水表!I:I,$N$3,收入流水表!A:A,A29) -> 0 | O29: =SUMIFS(收入流水表!J:J,收入流水表!I:I,$O$3,收入流水表!A:A,A29) -> 0 | P29: =SUMIFS(收入流水表!J:J,收入流水表!I:I,$P$3,收入流水表!A:A,A29) -> 0 | Q29: =SUMIFS(收入流水表!J:J,收入流水表!I:I,$Q$3,收入流水表!A:A,A29) -> 0
A30: 46230 | B30: =SUMIFS(收入流水表!J:J,收入流水表!C:C,$B$3,收入流水表!A:A,A30) -> 0 | C30: =SUMIFS(收入流水表!J:J,收入流水表!C:C,$C$3,收入流水表!A:A,A30) -> 0 | D30: =SUMIFS(收入流水表!J:J,收入流水表!C:C,$D$3,收入流水表!A:A,A30) -> 0 | E30: =SUMIFS(收入流水表!J:J,收入流水表!C:C,$E$3,收入流水表!A:A,A30) -> 0 | F30: =SUM(B30:E30) -> 0 | G30: =SUMIFS(收入流水表!J:J,收入流水表!C:C,$G$3,收入流水表!A:A,A30) -> 0 | H30: =SUMIFS(收入流水表!J:J,收入流水表!C:C,$H$3,收入流水表!A:A,A30) -> 0 | I30: =SUMIFS(收入流水表!J:J,收入流水表!C:C,$I$3,收入流水表!A:A,A30) -> 0 | J30: =SUMIFS(收入流水表!J:J,收入流水表!C:C,$J$3,收入流水表!A:A,A30) -> 0 | K30: =SUMIFS(收入流水表!J:J,收入流水表!C:C,$K$3,收入流水表!A:A,A30) -> 0 | L30: =SUM(G30:K30) -> 0 | M30: =F30+L30 -> 0 | N30: =SUMIFS(收入流水表!J:J,收入流水表!I:I,$N$3,收入流水表!A:A,A30) -> 0 | O30: =SUMIFS(收入流水表!J:J,收入流水表!I:I,$O$3,收入流水表!A:A,A30) -> 0 | P30: =SUMIFS(收入流水表!J:J,收入流水表!I:I,$P$3,收入流水表!A:A,A30) -> 0 | Q30: =SUMIFS(收入流水表!J:J,收入流水表!I:I,$Q$3,收入流水表!A:A,A30) -> 0
... A34: 46234 | B34: =SUMIFS(收入流水表!J:J,收入流水表!C:C,$B$3,收入流水表!A:A,A34) -> 0 | C34: =SUMIFS(收入流水表!J:J,收入流水表!C:C,$C$3,收入流水表!A:A,A34) -> 0 | D34: =SUMIFS(收入流水表!J:J,收入流水表!C:C,$D$3,收入流水表!A:A,A34) -> 0 | E34: =SUMIFS(收入流水表!J:J,收入流水表!C:C,$E$3,收入流水表!A:A,A34) -> 0 | F34: =SUM(B34:E34) -> 0 | G34: =SUMIFS(收入流水表!J:J,收入流水表!C:C,$G$3,收入流水表!A:A,A34) -> 0 | H34: =SUMIFS(收入流水表!J:J,收入流水表!C:C,$H$3,收入流水表!A:A,A34) -> 0 | I34: =SUMIFS(收入流水表!J:J,收入流水表!C:C,$I$3,收入流水表!A:A,A34) -> 0 | J34: =SUMIFS(收入流水表!J:J,收入流水表!C:C,$J$3,收入流水表!A:A,A34) -> 0 | K34: =SUMIFS(收入流水表!J:J,收入流水表!C:C,$K$3,收入流水表!A:A,A34) -> 0 | L34: =SUM(G34:K34) -> 0 | M34: =F34+L34 -> 0 | N34: =SUMIFS(收入流水表!J:J,收入流水表!I:I,$N$3,收入流水表!A:A,A34) -> 0 | O34: =SUMIFS(收入流水表!J:J,收入流水表!I:I,$O$3,收入流水表!A:A,A34) -> 0 | P34: =SUMIFS(收入流水表!J:J,收入流水表!I:I,$P$3,收入流水表!A:A,A34) -> 0 | Q34: =SUMIFS(收入流水表!J:J,收入流水表!I:I,$Q$3,收入流水表!A:A,A34) -> 0
A35: 7月合计 | B35: =SUM(B4:B34) -> 33553 | C35: =SUM(C4:C34) -> 0 | D35: =SUM(D4:D34) -> 40534 | E35: =SUM(E4:E34) -> 0 | F35: =SUM(F4:F34) -> 74087 | G35: =SUM(G4:G34) -> 718 | H35: =SUM(H4:H34) -> 505 | I35: =SUM(I4:I34) -> 429.9 | ... Q35: =SUM(Q4:Q34) -> 160
C37: =B35+D35 -> 74087

Sheet 收入流水表
A1: 日期 | B1: 收据编号 | C1: 收入类别 | D1: 姓名 | E1: 联系方式 | F1: 卡种/课种 | G1: 课时节数 | H1: 付款类别 | I1: 付款方式 | J1: 金额 | K1: 是否添加微信 | L1: 业绩奖励人 | M1: 奖励机制 | N1: 经办人 | O1: 备注 | P1: 合约编号 | Q1: 是否续卡/续课 | R1: 是否核单 | S1: 会员是否签字 | T1: 类型 | U1: 使用门店
A2: 46204 | B2: 3232934 | C2: 会籍收入 | D2: 姚起斌 | E2: 15390898980 | F2: 月卡 | H2: 全款 | I2: 微信 | J2: 297 | N2: 刘嘉俊 | O2: 抖音验券月卡 | P2: 9130930 | Q2: 否 | R2: 是 | S2: 是
A3: 46204 | C3: 水吧收入 | J3: 51 | O3: 水*10/纸*1/维他命*2/外星人*1/水溶*1/东方树叶*1
A4: 46204 | C4: 美团收入 | J4: 49.7 | O4: 14.9*2/19.9*1
A5: 46204 | C5: 抖音收入 | J5: 19.9 | O5: 19.9*1
A6: 46205 | B6: 3232935 | C6: 教练班收入 | D6: 杨蓓澄 | E6: 13870661059 | F6: 游泳培训班 | H6: 全款 | I6: 微信 | J6: 880 | N6: 肖翠 | O6: 一对四泳培送一个月，送泳镜，泳帽，鼻夹（已退款） | P6: 9310732 | Q6: 否 | R6: 是 | S6: 是
A7: 46205 | B7: 3232936 | C7: 会籍收入 | D7: 石拥强 | E7: 15070042767 | F7: 月卡 | H7: 全款 | I7: 微信 | J7: 281 | N7: 肖翠 | O7: 月卡 | P7: 9131471 | Q7: 否 | R7: 是 | S7: 是
A8: 46205 | B8: 3232937 | C8: 会籍收入 | D8: 罗琳皓 | E8: 18070090478 | F8: 月卡 | H8: 全款 | I8: 微信 | J8: 293 | N8: 肖翠 | O8: 月卡 | P8: 9131472 | Q8: 否 | R8: 是 | S8: 是
A9: 46205 | C9: 水吧收入 | J9: 61 | O9: 水*24/纸*/维他*1/脉*1
A10: 46205 | C10: 美团收入 | J10: 19.9 | O10: 19.9*1
A11: 46205 | C11: 抖音收入 | J11: 19.9 | O11: 19.9*1
A12: 46206 | B12: 2855837 | C12: 会籍收入 | D12: 万月霞 | E12: 13257313595 | F12: 月卡 | H12: 全款 | I12: 支付宝 | J12: 299 | N12: 刘嘉俊 | O12: 月卡 | P12: 9131473 | Q12: 否 | R12: 是 | S12: 是
A13: 46206 | B13: 2855838 | C13: 会籍收入 | D13: 汤寒张 | E13: 13044918527 | F13: 月卡 | H13: 全款 | I13: 微信 | J13: 499 | N13: 肖翠 | O13: 双月卡 | P13: 9131474 | Q13: 否 | R13: 是 | S13: 是
A14: 46206 | B14: 2855839 | C14: 教练班收入 | D14: 彭志坚 | E14: 18279285021 | F14: 游泳培训1V3 | H14: 全款 | I14: 微信 | J14: 980 | N14: 王海乐 | O14: 游泳培训1对3 | P14: 9310736 | Q14: 否 | R14: 是 | S14: 是
A15: 46206 | B15: 2855840 | C15: 教练班收入 | D15: 余静思/余静文/余静贤 | E15: 18970032303 | F15: 游泳培训1V3 | H15: 全款 | I15: 微信 | J15: 2700 | N15: 肖翠 | O15: 游泳培训1对3*3，各赠送一个月 | P15: 9310738 | Q15: 否 | R15: 是 | S15: 是
A16: 46206 | B16: 3232938 | C16: 会籍收入 | D16: 刘一显 | E16: 17746666110 | F16: 月卡 | H16: 全款 | I16: 微信 | J16: 500 | N16: 肖翠 | O16: 双月卡 | P16: 9131475 | Q16: 否 | R16: 是 | S16: 是
A17: 46206 | C17: 水吧收入 | J17: 87 | O17: 水*24/纸*2/外星人*2/脉动*2/维他命*1/红牛*1
A18: 46206 | C18: 美团收入 | J18: 19.9 | O18: 19.9*1
A19: 46206 | C19: 抖音收入 | J19: 19.9 | O19: 19.9*1
A20: 46207 | B20: 3232939 | C20: 会籍收入 | D20: 涂子睿 | E20: 15279143159 | F20: 月卡 | H20: 全款 | I20: 微信 | J20: 220 | N20: 凌培华 | O20: 月卡 | P20: 9131476 | Q20: 否 | R20: 是 | S20: 是
A21: 46207 | B21: 3232940 | C21: 教练班收入 | D21: 马允之 | E21: 18970935427 | F21: 游泳培训班 | H21: 全款 | I21: 微信 | J21: 758 | N21: 肖翠 | O21: 美团一对四泳培，送两个月月卡，固定下午之后 | P21: 9310737 | Q21: 否 | R21: 是 | S21: 是
A22: 46207 | B22: 3232141 | C22: 教练班收入 | D22: 廖兴惠 | E22: 13907009626 | F22: 游泳培训班 | H22: 全款 | I22: 微信 | J22: 780 | N22: 王海乐 | O22: 一对四，二期下午15:30-16:30上课（合同未签字） | P22: 9310739 | Q22: 否 | R22: 是 | S22: 是
A23: 46207 | B23: 3232142 | C23: 教练班收入 | D23: 熊隆盛 熊隆新 | E23: 15083814138 | F23: 游泳培训班 | H23: 全款 | I23: 微信 | J23: 1560 | N23: 刘嘉俊 | O23: 一对四*2.送月卡*2，早上9点以后上课 | P23: 9310740 | Q23: 否 | R23: 是 | S23: 是
A24: 46207 | B24: 3232144 | C24: 教练班收入 | D24: 陈子畅 | E24: 13803544386 | F24: 游泳培训1V2 | H24: 全款 | I24: 微信 | J24: 1280 | N24: 乔治 | O24: 一对二包教会 一期晚上6点上课，送一个月畅游 | P24: 9310742 | Q24: 否 | R24: 是 | S24: 是
A25: 46207 | B25: 3232145 | C25: 会籍收入 | D25: 裘友才 | E25: 18921077372 | F25: 年卡 | H25: 全款 | I25: 微信 | J25: 1000 | L25: 肖翠 | M25: 业绩达标奖励 | N25: 王海乐 | O25: 年卡赠送2个月，送健身三件套 | P25: 9131477 | Q25: 否 | R25: 是 | S25: 是
A26: 46207 | B26: 3232146 | C26: 教练班收入 | D26: 赖孜俊 李承羲 | E26: 18827769217 | F26: 游泳培训班 | H26: 全款 | I26: 微信 | J26: 1360 | N26: 王海乐 | O26: 一对六*2，二期7点-8点上课 | P26: 9310743 | Q26: 否 | R26: 是 | S26: 是
A27: 46207 | C27: 水吧收入 | J27: 48 | O27: 水*14/纸*2/外*1/脉*1/东方*1
A28: 46207 | C28: 游泳装备 | J28: 35 | O28: 布泳帽*3/鼻夹*1
A29: 46207 | C29: 抖音收入 | J29: 190 | O29: 95*2
A30: 46207 | B30: 3232147 | C30: 会籍收入 | D30: 邓奕浩/刘榕 | E30: 13369782190 19579883176 | F30: 月卡 | H30: 全款 | I30: 微信 | J30: 500 | N30: 刘嘉俊 | O30: 月卡*2（合同未签字） | P30: 9131480 | Q30: 否 | R30: 是 | S30: 是
A31: 46208 | B31: 3232148 | C31: 会籍收入 | D31: 杨令雨 | E31: 15397802300 | F31: 月卡 | H31: 全款 | I31: 微信 | J31: 299 | N31: 肖翠 | O31: 月卡 | P31: 9131479 | Q31: 否 | R31: 是 | S31: 是
A32: 46208 | B32: 3232149 | C32: 教练班收入 | D32: 徐成楠 | E32: 19979056750 | F32: 游泳培训1V3 | H32: 全款 | I32: 微信 | J32: 1280 | N32: 王海乐 | O32: 游泳培训1对3（合同未签字） | P32: 9310744 | Q32: 否 | R32: 是 | S32: 是
A33: 46208 | B33: 3232151 | C33: 教练班收入 | D33: 徐赫杨 | E33: 15279362987 | F33: 游泳培训1V3 | H33: 全款 | I33: 支付宝 | J33: 900 | N33: 肖翠 | O33: 游泳培训1对3（合并付款：2700元） | P33: 9310746 | Q33: 否 | R33: 是 | S33: 是
A34: 46208 | B34: 3232150 | C34: 教练班收入 | D34: 邬林俊/邬林志 | E34: 13694882406 | F34: 游泳培训1V3 | H34: 全款 | I34: 支付宝 | J34: 1800 | N34: 肖翠 | O34: 游泳培训1对3*2（合并付款：2700元） | P34: 9310745 | Q34: 否 | R34: 是 | S34: 是
A35: 46208 | B35: 2122961 | C35: 教练班收入 | D35: 何曦悦 | E35: 13627002502 | F35: 游泳培训班 | H35: 全款 | I35: 微信 | J35: 780 | N35: 肖翠 | O35: 游泳培训1对4送暑假畅游（19:00-20:00） | P35: 9310747 | Q35: 否 | R35: 是 | S35: 是
A36: 46208 | B36: 2122962 | C36: 会籍收入 | D36: 张皓轩 | E36: 18970870418 | F36: 月卡 | H36: 全款 | I36: 微信 | J36: 299 | N36: 肖翠 | O36: 月卡，送10天 | P36: 9131478 | Q36: 否 | R36: 是 | S36: 是
A37: 46208 | B37: 3232152 | C37: 会籍收入 | D37: 安芯 | E37: 13970955949 | F37: 月卡 | H37: 全款 | I37: 微信 | J37: 499 | N37: 肖翠 | O37: 双月卡，10号补差价升级年卡 | P37: 9131481 | Q37: 否 | R37: 是 | S37: 是
A38: 46208 | B38: 2122963 | C38: 会籍收入 | D38: 涂丹 | E38: 15007916111 | F38: 月卡 | H38: 全款 | I38: 微信 | J38: 300 | N38: 肖翠 | O38: 美团验券月卡300 | P38: 9131482 | Q38: 否 | R38: 是 | S38: 是
A39: 46208 | B39: 3232153 | C39: 会籍收入 | D39: 胡予沫 | E39: 13767024105 | F39: 月卡 | H39: 全款 | I39: 微信 | J39: 500 | N39: 肖翠 | O39: 双月卡 | P39: 9131483 | Q39: 否 | R39: 是 | S39: 是
A40: 46208 | B40: 2122964 | C40: 会籍收入 | D40: 李言蹊 | E40: 18826191662 | F40: 月卡 | H40: 全款 | I40: 微信 | J40: 420 | N40: 王海乐 | O40: 双月卡 | P40: 9131484 | Q40: 否 | R40: 是 | S40: 是
A41: 46208 | B41: 2122965 | C41: 教练班收入 | D41: 甘书瑶 | E41: 15179109737 | F41: 游泳培训班 | H41: 全款 | I41: 微信 | J41: 780 | N41: 王海乐 | O41: 游泳培训1对4，送一个月（8月中下旬，16:00以后） | P41: 9310748 | Q41: 否 | R41: 是 | S41: 是
A42: 46208 | B42: 3232154 | C42: 会籍收入 | D42: 徐晟恩 | E42: 18675572895 | F42: 月卡 | H42: 全款 | I42: 微信 | J42: 200 | N42: 肖翠 | O42: 月卡 | P42: 9131485 | Q42: 否 | R42: 是 | S42: 是
A43: 46208 | B43: 3232143 | C43: 教练班收入 | D43: 付锦灏 | E43: 13576038686 | F43: 游泳培训班 | H43: 全款 | I43: 微信 | J43: 780 | N43: 王总 | O43: 一对四，送一个月上课卡，下午四点上课（合同未签字） | P43: 93170741 | Q43: 否 | R43: 是 | S43: 是
A44: 46208 | C44: 水吧收入 | J44: 58 | O44: 水*20/脉动*1/外星人*1/维他命*1
A45: 46208 | C45: 游泳装备 | J45: 40 | O45: 布泳帽*4
A46: 46208 | C46: 美团收入 | J46: 139.5 | O46: 19.9*3/39.9*2
A47: 46208 | C47: 抖音收入 | J47: 95 | O47: 95*1
A48: 46209 | B48: 3232155 | C48: 教练班收入 | D48: 兰羽静 | E48: 13755665210 | F48: 游泳培训班 | H48: 全款 | I48: 微信 | J48: 688 | N48: 王海乐 | O48: 一对六，7:00-8:00上课（合同未签字） | P48: 9310749 | Q48: 否 | R48: 是 | S48: 是
A49: 46209 | B49: 3232156 | C49: 教练班收入 | D49: 龚剑风 | E49: 18170936757 | F49: 游泳培训班 | H49: 全款 | I49: 微信 | J49: 800 | N49: 张志明 | O49: 一对六泳培赠送畅游卡，泳镜*1 | P49: 9310750 | Q49: 否 | R49: 是 | S49: 是
A50: 46209 | B50: 3232159 | C50: 会籍收入 | D50: 涂嘉颖 | E50: 17370000768 | F50: 月卡 | H50: 全款 | I50: 微信 | J50: 292 | N50: 刘嘉俊 | O50: 美团月卡 | P50: 9131489 | Q50: 否 | R50: 是 | S50: 是
A51: 46209 | B51: 2122966 | C51: 会籍收入 | D51: 刘若天 | E51: 18170031717 | F51: 月卡 | H51: 全款 | I51: 微信 | J51: 300 | N51: 刘嘉俊 | O51: 美团月卡 | P51: 9131486 | Q51: 否 | R51: 是 | S51: 是
A52: 46209 | B52: 3232157 | C52: 会籍收入 | D52: 亚碧 | E52: 15307044695 | F52: 月卡 | H52: 全款 | I52: 微信 | J52: 299 | N52: 王海乐 | O52: 月卡 | P52: 9131487 | Q52: 否 | R52: 是 | S52: 是
A53: 46209 | B53: 2122967 | C53: 教练班收入 | D53: 黄博彦 黄博然 | E53: 15979187210 15270820328 | F53: 游泳培训班 | H53: 全款 | I53: 微信 | J53: 1560 | N53: 王总 | O53: 一对四泳培送暑假畅游卡*2，包教会一种泳姿（晚上7点-8点上课） | P53: 9310751 | Q53: 否 | R53: 是 | S53: 是
A54: 46209 | B54: 3232158 | C54: 会籍收入 | D54: 黄琳 | E54: 15079139079 | F54: 年卡 | H54: 全款 | I54: 微信 | J54: 1000 | N54: 肖翠 | O54: 年卡送三个月 | P54: 9131488 | Q54: 否 | R54: 是 | S54: 是
A55: 46209 | B55: 3232160 | C55: 会籍收入 | D55: 陶文轩 | E55: 15279112372 | F55: 月卡 | H55: 全款 | I55: 微信 | J55: 299 | N55: 刘嘉俊 | O55: 月卡 | P55: 9131490 | Q55: 否 | R55: 是 | S55: 是
A56: 46209 | B56: 2122968 | C56: 教练班收入 | D56: 熊浩然 熊浩锦 | E56: 18979113596 | F56: 长训班 | H56: 全款 | I56: 微信 | J56: 1800 | N56: 王海乐 | O56: 长训班16节*2，送两个月畅游卡*2，用于上课 | P56: 9310752 | Q56: 否 | R56: 是 | S56: 是
A57: 46209 | C57: 水吧收入 | J57: 76 | O57: 水*28/纸*2/外*1/溶*1/脉*1
A58: 46209 | C58: 游泳装备 | J58: 50 | O58: 泳帽*1/泳镜*2
A59: 46209 | C59: 美团收入 | J59: 74.6 | O59: 19.9*3/14.9*1
A60: 46209 | C60: 抖音收入 | J60: 19.9 | O60: 19.9*1
A61: 46210 | B61: 2022961 | C61: 会籍收入 | D61: 公顺 | E61: 13576048274 | F61: 年卡 | H61: 全款 | I61: 微信 | J61: 1000 | N61: 肖翠 | O61: 年卡送健身三件套*1 | P61: 9131491 | Q61: 否 | R61: 是 | S61: 是
A62: 46210 | B62: 2022962 | C62: 教练班收入 | D62: 欧阳陈骏 | E62: 13732989511 | F62: 游泳培训班 | H62: 全款 | I62: 微信 | J62: 800 | N62: 肖翠 | O62: 游泳培训1对4，送2个月暑假，下午时间都可以 | P62: 9310753 | Q62: 否 | R62: 是 | S62: 是
A63: 46210 | B63: 2022963 | C63: 教练班收入 | D63: 晏飘飘 | E63: 17779182659 | F63: 游泳培训班 | H63: 全款 | I63: 微信 | J63: 800 | N63: 刘嘉俊 | O63: 游泳培训1对4 | P63: 9310754 | Q63: 否 | R63: 是 | S63: 是
A64: 46210 | B64: 2022964 | O64: 收据合同作废 | P64: 9310755
A65: 46210 | B65: 2022965 | C65: 会籍收入 | D65: 黄宇晨 | E65: 15870786674 | F65: 月卡 | H65: 全款 | I65: 微信 | J65: 238 | N65: 刘嘉俊 | O65: 月卡 | P65: 9131492 | Q65: 否 | R65: 是 | S65: 是
A66: 46210 | B66: 2022965 | C66: 会籍收入 | D66: 黄以歆 | E66: 15870786674 | F66: 月卡 | H66: 全款 | I66: 微信 | J66: 300 | N66: 刘嘉俊 | O66: 美团验券月卡300 | P66: 9131492 | Q66: 否 | R66: 是 | S66: 是
A67: 46210 | B67: 2022967 | C67: 会籍收入 | D67: 夏颖 | E67: 18942321713 | F67: 年卡 | H67: 全款 | I67: 支付宝 | J67: 800 | N67: 王海乐 | O67: 月卡升级年卡
A68: 46210 | B68: 2022966 | C68: 会籍收入 | D68: 姚赣 | E68: 13307911910 | F68: 双年卡 | H68: 全款 | I68: 微信 | J68: 1314 | N68: 王海乐 | O68: 双年卡，赠3个月，赠健身包*1 | P68: 9131494 | Q68: 否 | R68: 是 | S68: 是
A69: 46210 | C69: 水吧收入 | J69: 58 | O69: 水*23/水溶*1/外星人*1
A70: 46210 | C70: 游泳装备 | J70: 45 | O70: 布泳帽*2/硅胶泳帽*1
A71: 46210 | C71: 美团收入 | J71: 16.9 | O71: 16.9*1
A72: 46210 | C72: 抖音收入 | J72: 249.7 | O72: 19.9*3/95*2
A73: 46211 | B73: 2022968 | C73: 教练班收入 | D73: 刘乐乐 | E73: 15270016720 | F73: 游泳培训班 | H73: 全款 | I73: 微信 | J73: 150 | O73: 金沙小学4（1）班
A74: 46211 | B74: 2022969 | C74: 教练班收入 | D74: 汪小雨 | E74: 15079102938 | F74: 游泳培训班 | H74: 全款 | I74: 微信 | J74: 150 | O74: 金沙小学4（1）班
A75: 46211 | B75: 2022970 | C75: 教练班收入 | D75: 欧阳子墨 | E75: 13036213610 | F75: 游泳培训班 | H75: 全款 | I75: 微信 | J75: 150 | O75: 金沙小学4（1）班
A76: 46211 | B76: 2022971 | C76: 教练班收入 | D76: 熊歆玥 | E76: 13870618712 | F76: 游泳培训班 | H76: 全款 | I76: 微信 | J76: 150 | O76: 金沙小学4（1）班
A77: 46211 | B77: 2022972 | C77: 教练班收入 | D77: 胡思妍 | E77: 15079043845 | F77: 游泳培训班 | H77: 全款 | I77: 微信 | J77: 150 | O77: 金沙小学4（1）班
A78: 46211 | B78: 3332881 | C78: 教练班收入 | D78: 李屹然 | E78: 18000206627 | F78: 游泳培训班 | H78: 全款 | I78: 微信 | J78: 150 | O78: 金沙小学4（1）班
A79: 46211 | B79: 3332882 | C79: 教练班收入 | D79: 李晨希 | E79: 15979016520 | F79: 游泳培训班 | H79: 全款 | I79: 微信 | J79: 150 | O79: 金沙小学4（1）班
A80: 46211 | B80: 2022973 | C80: 教练班收入 | D80: 梅亦辰 | E80: 18162202838 | F80: 游泳培训班 | H80: 全款 | I80: 微信 | J80: 150 | O80: 金沙小学4（1）班
A81: 46211 | B81: 2022974 | C81: 教练班收入 | D81: 万智轩 | E81: 15899921591 | F81: 游泳培训班 | H81: 全款 | I81: 微信 | J81: 150 | O81: 金沙小学4（1）班
A82: 46211 | B82: 2022975 | C82: 教练班收入 | D82: 余馨蕊 | E82: 13732927045 | F82: 游泳培训班 | H82: 全款 | I82: 微信 | J82: 150 | O82: 金沙小学4（1）班
A83: 46211 | B83: 2022976 | C83: 教练班收入 | D83: 张曦月 | E83: 18870048320 | F83: 游泳培训班 | H83: 全款 | I83: 微信 | J83: 150 | O83: 金沙小学4（1）班
A84: 46211 | B84: 3332883 | C84: 教练班收入 | D84: 吴星瑞 | E84: 17807039939 | F84: 游泳培训班 | H84: 全款 | I84: 微信 | J84: 150 | O84: 金沙小学4（1）班
... A120: 46211 | B120: 3332147 | C120: 教练班收入 | D120: 曾小萱 | E120: 15070032639 | F120: 游泳培训班 | H120: 全款 | I120: 微信 | J120: 150 | O120: 金沙小学3（6）班
A121: 46211 | B121: 2122975 | C121: 会籍收入 | D121: 邓懿玲 | E121: 17370061170 | F121: 年卡 | H121: 全款 | I121: 微信 | J121: 688 | N121: 刘嘉俊 | O121: 儿童年卡，合并付款：1488元 | P121: 9131493 | Q121: 否 | R121: 是 | S121: 是
A122: 46211 | B122: 2122975 | C122: 会籍收入 | D122: 邓懿轩 | E122: 17370061170 | F122: 年卡 | H122: 全款 | I122: 微信 | J122: 800 | N122: 刘嘉俊 | O122: 儿童年卡 合并付款：1488元 | P122: 9131495 | Q122: 否 | R122: 是 | S122: 是
A123: 46211 | B123: 2122976 | C123: 教练班收入 | D123: 邹昕妍 | E123: 13687085699 | F123: 游泳培训班 | H123: 全款 | I123: 微信 | J123: 150 | O123: 金沙小学4（2）班（已退费）
A124: 46211 | B124: 2122977 | C124: 会籍收入 | D124: 熊峻程 | E124: 15879147271 | F124: 年卡 | H124: 全款 | I124: 微信 | J124: 1000 | N124: 肖翠 | O124: 年卡 | P124: 9131499 | Q124: 否 | R124: 是 | S124: 是
A125: 46211 | B125: 2122978 | C125: 会籍收入 | D125: 黄卫群 | E125: 13687092717 | F125: 亲子卡 | H125: 全款 | I125: 微信 | J125: 1280 | N125: 章歆阳 | O125: 亲子年卡 | P125: 9131498 | Q125: 否 | R125: 是 | S125: 是
A126: 46211 | B126: 3332148 | C126: 会籍收入 | D126: 王菲宇 | E126: 18121376932 | F126: 月卡 | H126: 全款 | I126: 微信 | J126: 300 | N126: 张志明 | O126: 双月卡 | P126: 9131500 | Q126: 否 | R126: 是 | S126: 是
A127: 46211 | B127: 2122980 | C127: 会籍收入 | D127: 李漪凡 | E127: 13755797156 | F127: 月卡 | H127: 全款 | I127: 微信 | J127: 200 | N127: 肖翠 | O127: 月卡 | P127: 9131497 | Q127: 否 | R127: 是 | S127: 是
A128: 46211 | B128: 2122979 | C128: 会籍收入 | D128: 漆平安 漆喜乐 | E128: 18170098181 | F128: 月卡 | H128: 全款 | I128: 微信 | J128: 400 | N128: 肖翠 | O128: 月卡*2 | P128: 9131496 | Q128: 否 | R128: 是 | S128: 是
A129: 46211 | B129: 3332904 | C129: 会籍收入 | D129: 熊 | E129: 15079070357 | F129: 月卡 | H129: 全款 | I129: 微信 | J129: 400 | N129: 王海乐 | O129: 双月卡（因付错了款，已申请退款1000） | P129: 9131441 | Q129: 否 | R129: 是 | S129: 是
A130: 46211 | B130: 3332150 | C130: 教练班收入 | D130: 魏辰宇 | E130: 18679126168 | F130: 游泳培训班 | H130: 全款 | I130: 微信 | J130: 150 | O130: 金沙小学4（1）班
A131: 46211 | B131: 3332151 | C131: 会籍收入 | D131: 陈汐越 | E131: 13027239037 | F131: 月卡 | H131: 全款 | I131: 微信 | J131: 450 | N131: 刘嘉俊 | O131: 双月卡（合同未签字） | P131: 9131442 | Q131: 否 | R131: 是 | S131: 是
A132: 46211 | B132: 3332152 | C132: 会籍收入 | D132: 刘宸希 | E132: 13823760559 | F132: 游泳培训1V1 | H132: 全款 | I132: 微信 | J132: 1800 | L132: 乔治 | M132: 业绩达标奖励 | N132: 王海乐 | O132: 游泳培训1对1，送一个月上课卡 | P132: 9310756 | Q132: 否 | R132: 是 | S132: 是
A133: 46211 | C133: 水吧收入 | J133: 85 | O133: 水*21/纸*1/外*1/溶*1/脉*2/尖*1/东方树叶*2
A134: 46211 | C134: 游泳装备 | J134: 140 | O134: 泳镜*3/布泳帽*3/男小童裤*2
A135: 46211 | C135: 抖音收入 | J135: 19.9 | O135: 19.9*1
...

Sheet 水吧销售明细表
A1: 水吧销售明细表
A2: 日期 | B2: 农夫山泉 | D2: 纸 | F2: 外星人 | H2: 水溶 | J2: 维他命 | L2: 脉动 | N2: 尖叫 | P2: 红牛 | R2: 东方树叶 | T2: 收入 | U2: 成本 | V2: 利润 | W2: 备注
B3: 进价 | C3: 售价 | D3: 进价 | E3: 售价 | F3: 进价 | G3: 售价 | H3: 进价 | I3: 售价 | J3: 进价 | K3: 售价 | L3: 进价 | M3: 售价 | N3: 进价 | O3: 售价 | P3: 进价 | Q3: 售价 | R3: 进价 | S3: 售价
B4: 0.95 | C4: 2 | D4: 0.513 | E4: 1 | F4: 4 | G4: 6 | H4: 3.73 | I4: 6 | J4: 3.6 | K4: 6 | L4: 3.6 | M4: 6 | N4: 3.6 | O4: 6 | P4: 4.5 | Q4: 7 | R4: 3.6 | S4: 6
A5: 实际库存量 | T5: =$C$4*B5+$E$4*D5+$G$4*F5+$I$4*H5+$K$4*J5+$M$4*L5+$O$4*N5+$Q$4*P5+$S$4*R5 -> 0 | U5: =$B$4*B5+$D$4*D5+$F$4*F5+$H$4*H5+$J$4*J5+$L$4*L5+$N$4*N5+$P$4*P5+$R$4*R5 -> 0 | V5: =T5-U5 -> 0
A6: 46204 | B6: 10 | D6: 1 | F6: 1 | H6: 1 | J6: 2 | L6: 0 | N6: 0 | P6: 0 | R6: 1 | T6: =$C$4*B6+$E$4*D6+$G$4*F6+$I$4*H6+$K$4*J6+$M$4*L6+$O$4*N6+$Q$4*P6+$S$4*R6 -> 51 | U6: =$B$4*B6+$D$4*D6+$F$4*F6+$H$4*H6+$J$4*J6+$L$4*L6+$N$4*N6+$P$4*P6+$R$4*R6 -> 28.543 | V6: =T6-U6 -> 22.457
A7: 46205 | B7: 24 | D7: 1 | F7: 0 | H7: 0 | J7: 1 | L7: 1 | N7: 0 | P7: 0 | R7: 0 | T7: =$C$4*B7+$E$4*D7+$G$4*F7+$I$4*H7+$K$4*J7+$M$4*L7+$O$4*N7+$Q$4*P7+$S$4*R7 -> 61 | U7: =$B$4*B7+$D$4*D7+$F$4*F7+$H$4*H7+$J$4*J7+$L$4*L7+$N$4*N7+$P$4*P7+$R$4*R7 -> 30.513 | V7: =T7-U7 -> 30.487
A8: 46206 | B8: 24 | D8: 2 | F8: 2 | H8: 0 | J8: 1 | L8: 2 | N8: 0 | P8: 1 | R8: 0 | T8: =$C$4*B8+$E$4*D8+$G$4*F8+$I$4*H8+$K$4*J8+$M$4*L8+$O$4*N8+$Q$4*P8+$S$4*R8 -> 87 | U8: =$B$4*B8+$D$4*D8+$F$4*F8+$H$4*H8+$J$4*J8+$L$4*L8+$N$4*N8+$P$4*P8+$R$4*R8 -> 47.126 | V8: =T8-U8 -> 39.874
A9: 46207 | B9: 14 | D9: 2 | F9: 1 | H9: 0 | J9: 0 | L9: 1 | N9: 0 | P9: 0 | R9: 1 | T9: =$C$4*B9+$E$4*D9+$G$4*F9+$I$4*H9+$K$4*J9+$M$4*L9+$O$4*N9+$Q$4*P9+$S$4*R9 -> 48 | U9: =$B$4*B9+$D$4*D9+$F$4*F9+$H$4*H9+$J$4*J9+$L$4*L9+$N$4*N9+$P$4*P9+$R$4*R9 -> 25.526 | V9: =T9-U9 -> 22.474
A10: 46208 | B10: 20 | D10: 0 | F10: 1 | H10: 0 | J10: 1 | L10: 1 | N10: 0 | P10: 0 | R10: 0 | T10: =$C$4*B10+$E$4*D10+$G$4*F10+$I$4*H10+$K$4*J10+$M$4*L10+$O$4*N10+$Q$4*P10+$S$4*R10 -> 58 | U10: =$B$4*B10+$D$4*D10+$F$4*F10+$H$4*H10+$J$4*J10+$L$4*L10+$N$4*N10+$P$4*P10+$R$4*R10 -> 30.2 | V10: =T10-U10 -> 27.8
A11: 46209 | B11: 27 | D11: 2 | F11: 1 | H11: 1 | J11: 0 | L11: 1 | N11: 0 | P11: 0 | R11: 0 | T11: =$C$4*B11+$E$4*D11+$G$4*F11+$I$4*H11+$K$4*J11+$M$4*L11+$O$4*N11+$Q$4*P11+$S$4*R11 -> 74 | U11: =$B$4*B11+$D$4*D11+$F$4*F11+$H$4*H11+$J$4*J11+$L$4*L11+$N$4*N11+$P$4*P11+$R$4*R11 -> 38.006 | V11: =T11-U11 -> 35.994
A12: 46210 | B12: 23 | D12: 0 | F12: 1 | H12: 1 | J12: 0 | L12: 0 | N12: 0 | P12: 0 | R12: 0 | T12: =$C$4*B12+$E$4*D12+$G$4*F12+$I$4*H12+$K$4*J12+$M$4*L12+$O$4*N12+$Q$4*P12+$S$4*R12 -> 58 | U12: =$B$4*B12+$D$4*D12+$F$4*F12+$H$4*H12+$J$4*J12+$L$4*L12+$N$4*N12+$P$4*P12+$R$4*R12 -> 29.58 | V12: =T12-U12 -> 28.42
A13: 46211 | B13: 21 | D13: 1 | F13: 1 | H13: 1 | J13: 0 | L13: 2 | N13: 1 | P13: 0 | R13: 2 | T13: =$C$4*B13+$E$4*D13+$G$4*F13+$I$4*H13+$K$4*J13+$M$4*L13+$O$4*N13+$Q$4*P13+$S$4*R13 -> 85 | U13: =$B$4*B13+$D$4*D13+$F$4*F13+$H$4*H13+$J$4*J13+$L$4*L13+$N$4*N13+$P$4*P13+$R$4*R13 -> 46.193 | V13: =T13-U13 -> 38.807
A14: 46212 | B14: 14 | D14: 3 | F14: 0 | H14: 0 | J14: 0 | L14: 0 | N14: 1 | P14: 0 | R14: 1 | T14: =$C$4*B14+$E$4*D14+$G$4*F14+$I$4*H14+$K$4*J14+$M$4*L14+$O$4*N14+$Q$4*P14+$S$4*R14 -> 43 | U14: =$B$4*B14+$D$4*D14+$F$4*F14+$H$4*H14+$J$4*J14+$L$4*L14+$N$4*N14+$P$4*P14+$R$4*R14 -> 22.039 | V14: =T14-U14 -> 20.961
A15: 46213 | B15: 12 | D15: 0 | F15: 2 | H15: 1 | J15: 1 | L15: 0 | N15: 1 | P15: 1 | R15: 0 | T15: =$C$4*B15+$E$4*D15+$G$4*F15+$I$4*H15+$K$4*J15+$M$4*L15+$O$4*N15+$Q$4*P15+$S$4*R15 -> 61 | U15: =$B$4*B15+$D$4*D15+$F$4*F15+$H$4*H15+$J$4*J15+$L$4*L15+$N$4*N15+$P$4*P15+$R$4*R15 -> 34.83 | V15: =T15-U15 -> 26.17
A16: 46214 | B16: 22 | D16: 5 | F16: 1 | H16: 0 | J16: 0 | L16: 1 | N16: 0 | P16: 0 | R16: 0 | T16: =$C$4*B16+$E$4*D16+$G$4*F16+$I$4*H16+$K$4*J16+$M$4*L16+$O$4*N16+$Q$4*P16+$S$4*R16 -> 61 | U16: =$B$4*B16+$D$4*D16+$F$4*F16+$H$4*H16+$J$4*J16+$L$4*L16+$N$4*N16+$P$4*P16+$R$4*R16 -> 31.065 | V16: =T16-U16 -> 29.935
A17: 46215 | B17: 5 | D17: 1 | F17: 1 | H17: 0 | J17: 0 | L17: 0 | N17: 0 | P17: 0 | R17: 0 | T17: =$C$4*B17+$E$4*D17+$G$4*F17+$I$4*H17+$K$4*J17+$M$4*L17+$O$4*N17+$Q$4*P17+$S$4*R17 -> 17 | U17: =$B$4*B17+$D$4*D17+$F$4*F17+$H$4*H17+$J$4*J17+$L$4*L17+$N$4*N17+$P$4*P17+$R$4*R17 -> 9.263 | V17: =T17-U17 -> 7.737
A18: 46216 | T18: =$C$4*B18+$E$4*D18+$G$4*F18+$I$4*H18+$K$4*J18+$M$4*L18+$O$4*N18+$Q$4*P18+$S$4*R18 -> 0 | U18: =$B$4*B18+$D$4*D18+$F$4*F18+$H$4*H18+$J$4*J18+$L$4*L18+$N$4*N18+$P$4*P18+$R$4*R18 -> 0 | V18: =T18-U18 -> 0
A19: 46217 | T19: =$C$4*B19+$E$4*D19+$G$4*F19+$I$4*H19+$K$4*J19+$M$4*L19+$O$4*N19+$Q$4*P19+$S$4*R19 -> 0 | U19: =$B$4*B19+$D$4*D19+$F$4*F19+$H$4*H19+$J$4*J19+$L$4*L19+$N$4*N19+$P$4*P19+$R$4*R19 -> 0 | V19: =T19-U19 -> 0
A20: 46218 | T20: =$C$4*B20+$E$4*D20+$G$4*F20+$I$4*H20+$K$4*J20+$M$4*L20+$O$4*N20+$Q$4*P20+$S$4*R20 -> 0 | U20: =$B$4*B20+$D$4*D20+$F$4*F20+$H$4*H20+$J$4*J20+$L$4*L20+$N$4*N20+$P$4*P20+$R$4*R20 -> 0 | V20: =T20-U20 -> 0
A21: 46219 | T21: =$C$4*B21+$E$4*D21+$G$4*F21+$I$4*H21+$K$4*J21+$M$4*L21+$O$4*N21+$Q$4*P21+$S$4*R21 -> 0 | U21: =$B$4*B21+$D$4*D21+$F$4*F21+$H$4*H21+$J$4*J21+$L$4*L21+$N$4*N21+$P$4*P21+$R$4*R21 -> 0 | V21: =T21-U21 -> 0
A22: 46220 | T22: =$C$4*B22+$E$4*D22+$G$4*F22+$I$4*H22+$K$4*J22+$M$4*L22+$O$4*N22+$Q$4*P22+$S$4*R22 -> 0 | U22: =$B$4*B22+$D$4*D22+$F$4*F22+$H$4*H22+$J$4*J22+$L$4*L22+$N$4*N22+$P$4*P22+$R$4*R22 -> 0 | V22: =T22-U22 -> 0
A23: 46221 | T23: =$C$4*B23+$E$4*D23+$G$4*F23+$I$4*H23+$K$4*J23+$M$4*L23+$O$4*N23+$Q$4*P23+$S$4*R23 -> 0 | U23: =$B$4*B23+$D$4*D23+$F$4*F23+$H$4*H23+$J$4*J23+$L$4*L23+$N$4*N23+$P$4*P23+$R$4*R23 -> 0 | V23: =T23-U23 -> 0
A24: 46222 | T24: =$C$4*B24+$E$4*D24+$G$4*F24+$I$4*H24+$K$4*J24+$M$4*L24+$O$4*N24+$Q$4*P24+$S$4*R24 -> 0 | U24: =$B$4*B24+$D$4*D24+$F$4*F24+$H$4*H24+$J$4*J24+$L$4*L24+$N$4*N24+$P$4*P24+$R$4*R24 -> 0 | V24: =T24-U24 -> 0
A25: 46223 | T25: =$C$4*B25+$E$4*D25+$G$4*F25+$I$4*H25+$K$4*J25+$M$4*L25+$O$4*N25+$Q$4*P25+$S$4*R25 -> 0 | U25: =$B$4*B25+$D$4*D25+$F$4*F25+$H$4*H25+$J$4*J25+$L$4*L25+$N$4*N25+$P$4*P25+$R$4*R25 -> 0 | V25: =T25-U25 -> 0
A26: 46224 | T26: =$C$4*B26+$E$4*D26+$G$4*F26+$I$4*H26+$K$4*J26+$M$4*L26+$O$4*N26+$Q$4*P26+$S$4*R26 -> 0 | U26: =$B$4*B26+$D$4*D26+$F$4*F26+$H$4*H26+$J$4*J26+$L$4*L26+$N$4*N26+$P$4*P26+$R$4*R26 -> 0 | V26: =T26-U26 -> 0
A27: 46225 | T27: =$C$4*B27+$E$4*D27+$G$4*F27+$I$4*H27+$K$4*J27+$M$4*L27+$O$4*N27+$Q$4*P27+$S$4*R27 -> 0 | U27: =$B$4*B27+$D$4*D27+$F$4*F27+$H$4*H27+$J$4*J27+$L$4*L27+$N$4*N27+$P$4*P27+$R$4*R27 -> 0 | V27: =T27-U27 -> 0
A28: 46226 | T28: =$C$4*B28+$E$4*D28+$G$4*F28+$I$4*H28+$K$4*J28+$M$4*L28+$O$4*N28+$Q$4*P28+$S$4*R28 -> 0 | U28: =$B$4*B28+$D$4*D28+$F$4*F28+$H$4*H28+$J$4*J28+$L$4*L28+$N$4*N28+$P$4*P28+$R$4*R28 -> 0 | V28: =T28-U28 -> 0
A29: 46227 | T29: =$C$4*B29+$E$4*D29+$G$4*F29+$I$4*H29+$K$4*J29+$M$4*L29+$O$4*N29+$Q$4*P29+$S$4*R29 -> 0 | U29: =$B$4*B29+$D$4*D29+$F$4*F29+$H$4*H29+$J$4*J29+$L$4*L29+$N$4*N29+$P$4*P29+$R$4*R29 -> 0 | V29: =T29-U29 -> 0
... A36: 46234 | T36: =$C$4*B36+$E$4*D36+$G$4*F36+$I$4*H36+$K$4*J36+$M$4*L36+$O$4*N36+$Q$4*P36+$S$4*R36 -> 0 | U36: =$B$4*B36+$D$4*D36+$F$4*F36+$H$4*H36+$J$4*J36+$L$4*L36+$N$4*N36+$P$4*P36+$R$4*R36 -> 0 | V36: =T36-U36 -> 0
A37: 6月合计 | B37: =SUM(B6:C36) -> 216 | D37: =SUM(D6:E36) -> 18 | F37: =SUM(F6:G36) -> 12 | H37: =SUM(H6:I36) -> 5 | J37: =SUM(J6:K36) -> 6 | L37: =SUM(L6:M36) -> 9 | N37: =SUM(N6:O36) -> 3 | P37: =SUM(P6:Q36) -> 2 | R37: =SUM(R6:S36) -> 5 | T37: =SUM(T6:T36) -> 704 | U37: =SUM(U6:U36) -> 372.884 | V37: =SUM(V6:V36) -> 331.116
A38: 6月进货 | T38: =$C$4*B38+$E$4*D38+$G$4*F38+$I$4*H38+$K$4*J38+$M$4*L38+$O$4*N38+$Q$4*P38 -> 0 | U38: =$B$4*B38+$D$4*D38+$F$4*F38+$H$4*H38+$J$4*J38+$L$4*L38+$N$4*N38+$P$4*P38 -> 0 | V38: =T38-U38 -> 0
A39: 应有库存量 | B39: =B5-B37+B38 -> -216 | D39: =D5-D37+D38 -> -18 | F39: =F5-F37+F38 -> -12 | H39: =H5-H37+H38 -> -5 | J39: =J5-J37+J38 -> -6 | L39: =L5-L37+L38 -> -9 | N39: =N5-N37+N38 -> -3 | P39: =P5-P37+P38 -> -2 | R39: =R5-R37+R38 -> -5 | T39: =$C$4*B39+$E$4*D39+$G$4*F39+$I$4*H39+$K$4*J39+$M$4*L39+$O$4*N39+$Q$4*P39+$S$4*R39 -> -704 | U39: =$B$4*B39+$D$4*D39+$F$4*F39+$H$4*H39+$J$4*J39+$L$4*L39+$N$4*N39+$P$4*P39+$R$4*R39 -> -372.884 | V39: =T39-U39 -> -331.116
A40: 实际库存量 | T40: =$C$4*B40+$E$4*D40+$G$4*F40+$I$4*H40+$K$4*J40+$M$4*L40+$O$4*N40+$Q$4*P40 -> 0 | U40: =$B$4*B40+$D$4*D40+$F$4*F40+$H$4*H40+$J$4*J40+$L$4*L40+$N$4*N40+$P$4*P40 -> 0 | V40: =T40-U40 -> 0

Sheet 游泳装备销售明细表
A1: 游泳装备销售明细表
A2: 日期 | B2: 泳镜 | D2: 硅胶泳帽 | F2: 布泳帽 | H2: 成人泳裤 | J2: 中童泳裤 | L2: 小童泳裤 | N2: 小童泳衣 | P2: 中童泳衣 | R2: 大童泳衣 | T2: 鼻夹 | V2: 收入 | W2: 成本 | X2: 利润 | Y2: 备注
B3: 进价 | C3: 售价 | D3: 进价 | E3: 售价 | F3: 进价 | G3: 售价 | H3: 进价 | I3: 售价 | J3: 进价 | K3: 售价 | L3: 进价 | M3: 售价 | N3: 进价 | O3: 售价 | P3: 进价 | Q3: 售价 | R3: 进价 | S3: 售价 | T3: 进价 | U3: 售价
B4: 6.5 | C4: 20 | D4: 5 | E4: 25 | F4: 1.2 | G4: 10 | H4: 5 | I4: 30 | J4: 5 | K4: 25 | L4: 5 | M4: 25 | N4: 18 | O4: 35 | P4: 28 | Q4: 35 | R4: 22 | S4: 40 | T4: 1.5 | U4: 5
A5: 实际库存量 | V5: =$C$4*B5+$E$4*D5+$G$4*F5+$I$4*H5+$K$4*J5+$M$4*L5+$O$4*N5+$U$4*T5 -> 0 | W5: =$B$4*B5+$D$4*D5+$F$4*F5+$H$4*H5+$J$4*J5+$L$4*L5+$N$4*N5+$T$4*T5 -> 0 | X5: =V5-W5 -> 0
A6: 46204 | B6: 0 | D6: 0 | F6: 0 | H6: 0 | J6: 0 | L6: 0 | N6: 0 | P6: 0 | R6: 0 | T6: 0 | V6: =$C$4*B6+$E$4*D6+$G$4*F6+$I$4*H6+$K$4*J6+$M$4*L6+$O$4*N6+$U$4*T6 -> 0 | W6: =$B$4*B6+$D$4*D6+$F$4*F6+$H$4*H6+$J$4*J6+$L$4*L6+$N$4*N6+$T$4*T6 -> 0 | X6: =V6-W6 -> 0
A7: 46205 | B7: 0 | D7: 0 | F7: 0 | H7: 0 | J7: 0 | L7: 0 | N7: 0 | P7: 0 | R7: 0 | T7: 0 | V7: =$C$4*B7+$E$4*D7+$G$4*F7+$I$4*H7+$K$4*J7+$M$4*L7+$O$4*N7+$U$4*T7 -> 0 | W7: =$B$4*B7+$D$4*D7+$F$4*F7+$H$4*H7+$J$4*J7+$L$4*L7+$N$4*N7+$T$4*T7 -> 0 | X7: =V7-W7 -> 0
A8: 46206 | B8: 0 | D8: 0 | F8: 0 | H8: 0 | J8: 0 | L8: 0 | N8: 0 | P8: 0 | R8: 0 | T8: 0 | V8: =$C$4*B8+$E$4*D8+$G$4*F8+$I$4*H8+$K$4*J8+$M$4*L8+$O$4*N8+$U$4*T8 -> 0 | W8: =$B$4*B8+$D$4*D8+$F$4*F8+$H$4*H8+$J$4*J8+$L$4*L8+$N$4*N8+$T$4*T8 -> 0 | X8: =V8-W8 -> 0
A9: 46207 | B9: 0 | D9: 0 | F9: 3 | H9: 0 | J9: 0 | L9: 0 | N9: 0 | P9: 0 | R9: 0 | T9: 1 | V9: =$C$4*B9+$E$4*D9+$G$4*F9+$I$4*H9+$K$4*J9+$M$4*L9+$O$4*N9+$U$4*T9 -> 35 | W9: =$B$4*B9+$D$4*D9+$F$4*F9+$H$4*H9+$J$4*J9+$L$4*L9+$N$4*N9+$T$4*T9 -> 5.1 | X9: =V9-W9 -> 29.9
A10: 46208 | B10: 0 | D10: 0 | F10: 4 | H10: 0 | J10: 0 | L10: 0 | N10: 0 | P10: 0 | R10: 0 | T10: 0 | V10: =$C$4*B10+$E$4*D10+$G$4*F10+$I$4*H10+$K$4*J10+$M$4*L10+$O$4*N10+$U$4*T10 -> 40 | W10: =$B$4*B10+$D$4*D10+$F$4*F10+$H$4*H10+$J$4*J10+$L$4*L10+$N$4*N10+$T$4*T10 -> 4.8 | X10: =V10-W10 -> 35.2
A11: 46209 | B11: 2 | D11: 0 | F11: 1 | H11: 0 | J11: 0 | L11: 0 | N11: 0 | P11: 0 | R11: 0 | T11: 0 | V11: =$C$4*B11+$E$4*D11+$G$4*F11+$I$4*H11+$K$4*J11+$M$4*L11+$O$4*N11+$U$4*T11 -> 50 | W11: =$B$4*B11+$D$4*D11+$F$4*F11+$H$4*H11+$J$4*J11+$L$4*L11+$N$4*N11+$T$4*T11 -> 14.2 | X11: =V11-W11 -> 35.8
A12: 46210 | B12: 0 | D12: 1 | F12: 2 | H12: 0 | J12: 0 | L12: 0 | N12: 0 | P12: 0 | R12: 0 | T12: 0 | V12: =$C$4*B12+$E$4*D12+$G$4*F12+$I$4*H12+$K$4*J12+$M$4*L12+$O$4*N12+$U$4*T12 -> 45 | W12: =$B$4*B12+$D$4*D12+$F$4*F12+$H$4*H12+$J$4*J12+$L$4*L12+$N$4*N12+$T$4*T12 -> 7.4 | X12: =V12-W12 -> 37.6
A13: 46211 | B13: 3 | D13: 0 | F13: 3 | H13: 0 | J13: 0 | L13: 2 | N13: 0 | P13: 0 | R13: 0 | T13: 0 | V13: =$C$4*B13+$E$4*D13+$G$4*F13+$I$4*H13+$K$4*J13+$M$4*L13+$O$4*N13+$U$4*T13 -> 140 | W13: =$B$4*B13+$D$4*D13+$F$4*F13+$H$4*H13+$J$4*J13+$L$4*L13+$N$4*N13+$T$4*T13 -> 33.1 | X13: =V13-W13 -> 106.9
A14: 46212 | B14: 0 | D14: 3 | F14: 0 | H14: 1 | J14: 0 | L14: 0 | N14: 0 | P14: 0 | R14: 0 | T14: 0 | V14: =$C$4*B14+$E$4*D14+$G$4*F14+$I$4*H14+$K$4*J14+$M$4*L14+$O$4*N14+$U$4*T14 -> 105 | W14: =$B$4*B14+$D$4*D14+$F$4*F14+$H$4*H14+$J$4*J14+$L$4*L14+$N$4*N14+$T$4*T14 -> 20 | X14: =V14-W14 -> 85
A15: 46213 | B15: 0 | D15: 0 | F15: 0 | H15: 0 | J15: 0 | L15: 0 | N15: 0 | P15: 0 | R15: 0 | T15: 1 | V15: =$C$4*B15+$E$4*D15+$G$4*F15+$I$4*H15+$K$4*J15+$M$4*L15+$O$4*N15+$U$4*T15 -> 5 | W15: =$B$4*B15+$D$4*D15+$F$4*F15+$H$4*H15+$J$4*J15+$L$4*L15+$N$4*N15+$T$4*T15 -> 1.5 | X15: =V15-W15 -> 3.5
A16: 46214 | B16: 0 | D16: 0 | F16: 4 | H16: 0 | J16: 0 | L16: 0 | N16: 0 | P16: 0 | R16: 0 | T16: 1 | V16: =$C$4*B16+$E$4*D16+$G$4*F16+$I$4*H16+$K$4*J16+$M$4*L16+$O$4*N16+$U$4*T16 -> 45 | W16: =$B$4*B16+$D$4*D16+$F$4*F16+$H$4*H16+$J$4*J16+$L$4*L16+$N$4*N16+$T$4*T16 -> 6.3 | X16: =V16-W16 -> 38.7
A17: 46215 | B17: 0 | D17: 1 | F17: 1 | H17: 0 | J17: 0 | L17: 0 | N17: 0 | P17: 0 | R17: 0 | T17: 1 | V17: =$C$4*B17+$E$4*D17+$G$4*F17+$I$4*H17+$K$4*J17+$M$4*L17+$O$4*N17+$U$4*T17 -> 40 | W17: =$B$4*B17+$D$4*D17+$F$4*F17+$H$4*H17+$J$4*J17+$L$4*L17+$N$4*N17+$T$4*T17 -> 7.7 | X17: =V17-W17 -> 32.3
A18: 46216 | V18: =$C$4*B18+$E$4*D18+$G$4*F18+$I$4*H18+$K$4*J18+$M$4*L18+$O$4*N18+$U$4*T18 -> 0 | W18: =$B$4*B18+$D$4*D18+$F$4*F18+$H$4*H18+$J$4*J18+$L$4*L18+$N$4*N18+$T$4*T18 -> 0 | X18: =V18-W18 -> 0
A19: 46217 | V19: =$C$4*B19+$E$4*D19+$G$4*F19+$I$4*H19+$K$4*J19+$M$4*L19+$O$4*N19+$U$4*T19 -> 0 | W19: =$B$4*B19+$D$4*D19+$F$4*F19+$H$4*H19+$J$4*J19+$L$4*L19+$N$4*N19+$T$4*T19 -> 0 | X19: =V19-W19 -> 0
A20: 46218 | V20: =$C$4*B20+$E$4*D20+$G$4*F20+$I$4*H20+$K$4*J20+$M$4*L20+$O$4*N20+$U$4*T20 -> 0 | W20: =$B$4*B20+$D$4*D20+$F$4*F20+$H$4*H20+$J$4*J20+$L$4*L20+$N$4*N20+$T$4*T20 -> 0 | X20: =V20-W20 -> 0
A21: 46219 | V21: =$C$4*B21+$E$4*D21+$G$4*F21+$I$4*H21+$K$4*J21+$M$4*L21+$O$4*N21+$U$4*T21 -> 0 | W21: =$B$4*B21+$D$4*D21+$F$4*F21+$H$4*H21+$J$4*J21+$L$4*L21+$N$4*N21+$T$4*T21 -> 0 | X21: =V21-W21 -> 0
A22: 46220 | V22: =$C$4*B22+$E$4*D22+$G$4*F22+$I$4*H22+$K$4*J22+$M$4*L22+$O$4*N22+$U$4*T22 -> 0 | W22: =$B$4*B22+$D$4*D22+$F$4*F22+$H$4*H22+$J$4*J22+$L$4*L22+$N$4*N22+$T$4*T22 -> 0 | X22: =V22-W22 -> 0
A23: 46221 | V23: =$C$4*B23+$E$4*D23+$G$4*F23+$I$4*H23+$K$4*J23+$M$4*L23+$O$4*N23+$U$4*T23 -> 0 | W23: =$B$4*B23+$D$4*D23+$F$4*F23+$H$4*H23+$J$4*J23+$L$4*L23+$N$4*N23+$T$4*T23 -> 0 | X23: =V23-W23 -> 0
A24: 46222 | V24: =$C$4*B24+$E$4*D24+$G$4*F24+$I$4*H24+$K$4*J24+$M$4*L24+$O$4*N24+$U$4*T24 -> 0 | W24: =$B$4*B24+$D$4*D24+$F$4*F24+$H$4*H24+$J$4*J24+$L$4*L24+$N$4*N24+$T$4*T24 -> 0 | X24: =V24-W24 -> 0
A25: 46223 | V25: =$C$4*B25+$E$4*D25+$G$4*F25+$I$4*H25+$K$4*J25+$M$4*L25+$O$4*N25+$U$4*T25 -> 0 | W25: =$B$4*B25+$D$4*D25+$F$4*F25+$H$4*H25+$J$4*J25+$L$4*L25+$N$4*N25+$T$4*T25 -> 0 | X25: =V25-W25 -> 0
A26: 46224 | V26: =$C$4*B26+$E$4*D26+$G$4*F26+$I$4*H26+$K$4*J26+$M$4*L26+$O$4*N26+$U$4*T26 -> 0 | W26: =$B$4*B26+$D$4*D26+$F$4*F26+$H$4*H26+$J$4*J26+$L$4*L26+$N$4*N26+$T$4*T26 -> 0 | X26: =V26-W26 -> 0
A27: 46225 | V27: =$C$4*B27+$E$4*D27+$G$4*F27+$I$4*H27+$K$4*J27+$M$4*L27+$O$4*N27+$U$4*T27 -> 0 | W27: =$B$4*B27+$D$4*D27+$F$4*F27+$H$4*H27+$J$4*J27+$L$4*L27+$N$4*N27+$T$4*T27 -> 0 | X27: =V27-W27 -> 0
A28: 46226 | V28: =$C$4*B28+$E$4*D28+$G$4*F28+$I$4*H28+$K$4*J28+$M$4*L28+$O$4*N28+$U$4*T28 -> 0 | W28: =$B$4*B28+$D$4*D28+$F$4*F28+$H$4*H28+$J$4*J28+$L$4*L28+$N$4*N28+$T$4*T28 -> 0 | X28: =V28-W28 -> 0
A29: 46227 | V29: =$C$4*B29+$E$4*D29+$G$4*F29+$I$4*H29+$K$4*J29+$M$4*L29+$O$4*N29+$U$4*T29 -> 0 | W29: =$B$4*B29+$D$4*D29+$F$4*F29+$H$4*H29+$J$4*J29+$L$4*L29+$N$4*N29+$T$4*T29 -> 0 | X29: =V29-W29 -> 0
... A36: 46234 | V36: =$C$4*B36+$E$4*D36+$G$4*F36+$I$4*H36+$K$4*J36+$M$4*L36+$O$4*N36+$U$4*T36 -> 0 | W36: =$B$4*B36+$D$4*D36+$F$4*F36+$H$4*H36+$J$4*J36+$L$4*L36+$N$4*N36+$T$4*T36 -> 0 | X36: =V36-W36 -> 0
A37: 6月合计 | B37: =SUM(B6:C36) -> 5 | D37: 1 | F37: =SUM(F6:G36) -> 18 | H37: =SUM(H6:I36) -> 1 | J37: =SUM(J6:K36) -> 0 | L37: =SUM(L6:M36) -> 2 | N37: =SUM(N6:O36) -> 0 | T37: =SUM(T6:U36) -> 4 | V37: =SUM(V6:V36) -> 505 | W37: =SUM(W6:W36) -> 100.1 | X37: =SUM(X6:X36) -> 404.9
A38: 6月进货 | V38: =$C$4*B38+$E$4*D38+$G$4*F38+$I$4*H38+$K$4*J38+$M$4*L38+$O$4*N38+$U$4*T38 -> 0 | W38: =$B$4*B38+$D$4*D38+$F$4*F38+$H$4*H38+$J$4*J38+$L$4*L38+$N$4*N38+$T$4*T38 -> 0 | X38: =V38-W38 -> 0
A39: 应有库存量 | B39: =B5-B37+B38 -> -5 | D39: =D5-D37+D38 -> -1 | F39: =F5-F37+F38 -> -18 | H39: =H5-H37+H38 -> -1 | J39: =J5-J37+J38 -> 0 | L39: =L5-L37+L38 -> -2 | N39: =N5-N37+N38 -> 0 | T39: =T5-T37+T38 -> -4 | V39: =$C$4*B39+$E$4*D39+$G$4*F39+$I$4*H39+$K$4*J39+$M$4*L39+$O$4*N39+$U$4*T39 -> -405 | W39: =$B$4*B39+$D$4*D39+$F$4*F39+$H$4*H39+$J$4*J39+$L$4*L39+$N$4*N39+$T$4*T39 -> -80.1 | X39: =V39-W39 -> -324.9
A40: 实际库存量 | V40: =$C$4*B40+$E$4*D40+$G$4*F40+$I$4*H40+$K$4*J40+$M$4*L40+$O$4*N40+$U$4*T40 -> 0 | W40: =$B$4*B40+$D$4*D40+$F$4*F40+$H$4*H40+$J$4*J40+$L$4*L40+$N$4*N40+$T$4*T40 -> 0 | X40: =V40-W40 -> 0

Sheet 礼品赠送明细表
A1: 礼品赠送明细表
A2: 日期 | B2: 会员姓名 | C2: 会员电话 | D2: 办卡金额 | E2: 礼品 | F2: 数量
A3: 202+6/7/3 | B3: 余静思 | C3: 18970032303 | D3: 2700 | E3: 布泳帽*3/泳镜*3/中童泳衣*1/中童泳裤*2
A4: 46207 | B4: 温勤勤 | E4: 次卡*7/周卡*2/泳帽*2/泳镜*2
A5: 46207 | B5: 李小敏 | C5: 15070983360 | E5: 游泳三件套*1 | F5: 1
A6: 46207 | B6: 王若羲 | C6: 15398208259 | E6: 游泳三件套*1 | F6: 1
A7: 46214 | B7: 刘星岳 | C7: 18870870601 | E7: 瑜伽垫 | F7: 1
A8: 46214 | B8: 刘星牧 | C8: 18870870601 | E8: 吨吨杯 | F8: 1

Sheet 发票信息登记表
A1: 日期 | B1: 会员姓名 | C1: 联系方式 | D1: 发票抬头 | H1: 开票金额 | I1: 开票情况 | J1: 会员领取情况
D2: 开票名称 | E2: 开票税号 | F2: 开票地址、电话 | G2: 开票账户
A3: 46160 | B3: 熊婷 | C3: 18107910921
A4: 46163 | B4: 熊海燕 | C4: 18702511197
A5: 46210 | B5: 欧阳霞 | C5: 13732989511

Sheet 赠送
A1: 办卡日期 | B1: 会员 | C1: 手机 | D1: 收入类型 | E1: 卡名/课名 | F1: 次数/时效 | G1: 赠送部分 | H1: 实付金额 | I1: 备注

Sheet 礼品盘点表
A1: 礼品盘点表
A2: 礼品名称 | B2: 单位 | C2: 规格 | D2: 期初库存 | E2: 2024年9月 | F2: 2024年10月 | G2: 2024年11月 | H2: 2024年12月
E3: 本月库存量 | F3: 本月库存量 | G3: 本月库存量 | H3: 本月库存量 | I3: 本月库存量 | J3: 本月库存量

Sheet 电
A1: 日期 | B1: 总额 | C1: 表一 | D1: 表二
A2: 3.31 | B2: 6000
A3: 3.29 | C3: 1000 | D3: 500
A4: 4.2 | C4: 1000
A5: 4.7 | D5: 500
A6: 4.1 | C6: 1000
A7: 4.11 | D7: 500
A8: 4.17 | C8: 1000 | D8: 500
A9: 4.2 | D9: 500 | E9: 用完
A10: 4.22 | B10: 6000
A11: 4.23 | D11: 500
A12: 4.27 | C12: 500 | D12: 500
A13: 5.3 | C13: 500 | D13: 500
A14: 5.6 | D14: 500
A15: 5.9 | C15: 500 | D15: 500
A16: 5.13 | C16: 500 | D16: 500
A17: 5.16 | C17: 400 | D17: 600 | E17: 用完
A18: 5.19 | B18: 6000 | D18: 200
A19: 5.2 | C19: 200 | D19: 800
A20: 5.23 | C20: 500 | D20: 500
A21: 5.28 | C21: 500 | D21: 500
A22: 5.31 | C22: 300 | D22: 700
A23: 6.5 | C23: 300 | D23: 700
A24: 6.7 | D24: 1000
A25: 6.8 | C25: 500 | E25: -700
A26: 6.1 | B26: 6000
A27: 6.11 | C27: 1000 | D27: 1000
A28: 6.16 | D28: 1000
A29: 6.2 | D29: 500
A30: 6.22 | C30: 800 | D30: 1000 | E30: 用完
A31: 6.27 | B31: 6000 | C31: 500 | D31: 1500
A32: 7.2 | C32: 1000 | D32: 1000
A33: 7.5 | C33: 300 | D33: 1700 | E33: 用完
A34: 7.9 | B34: 6000
A35: 7.9 | C35: 500 | D35: 1500
A36: 7.12 | C36: 1000 | D36: 1000
A37: 7.14 | C37: 500 | D37: 1500 | E37: 用完
A38: 7.15 | C38: 500 | D38: 1500 | E38: -2000
A39: 7.17 | B39: 6000
A40: 7.21 | C40: 500 | D40: 1500
A41: 7.27 | C41: 500 | D41: 500
A42: 7.28 | B42: 6000 | D42: 1000 | E42: 用完
A43: 7.29 | C43: 1000
A44: 7.3 | C44: 500 | D44: 1500
A45: 8.2 | C45: 500 | D45: 1500 | E45: 用完
A46: 8.5 | B46: 6000 | C46: 500 | D46: 1500
A47: 12.8 | B47: 6000 | C47: 1000
A48: 12.14 | C48: 500 | D48: 500
A49: 12.18 | C49: 1500 | D49: 500
A50: 12.27 | C50: 500 | D50: 500
A51: 12.31 | C51: 500 | D51: 500 | E51: 用完
A52: 12.31 | B52: 6000
A53: 26.1.2 | C53: 1000
A54: 1.5 | D54: 1000
A55: 1.8 | C55: 1000
A56: 1.14 | C56: 400 | D56: 400
A57: 1.16 | C57: 800 | D57: 400
A58: 1.22 | C58: 1000 | D58: 1000 | E58: 用完-1000
A59: 1.27 | B59: 3000 | C59: 700 | D59: 300
A60: 2.3 | C60: 400 | D60: 600 | E60: 用完
A61: 2.3 | B61: 3000
A62: 2.28 | C62: 500 | D62: 500
A63: 3.7 | C63: 300 | D63: 300
A64: 3.1 | C64: 700 | D64: 700 | E64: 用完
A65: 3.13 | B65: 6000 | C65: 1000
A66: 3.19 | C66: 500 | D66: 500
A67: 3.23 | C67: 1000
A68: 3.28 | C68: 500 | D68: 500
A69: 26.4.2 | C69: 500
A70: 4.4 | D70: 500
A71: 4.7 | C71: 1000 | E71: 用完
A72: 4.7 | B72: 6000
A73: 4.11 | D73: 1000
A74: 4.14 | C74: 500
A75: 4.19 | C75: 500
A76: 4.23 | C76: 500 | D76: 500
A77: 4.28 | C77: 500
A78: 4.3 | C78: 1000 | D78: 500
A79: 5.7 | D79: 500
A80: 5.11 | B80: 6000 | C80: 500（用完） | D80: 500
A81: 5.14 | D81: 500
A82: 5.16 | C82: 500 | D82: 500
A83: 5.21 | C83: 1000 | D83: 1000
A84: 5.26 | D84: 1000
A85: 5.31 | C85: 500 | D85: 500 | E85: 用完
A86: 6.2 | B86: 6000
A87: 6.3 | C87: 500 | D87: 1000
A88: 6.7 | D88: 1000
A89: 6.9 | C89: 500 | D89: 1000
A90: 6.13 | C90: 500
A91: 6.18 | C91: 500 | D91: 1000 | E91: 用完
A92: 6.18 | B92: 6000
A93: 6.22 | C93: 1000 | D93: 1000
A94: 6.29 | C94: 500 | D94: 1000
A95: 7.3 | C95: 1000 | D95: 1000
A96: 7.6 | D96: 500 | E96: 用完
A97: 7.7 | B97: 6000
A98: 7.8 | C98: 1000 | D98: 1000
A99: 7.11 | D99: 1000
C105: =SUM(C36:C104) -> 31300 | D105: =SUM(D36:D104) -> 36200
...

Sheet 固定资产盘点表
A1: 固定资产盘点表
A2: 器械名称 | B2: 单位 | C2: 规格 | D2: 期初库存 | E2: 2024年9月 | F2: 2024年10月 | G2: 2024年11月 | H2: 2024年12月
E3: 本月库存量 | F3: 本月库存量 | G3: 本月库存量 | H3: 本月库存量 | I3: 本月库存量 | J3: 本月库存量
